Workbook

Sheet Raw Atomic Data (Pro)
A1: Participant | B1: Provider segment | C1: Category | D1: Theme | E1: Type | F1: Observation | G1: Quote | H1: First occurrence (participant x theme x type)
A2: Ami | B2: Pro | C2: Context and provider model | D2: provider-background | E2: fact | F2: She is 60 years old ("I am 60. I just turned 60, which was hard to believe.") and worked as a music teacher for 32 years before retiring. | G2: I am 60. I just turned 60, which was hard to believe. | H2: =IF(COUNTIFS($D$2:D2,D2,$E$2:E2,E2,$A$2:A2,A2)=1,1,0) -> 1
A3: Ami | B3: Pro | C3: Context and provider model | D3: provider-background | E3: fact | F3: She retired from teaching music and singing in 2024 after 32 years ("I retired um in 2024 and I taught for 32 years"). | G3: I retired um in 2024 and I taught for 32 years | H3: =IF(COUNTIFS($D$2:D3,D3,$E$2:E3,E3,$A$2:A3,A3)=1,1,0) -> 0
A4: Ami | B4: Pro | C4: Context and provider model | D4: provider-background | E4: fact | F4: She currently manages roughly 10 regular Rover clients by her own rough estimate, and at the time of the interview was only taking current/regular clients rather than accepting new ones ("I probably have maybe like I 10 like that's a rough estimate right now" and "at this point, I'm only doing taking, um, current clients. I'm not accepting new clients."). | G4: I probably have maybe like I 10 like that's a rough estimate right now | H4: =IF(COUNTIFS($D$2:D4,D4,$E$2:E4,E4,$A$2:A4,A4)=1,1,0) -> 0
A5: Ami | B5: Pro | C5: Context and provider model | D5: business-model-fit | E5: fact | F5: Pet sitting fits within her retirement schedule; she describes the workload as sporadic, with busy spurts followed by lulls, and says a typical day has anywhere from about two to six visits ("it fits within a retirement schedule really well"; "it's also very sporadic like sometimes I'll get really really busy and then I get a little bit a lull and then I get really busy and then a lull"; "I'll have anywhere from like two to two to six visits the most"). | G5: it fits within a retirement schedule really well | H5: =IF(COUNTIFS($D$2:D5,D5,$E$2:E5,E5,$A$2:A5,A5)=1,1,0) -> 1
A6: Ami | B6: Pro | C6: Context and provider model | D6: provider-background | E6: fact | F6: She is married with three kids and currently owns two dogs and a cat of her own ("I have two dogs and a cat" and "my three kids, my husband"). | G6: I have two dogs and a cat | H6: =IF(COUNTIFS($D$2:D6,D6,$E$2:E6,E6,$A$2:A6,A6)=1,1,0) -> 0
A7: Ami | B7: Pro | C7: Context and provider model | D7: business-model-fit | E7: value-statement | F7: Before starting on Rover, she originally planned to launch her own independent pet-sitting business, saying she thought she'd "build a, you know, a Google survey" and put out "business cards and I'll put that around my neighborhood" ("I originally was going to try to do something like that on my own"), but decided to start with Rover first, and only after doing so did she realize Rover already offered the organizational setup she would have had to build herself, which is why she stuck with it ("I think I'll just I'll start with Rover"; "then then I realized that it it was easier just to I like the way Rover was set up because I didn't have to do all of that"). | G7: I originally was going to try to do something like that on my own | H7: =IF(COUNTIFS($D$2:D7,D7,$E$2:E7,E7,$A$2:A7,A7)=1,1,0) -> 1
A8: Ami | B8: Pro | C8: Context and provider model | D8: onboarding-signup-process | E8: value-statement | F8: She says the background check requirement was part of what convinced her to stick with Rover, since it matched the kind of screening she was used to from her teaching career ("I think the fact that uh they wanted to do a background check which was great because you know coming out of teaching I was used to having that you know kind of screening being done which I thought was good"). | G8: I think the fact that uh they wanted to do a background check which was great because you know coming out of teaching I was used to having that you know kind of screening being done which I thought was good | H8: =IF(COUNTIFS($D$2:D8,D8,$E$2:E8,E8,$A$2:A8,A8)=1,1,0) -> 1
A9: Ami | B9: Pro | C9: Context and provider model | D9: onboarding-signup-process | E9: value-statement | F9: She found account setup easy and, once her background check and approval went through, quickly received her first booking request from what she calls her first clients, the "OGs" ("it was pretty easy to get get on to it"; "I pretty quickly got a request uh from my uh uh first I call them the OGs, my first clients"). | G9: I pretty quickly got a request uh from my uh uh first I call them the OGs, my first clients | H9: =IF(COUNTIFS($D$2:D9,D9,$E$2:E9,E9,$A$2:A9,A9)=1,1,0) -> 0
A10: Andrew | B10: Pro | C10: Context and provider model | D10: business-model-fit | E10: fact | F10: Drew is a video editor by trade who has been doing Rover for about a year to a year and a half to supplement his income as film work slows down ("I've been doing Rover for a little bit over a year now. Uh just as a way to supplement my income because the industry is I think wrapping up uh in terms of film making"). | G10: I've been doing Rover for a little bit over a year now. Uh just as a way to supplement my income because the industry is I think wrapping up uh in terms of film making | H10: =IF(COUNTIFS($D$2:D10,D10,$E$2:E10,E10,$A$2:A10,A10)=1,1,0) -> 1
A11: Andrew | B11: Pro | C11: Context and provider model | D11: provider-background | E11: fact | F11: His services are boarding and doggy daycare, with boarding making up almost all of his business ("I do do boarding and um and doggy daycare, but it's it's almost 99%"). | G11: I do do boarding and um and doggy daycare, but it's it's almost 99% | H11: =IF(COUNTIFS($D$2:D11,D11,$E$2:E11,E11,$A$2:A11,A11)=1,1,0) -> 1
A12: Andrew | B12: Pro | C12: Context and provider model | D12: capacity-multi-pet-management | E12: fact | F12: He currently caps his capacity at two dogs at a time in addition to his own, occasionally taking a third for an emergency booking ("right now I take two dogs at a time"; "every once in a while, you know, if if there's a emergency booking, I'll take a third"). | G12: right now I take two dogs at a time | H12: =IF(COUNTIFS($D$2:D12,D12,$E$2:E12,E12,$A$2:A12,A12)=1,1,0) -> 1
A13: Andrew | B13: Pro | C13: Context and provider model | D13: provider-background | E13: fact | F13: In the month before the interview he was almost continuously booked, likely due to the start of summer travel season ("the last month I have been almost completely booked. I've had probably three or four days without at least one dog here"). | G13: the last month I have been almost completely booked. I've had probably three or four days without at least one dog here | H13: =IF(COUNTIFS($D$2:D13,D13,$E$2:E13,E13,$A$2:A13,A13)=1,1,0) -> 0
... A25: Anita | B25: Pro | C25: Context and provider model | D25: business-model-fit | E25: fact | F25: She describes her Rover income as essential to her finances, covering her rent and bills ("It's keeping me in this tiny apartment. It's helping me pay my bills. I absolutely need it."). | G25: It's keeping me in this tiny apartment. It's helping me pay my bills. I absolutely need it. | H25: =IF(COUNTIFS($D$2:D25,D25,$E$2:E25,E25,$A$2:A25,A25)=1,1,0) -> 1
A26: Anita | B26: Pro | C26: Context and provider model | D26: provider-background | E26: fact | F26: Her active client count fluctuates seasonally, from a high of six simultaneous households around one Christmas down to just one or two clients during a slow summer. | H26: =IF(COUNTIFS($D$2:D26,D26,$E$2:E26,E26,$A$2:A26,A26)=1,1,0) -> 0
A27: Anita | B27: Pro | C27: Context and provider model | D27: repeat-client-relationships | E27: fact | F27: One dog in her routine care, Boo, is technically a former client's dog who now lives with her full-time because his owner had a stroke and is currently in a care facility ("He's one of my dogs, but his mom had um strokes, so now I'm taking care of him full-time because she's in care."). | G27: He's one of my dogs, but his mom had um strokes, so now I'm taking care of him full-time because she's in care. | H27: =IF(COUNTIFS($D$2:D27,D27,$E$2:E27,E27,$A$2:A27,A27)=1,1,0) -> 1
A28: Becky | B28: Pro | C28: Context and provider model | D28: provider-background | E28: fact | F28: She says she is 36 years old ("I I'm still I'm 36"). | G28: I I'm still I'm 36 | H28: =IF(COUNTIFS($D$2:D28,D28,$E$2:E28,E28,$A$2:A28,A28)=1,1,0) -> 1
A29: Becky | B29: Pro | C29: Context and provider model | D29: provider-background | E29: fact | F29: She says she has been using Rover for about two years, though stated with hedging ("I've been using Rover for two years, I think."). | G29: I've been using Rover for two years, I think. | H29: =IF(COUNTIFS($D$2:D29,D29,$E$2:E29,E29,$A$2:A29,A29)=1,1,0) -> 0
A30: Becky | B30: Pro | C30: Context and provider model | D30: provider-background | E30: fact | F30: She immediately added further uncertainty about that length, saying it might actually be three years ("Maybe three, I don't know."). | G30: Maybe three, I don't know. | H30: =IF(COUNTIFS($D$2:D30,D30,$E$2:E30,E30,$A$2:A30,A30)=1,1,0) -> 0
A31: Becky | B31: Pro | C31: Context and provider model | D31: provider-background | E31: fact | F31: She says she is still working from home, a setup that has continued since COVID ("I'm still working from home after COVID time."). | G31: I'm still working from home after COVID time. | H31: =IF(COUNTIFS($D$2:D31,D31,$E$2:E31,E31,$A$2:A31,A31)=1,1,0) -> 0
A32: Becky | B32: Pro | C32: Context and provider model | D32: provider-background | E32: fact | F32: Before Rover, her pet-sitting experience was informal — watching her parents' or friends' dogs when they traveled ("I had done like my parents when they would go out of town I would watch their dogs or like their friends or something. Nothing too elaborate"). | G32: I had done like my parents when they would go out of town I would watch their dogs or like their friends or something. Nothing too elaborate | H32: =IF(COUNTIFS($D$2:D32,D32,$E$2:E32,E32,$A$2:A32,A32)=1,1,0) -> 0
A33: Becky | B33: Pro | C33: Context and provider model | D33: provider-background | E33: fact | F33: She says having a dog at her house, or being at someone else's, has become a frequent occurrence for her ("now I have a dog most mo more times than not I have a dog at my house or I'm at someone else."). | G33: now I have a dog most mo more times than not I have a dog at my house or I'm at someone else. | H33: =IF(COUNTIFS($D$2:D33,D33,$E$2:E33,E33,$A$2:A33,A33)=1,1,0) -> 0
A34: Becky | B34: Pro | C34: Context and provider model | D34: business-model-fit | E34: fact | F34: She says the concentration of her bookings in boarding is driven by demand rather than her own preference ("it's not because I have a preference. It's just because that's what gets booked more often."). | G34: it's not because I have a preference. It's just because that's what gets booked more often. | H34: =IF(COUNTIFS($D$2:D34,D34,$E$2:E34,E34,$A$2:A34,A34)=1,1,0) -> 1
A35: Becky | B35: Pro | C35: Context and provider model | D35: motivation-emotional-connection | E35: value-statement | F35: Asked directly about her own preference, though, she says she actually prefers overnight boarding and house-sitting over dog-walking because she doesn't have to travel back and forth as much ("it's actually much I prefer to have like the overnight sitting, the boarding or and I'm housesitting because then I don't have to drag so much. I'm just like wherever I am."). | G35: it's actually much I prefer to have like the overnight sitting, the boarding or and I'm housesitting because then I don't have to drag so much. I'm just like wherever I am. | H35: =IF(COUNTIFS($D$2:D35,D35,$E$2:E35,E35,$A$2:A35,A35)=1,1,0) -> 1
A36: Becky | B36: Pro | C36: Context and provider model | D36: provider-background | E36: fact | F36: She had expected significantly more dog-walking requests when she first signed up than she has actually received ("I thought when I first signed up, I was expecting a lot more dog walking."). | G36: I thought when I first signed up, I was expecting a lot more dog walking. | H36: =IF(COUNTIFS($D$2:D36,D36,$E$2:E36,E36,$A$2:A36,A36)=1,1,0) -> 0
A37: Becky | B37: Pro | C37: Context and provider model | D37: business-model-fit | E37: fact | F37: She says her boss was aware that she does dog sitting and that this wasn't a problem ("My boss um was aware of that I dog sitting. She's a big dog person, so it was not it wasn't at all."). | G37: My boss um was aware of that I dog sitting. She's a big dog person, so it was not it wasn't at all. | H37: =IF(COUNTIFS($D$2:D37,D37,$E$2:E37,E37,$A$2:A37,A37)=1,1,0) -> 0
A38: Becky | B38: Pro | C38: Context and provider model | D38: business-model-fit | E38: fact | F38: She describes fitting sitting into her work schedule as more a matter of working around her meetings than an actual problem, and says it didn't affect the quality of her work ("it was more like working around my meetings, but it didn't impact the quality of my work."). | G38: it was more like working around my meetings, but it didn't impact the quality of my work. | H38: =IF(COUNTIFS($D$2:D38,D38,$E$2:E38,E38,$A$2:A38,A38)=1,1,0) -> 0
... A67: Erika | B67: Pro | C67: Context and provider model | D67: provider-background | E67: fact | F67: She now has a baby, which is part of her current household context ("I also have a baby"). | G67: I also have a baby | H67: =IF(COUNTIFS($D$2:D67,D67,$E$2:E67,E67,$A$2:A67,A67)=1,1,0) -> 0
A68: Erika | B68: Pro | C68: Context and provider model | D68: client-dog-screening-criteria | E68: fact | F68: Her living situation also shapes which bookings she can take: she rents her home under a landlord agreement restricting her to small- or medium-sized pets (see Evaluation and meet-and-greet for the full detail and quote). | H68: =IF(COUNTIFS($D$2:D68,D68,$E$2:E68,E68,$A$2:A68,A68)=1,1,0) -> 1
A69: Erika | B69: Pro | C69: Context and provider model | D69: repeat-client-relationships | E69: fact | F69: She has a base of regular clients, though she says the balance has recently shifted toward new clients ("I have a couple of regular clients"). | G69: I have a couple of regular clients | H69: =IF(COUNTIFS($D$2:D69,D69,$E$2:E69,E69,$A$2:A69,A69)=1,1,0) -> 1
A70: Erika | B70: Pro | C70: Context and provider model | D70: provider-background | E70: fact | F70: Her Rover profile also has drop-in visits and daycare activated, but boarding -- pets staying with her for scheduled days or nights -- is the service type she says she has done most ("the most common one is the boarding one. That is the one that they spend some days or some nights here as like schedule times... so that's the most common and to be honest that's the one that I mostly have done so far"). | G70: the most common one is the boarding one. That is the one that they spend some days or some nights here as like schedule times... so that's the most common and to be honest that's the one that I mostly have done so far | H70: =IF(COUNTIFS($D$2:D70,D70,$E$2:E70,E70,$A$2:A70,A70)=1,1,0) -> 0
A71: Erika | B71: Pro | C71: Context and provider model | D71: client-acquisition-discovery | E71: fact | F71: In roughly the three to four months before the interview she noticed a sharp rise in new clients on top of her existing regulars ("I've noticed that in this last I don't know like maybe three" ... "to four months I've gotten lots of new" [pets]). | G71: to four months I've gotten lots of new | H71: =IF(COUNTIFS($D$2:D71,D71,$E$2:E71,E71,$A$2:A71,A71)=1,1,0) -> 1
A72: Kristin | B72: Pro | C72: Context and provider model | D72: business-model-fit | E72: fact | F72: She did Rover full-time until April, then returned to her full-time day job and is now doing Rover part-time again ("I had been doing Rover full-time. um up until April."). | G72: I had been doing Rover full-time. um up until April. | H72: =IF(COUNTIFS($D$2:D72,D72,$E$2:E72,E72,$A$2:A72,A72)=1,1,0) -> 1
A73: Kristin | B73: Pro | C73: Context and provider model | D73: provider-background | E73: fact | F73: Her full-time day job is on the administrative side of the emergency field, which she describes as less stressful than the facility-based role she previously had in the same field ("it's on the admin side and I don't deal with it in the facility"). | G73: it's on the admin side and I don't deal with it in the facility | H73: =IF(COUNTIFS($D$2:D73,D73,$E$2:E73,E73,$A$2:A73,A73)=1,1,0) -> 1
A74: Kristin | B74: Pro | C74: Context and provider model | D74: business-model-fit | E74: fact | F74: Roughly 90% of her pet-sitting income comes through Rover, with the rest from private clients found through word of mouth, Facebook, and NextDoor ("90% of my petsitting income off Rover."). | G74: 90% of my petsitting income off Rover. | H74: =IF(COUNTIFS($D$2:D74,D74,$E$2:E74,E74,$A$2:A74,A74)=1,1,0) -> 0
A75: Kristin | B75: Pro | C75: Context and provider model | D75: provider-background | E75: fact | F75: Her active client base includes "approximately six or seven like weekly clients" plus an estimated 60-100 intermittent yearly clients who book around vacations. | G75: approximately six or seven like weekly clients | H75: =IF(COUNTIFS($D$2:D75,D75,$E$2:E75,E75,$A$2:A75,A75)=1,1,0) -> 0
A76: Kristin | B76: Pro | C76: Context and provider model | D76: provider-background | E76: fact | F76: She is engaged and has her own dogs at home, which come up as part of her daily life during the interview itself ("my dog and dogs are going to start barking and my fiance's getting ready for work."). | G76: my dog and dogs are going to start barking and my fiance's getting ready for work. | H76: =IF(COUNTIFS($D$2:D76,D76,$E$2:E76,E76,$A$2:A76,A76)=1,1,0) -> 0
A77: Kristin | B77: Pro | C77: Context and provider model | D77: provider-background | E77: fact | F77: She recently had surgery, which affected her capacity to work ("I've just recently had surgery"). | G77: I've just recently had surgery | H77: =IF(COUNTIFS($D$2:D77,D77,$E$2:E77,E77,$A$2:A77,A77)=1,1,0) -> 0
A78: Kristin | B78: Pro | C78: Context and provider model | D78: motivation-emotional-connection | E78: value-statement | F78: She describes herself as a very busy person who likes it that way, juggling dog walks and drop-ins around her full-time job plus overnight house-sits ("Yeah. Yeah. I'm a very busy person. I like being busy."). | G78: Yeah. Yeah. I'm a very busy person. I like being busy. | H78: =IF(COUNTIFS($D$2:D78,D78,$E$2:E78,E78,$A$2:A78,A78)=1,1,0) -> 1
A79: Naomi | B79: Pro | C79: Context and provider model | D79: provider-background | E79: fact | F79: She is a Pro-segment Rover provider based in the Bronx, New York City, running her boarding operation out of a home with a large yard that she bought after leaving the tech industry ("I bought a home in the Bronx and so the home has a large yard"). | G79: I bought a home in the Bronx and so the home has a large yard | H79: =IF(COUNTIFS($D$2:D79,D79,$E$2:E79,E79,$A$2:A79,A79)=1,1,0) -> 1
A80: Naomi | B80: Pro | C80: Context and provider model | D80: business-model-fit | E80: fact | F80: Rover is one part of several income streams she runs from that property, alongside tenants, an Airbnb, personal training, and teaching Muay Thai and yoga ("I have a few different streams of income... I have tenants and Airbnb rover and I'm a personal trainer and I teach uh Muay Thai and yoga"). | G80: I have a few different streams of income... I have tenants and Airbnb rover and I'm a personal trainer and I teach uh Muay Thai and yoga | H80: =IF(COUNTIFS($D$2:D80,D80,$E$2:E80,E80,$A$2:A80,A80)=1,1,0) -> 1
... A174: Shania | B174: Pro | C174: Motivation | D174: motivation-emotional-connection | E174: value-statement | F174: Getting a new booking notification gives her a small emotional lift and a sense of satisfaction from providing the service, even though sitting isn't a major part of her daily life: "when I received a notification from it, I just I get a little excited... it's just a good feeling to... provide [services]." | G174: I just I get a little excited | H174: =IF(COUNTIFS($D$2:D174,D174,$E$2:E174,E174,$A$2:A174,A174)=1,1,0) -> 0
A175: Tianrui | B175: Pro | C175: Motivation | D175: business-model-fit | E175: fact | F175: A primary motivation for joining Rover was earning supplemental income while not working full-time and applying to grad school. | H175: =IF(COUNTIFS($D$2:D175,D175,$E$2:E175,E175,$A$2:A175,A175)=1,1,0) -> 0
A176: Tianrui | B176: Pro | C176: Motivation | D176: motivation-emotional-connection | E176: fact | F176: TR's shelter-fostering background gave them confidence in cat care, which factored into wanting to care for other people's cats ("I think I know a lot about cat caring"). | G176: I think I know a lot about cat caring | H176: =IF(COUNTIFS($D$2:D176,D176,$E$2:E176,E176,$A$2:A176,A176)=1,1,0) -> 0
A177: Tianrui | B177: Pro | C177: Motivation | D177: motivation-emotional-connection | E177: value-statement | F177: Being around animals makes TR feel needed and important, since the animals rely on them ("being with animals making me feel like I have some little beings that's relying on me and then making me feel like uh I'm really important to them"). | G177: being with animals making me feel like I have some little beings that's relying on me and then making me feel like uh I'm really important to them | H177: =IF(COUNTIFS($D$2:D177,D177,$E$2:E177,E177,$A$2:A177,A177)=1,1,0) -> 0
A178: Tianrui | B178: Pro | C178: Motivation | D178: motivation-emotional-connection | E178: value-statement | F178: TR says having animals to care for makes them feel less alone in their apartment, since they have their partner and now also an animal to look after ("feels like I'm no longer alone in having apartments always my partner and I have someone else to take care of"). | G178: feels like I'm no longer alone in having apartments always my partner and I have someone else to take care of | H178: =IF(COUNTIFS($D$2:D178,D178,$E$2:E178,E178,$A$2:A178,A178)=1,1,0) -> 0
A179: Tianrui | B179: Pro | C179: Motivation | D179: motivation-emotional-connection | E179: value-statement | F179: For TR, what they get back from animals personally is described as companionship — simply being physically close ("more like companionship like just be next to me and just sleeping next to me something like that"). | G179: more like companionship like just be next to me and just sleeping next to me something like that | H179: =IF(COUNTIFS($D$2:D179,D179,$E$2:E179,E179,$A$2:A179,A179)=1,1,0) -> 0
A180: Tianrui | B180: Pro | C180: Motivation | D180: motivation-emotional-connection | E180: fact | F180: TR describes their own temperament, using a cat metaphor, as preferring solitude but choosing to engage occasionally on their own terms, contrasting this with the constant demands of dogs ("I want to be the cat more of my loner... occasionally when I want to, I go to the person instead of like a dog"). | G180: I want to be the cat more of my loner | H180: =IF(COUNTIFS($D$2:D180,D180,$E$2:E180,E180,$A$2:A180,A180)=1,1,0) -> 0
A181: Tifany | B181: Pro | C181: Motivation | D181: motivation-emotional-connection | E181: fact | F181: She entered pet sitting somewhat by accident: a pastor friend asked her to housesit for 23 days while he traveled, and being paid to stay at his house and care for his dogs made her reconsider it as real work ('I got asked by a friend um to watch their house and their pets for 23 days when they went to Jerusalem'; 'Hey, that was actually really nice. Like, you know, I got paid to stay at your house and, you know, feed your dogs and hang out with your dogs'). | G181: Hey, that was actually really nice. Like, you know, I got paid to stay at your house and, you know, feed your dogs and hang out with your dogs | H181: =IF(COUNTIFS($D$2:D181,D181,$E$2:E181,E181,$A$2:A181,A181)=1,1,0) -> 1
A182: Tifany | B182: Pro | C182: Motivation | D182: provider-background | E182: fact | F182: Before that first paid housesit, she had already informally watched pets for family and friends for years, including her mother's dogs and other people's cats, without thinking of it as a side gig until her mother told her about Rover ('I had already like done it. Um, but I just didn't I didn't know about it as like a side gig um until my mom was telling me about Rover'). | G182: I had already like done it. Um, but I just didn't I didn't know about it as like a side gig um until my mom was telling me about Rover | H182: =IF(COUNTIFS($D$2:D182,D182,$E$2:E182,E182,$A$2:A182,A182)=1,1,0) -> 0
A183: Tifany | B183: Pro | C183: Motivation | D183: onboarding-signup-process | E183: fact | F183: Her mother, who was already using Rover, suggested she formalize the work on the platform after hearing about that housesit ('my mom was like, Yeah, you should get on Rover'). | G183: my mom was like, Yeah, you should get on Rover | H183: =IF(COUNTIFS($D$2:D183,D183,$E$2:E183,E183,$A$2:A183,A183)=1,1,0) -> 1
A184: Tifany | B184: Pro | C184: Motivation | D184: motivation-emotional-connection | E184: value-statement | F184: On a personal level, she values animals because they don't make the kind of relational demands people do, which fits how she describes her own personality as roughly half extroverted, half introverted ('I enjoy animals because they don't talk or need anything from me like relationally, you know, like I get to go be with them and they're next to me or they want attention, but I don't have to like chat all day'). | G184: I enjoy animals because they don't talk or need anything from me like relationally, you know, like I get to go be with them and they're next to me or they want attention, but I don't have to like chat all day | H184: =IF(COUNTIFS($D$2:D184,D184,$E$2:E184,E184,$A$2:A184,A184)=1,1,0) -> 1
A185: Tifany | B185: Pro | C185: Motivation | D185: motivation-emotional-connection | E185: fact | F185: She explicitly resists giving what she calls the sentimental 'pretty answer' about loving animals, framing her connection to them as more practical after years of doing the work ('I think people really want like a really pretty answer like, Oh, I love animals... and because I think it's because I've been doing it so long... I just like certain things about animals that are not like people'). | G185: I think people really want like a really pretty answer like, Oh, I love animals | H185: =IF(COUNTIFS($D$2:D185,D185,$E$2:E185,E185,$A$2:A185,A185)=1,1,0) -> 0
A186: Tifany | B186: Pro | C186: Motivation | D186: motivation-emotional-connection | E186: value-statement | F186: She admires loyalty in dogs, especially herding breeds like Australian Shepherds, which are initially standoffish with her but become devoted after repeated stays, and says she'd want to be that kind of dog herself ('they end up becoming my favorite and they really loyal to me after we've stayed for a while'; 'I would be one of them. Uh, just because I want to be loyal'). | G186: I would be one of them. Uh, just because I want to be loyal | H186: =IF(COUNTIFS($D$2:D186,D186,$E$2:E186,E186,$A$2:A186,A186)=1,1,0) -> 0
A187: Tifany | B187: Pro | C187: Motivation | D187: motivation-emotional-connection | E187: fact | F187: When first asked what comes to mind about dog sitting in general, her immediate association is work/task rather than an emotional response ('work that's what comes to mind. I think okay I have another task'). | G187: work that's what comes to mind. I think okay I have another task | H187: =IF(COUNTIFS($D$2:D187,D187,$E$2:E187,E187,$A$2:A187,A187)=1,1,0) -> 0
... A459: Colin | B459: Pro | C459: Sitting preparation | D459: care-instructions-handoff | E459: fact | F459: By the time a job actually starts, it's rare for anything pressing or unexpected to come up, aside from occasional things like a dog eating something unusual ("by the time the job comes around, it's pretty rare that anything pressing comes up, you know, unless a dog eats something weird"). | G459: by the time the job comes around, it's pretty rare that anything pressing comes up | H459: =IF(COUNTIFS($D$2:D459,D459,$E$2:E459,E459,$A$2:A459,A459)=1,1,0) -> 0
A460: Dawn | B460: Pro | C460: Sitting preparation | D460: care-instructions-handoff | E460: fact | F460: Not discussed in this interview. | H460: =IF(COUNTIFS($D$2:D460,D460,$E$2:E460,E460,$A$2:A460,A460)=1,1,0) -> 0
A461: Erika | B461: Pro | C461: Sitting preparation | D461: care-instructions-handoff | E461: fact | F461: Not discussed in this interview. | H461: =IF(COUNTIFS($D$2:D461,D461,$E$2:E461,E461,$A$2:A461,A461)=1,1,0) -> 0
A462: Kristin | B462: Pro | C462: Sitting preparation | D462: care-instructions-handoff | E462: workaround | F462: For bookings made well in advance, she reaches out seven days prior to confirm there have been no food, medication, or bathroom-routine changes, since conditions can shift quickly for elderly pets or puppies ("I'll reach out to the client seven days prior to the booking and like touch base with them to make sure there's no changes cuz sometimes like elderly dogs there's like a lot of changes or like puppies there's a lot of changes cuz there's a lot of growth in between. So sometimes there's food changes, medication changes, um, bathroom type changes."). | G462: I'll reach out to the client seven days prior to the booking and like touch base with them to make sure there's no changes cuz sometimes like elderly dogs there's like a lot of changes or like puppies there's a lot of changes cuz there's a lot of growth in between. So sometimes there's food changes, medication changes, um, bathroom type changes. | H462: =IF(COUNTIFS($D$2:D462,D462,$E$2:E462,E462,$A$2:A462,A462)=1,1,0) -> 1
A463: Kristin | B463: Pro | C463: Sitting preparation | D463: care-instructions-handoff | E463: fact | F463: As part of that pre-sit check-in, she arranges a "way to pick up the key if I haven't already gotten the key.", and asks about door or garage codes. | G463: way to pick up the key if I haven't already gotten the key. | H463: =IF(COUNTIFS($D$2:D463,D463,$E$2:E463,E463,$A$2:A463,A463)=1,1,0) -> 0
A464: Kristin | B464: Pro | C464: Sitting preparation | D464: care-instructions-handoff | E464: fact | F464: She asks clients to leave a hidden backup key somewhere on the property even if she already has a key or a code, in case "batteries die, electricity goes out, that sort of thing just to make sure that there's a way to get into the house." | G464: batteries die, electricity goes out, that sort of thing just to make sure that there's a way to get into the house. | H464: =IF(COUNTIFS($D$2:D464,D464,$E$2:E464,E464,$A$2:A464,A464)=1,1,0) -> 0
A465: Naomi | B465: Pro | C465: Sitting preparation | D465: capacity-multi-pet-management | E465: fact | F465: She has been reconfiguring her home's layout and buying additional crates so she can safely keep dogs who don't know each other separated as she takes on more dogs ("I'm more so refiguring out where I'm keeping everyone because they don't know each other, so they need to be separate"). | G465: I'm more so refiguring out where I'm keeping everyone because they don't know each other, so they need to be separate | H465: =IF(COUNTIFS($D$2:D465,D465,$E$2:E465,E465,$A$2:A465,A465)=1,1,0) -> 0
A466: Naomi | B466: Pro | C466: Sitting preparation | D466: capacity-multi-pet-management | E466: fact | F466: She has been shifting toward smaller crates because the dogs she is currently taking skew smaller than the big dogs she used to have ("in the past I had a lot of big dogs, so I bought big crates and now I'm sort of using a smaller area of my home, so I might not be having as many big dogs"). | G466: in the past I had a lot of big dogs, so I bought big crates and now I'm sort of using a smaller area of my home, so I might not be having as many big dogs | H466: =IF(COUNTIFS($D$2:D466,D466,$E$2:E466,E466,$A$2:A466,A466)=1,1,0) -> 0
A467: Shania | B467: Pro | C467: Sitting preparation | D467: care-instructions-handoff | E467: fact | F467: Care-related logistics for a specific home (such as how something works or is accessed) get communicated to her ahead of time by the client where possible; for one long-term client's house sit, she was told in advance that the water sometimes needed to be manually pumped from downstairs. "I had a three-day house sit with the the same lady that books me full-time right but one time her water wasn't really working so I had to go downstairs and uh manually pump the water through the pipes right so that was... something that she let me know of ahead of time." | G467: one time her water wasn't really working so I had to go downstairs and uh manually pump the water through the pipes | H467: =IF(COUNTIFS($D$2:D467,D467,$E$2:E467,E467,$A$2:A467,A467)=1,1,0) -> 0
A468: Shania | B468: Pro | C468: Sitting preparation | D468: care-instructions-handoff | E468: fact | F468: When she is unsure whether she's allowed to do something in a client's home, she checks with the owner directly rather than assuming: "I asked her if like it was good for me to do certain things at home and she was like, 'Yeah, you know, it's not crazy.'" | G468: I asked her if like it was good for me to do certain things at home | H468: =IF(COUNTIFS($D$2:D468,D468,$E$2:E468,E468,$A$2:A468,A468)=1,1,0) -> 0
A469: Shania | B469: Pro | C469: Sitting preparation | D469: care-instructions-handoff | E469: fact | F469: Most preparation-related information (what she'll need to know to do the job) surfaces first during the meet-and-greet and continues to be confirmed through the booking itself: "everything kind of just gets uh in the meet and greet and then follow through into the booking." | G469: everything kind of just gets uh in the meet and greet and then follow through into the booking | H469: =IF(COUNTIFS($D$2:D469,D469,$E$2:E469,E469,$A$2:A469,A469)=1,1,0) -> 0
A470: Tianrui | B470: Pro | C470: Sitting preparation | D470: care-instructions-handoff | E470: value-statement | F470: Some clients bring a printed handout of care instructions, which TR finds helpful, while others go through the information verbally or by text message ("some clients will bring a print out. Um so that's maybe helpful and some clients they just like verbally going through everything like send me a text message"). | G470: some clients will bring a print out. Um so that's maybe helpful and some clients they just like verbally going through everything like send me a text message | H470: =IF(COUNTIFS($D$2:D470,D470,$E$2:E470,E470,$A$2:A470,A470)=1,1,0) -> 1
A471: Tianrui | B471: Pro | C471: Sitting preparation | D471: profile-information-completeness | E471: friction | F471: TR doesn't usually use Rover's own care-instructions fields on the profile, finding the layout not user-friendly, and instead relies on reading the owner's text messages directly ("the information layouts was a bit not that friendly... I usually I don't click on that... I just look at the owner's text message because I think the text message is actually better for me to read"). | G471: the information layouts was a bit not that friendly | H471: =IF(COUNTIFS($D$2:D471,D471,$E$2:E471,E471,$A$2:A471,A471)=1,1,0) -> 1
A472: Tifany | B472: Pro | C472: Sitting preparation | D472: care-instructions-handoff | E472: fact | F472: During meet-and-greets she goes through a mental checklist of practical items with the client, including what to do in case of an emergency ('when I'm doing a meet and greet I make sure that we go through all sorts of lists of things right like hey you know what if there's an emergency'). | G472: when I'm doing a meet and greet I make sure that we go through all sorts of lists of things right like hey you know what if there's an emergency | H472: =IF(COUNTIFS($D$2:D472,D472,$E$2:E472,E472,$A$2:A472,A472)=1,1,0) -> 1
A473: Tifany | B473: Pro | C473: Sitting preparation | D473: care-instructions-handoff | E473: fact | F473: She keeps no written spreadsheet or checklist of intake questions or care instructions, relying instead on a mental list of what to watch for and ask ('I don't have a spreadsheet... it's mostly just like knowing what I will and won't accept'). | G473: I don't have a spreadsheet | H473: =IF(COUNTIFS($D$2:D473,D473,$E$2:E473,E473,$A$2:A473,A473)=1,1,0) -> 0
... A532: Shania | B532: Pro | C532: Service delivery | D532: provider-background | E532: fact | F532: Her services are mostly dog walking and house-sitting, and she has also done drop-in visits and cared for a cat once last year: "it's mostly dogs. I have done cats one time" (last year), and "they were both dog walking" for her earliest bookings. | G532: it's mostly dogs. I have done cats one time | H532: =IF(COUNTIFS($D$2:D532,D532,$E$2:E532,E532,$A$2:A532,A532)=1,1,0) -> 0
A533: Shania | B533: Pro | C533: Service delivery | D533: daily-care-tasks | E533: workaround | F533: During a house sit, she handled an on-site issue by improvising within what the owner had permitted, manually pumping water through the pipes when the water wasn't working, after having been told in advance this could happen. | H533: =IF(COUNTIFS($D$2:D533,D533,$E$2:E533,E533,$A$2:A533,A533)=1,1,0) -> 1
A534: Shania | B534: Pro | C534: Service delivery | D534: repeat-client-relationships | E534: friction | F534: She managed a difficult long-duration drop-in visit case: a client who was away in Texas for about three months did not clearly communicate her return date, initially saying she'd be back at the end of June but not actually returning until early August. "she was in Texas for about um 3 months... she said she was going to come back at the end of June, right? So, just a weird situation." | G534: she said she was going to come back at the end of June, right? So, just a weird situation | H534: =IF(COUNTIFS($D$2:D534,D534,$E$2:E534,E534,$A$2:A534,A534)=1,1,0) -> 1
A535: Shania | B535: Pro | C535: Service delivery | D535: sitter-support-resources | E535: fact | F535: She contacted Rover support during that situation to get a clear answer from the client about her return date. When the interviewer suggested she "had to expand her sitting service," Shania corrected that framing — she says the change was to her rate, not the scope of care she provided (see Payments and earnings for the rate change itself): "I had to uh well not expand the [sitting] service." | G535: I had to uh well not expand the | H535: =IF(COUNTIFS($D$2:D535,D535,$E$2:E535,E535,$A$2:A535,A535)=1,1,0) -> 1
A536: Shania | B536: Pro | C536: Service delivery | D536: repeat-client-relationships | E536: fact | F536: She felt the client in that situation expected an open-ended booking, which she contrasts with her own view that every booking needs a defined end: "she kind of expected a uh like indefinite at booking. But you know, every booking needs to have an end." | G536: every booking needs to have an end | H536: =IF(COUNTIFS($D$2:D536,D536,$E$2:E536,E536,$A$2:A536,A536)=1,1,0) -> 0
A537: Shania | B537: Pro | C537: Service delivery | D537: sitter-support-resources | E537: value-statement | F537: Rover support contacted the client on her behalf and sent a message that created a sense of urgency, prompting a faster reply than the client's usual full-day response time, though the client reportedly worried something bad had happened: "they sent a message through my channel to her and then uh she had thought that something had happened to her. Right. But uh it was just kind of to give her a sense of urgency because like normally she was taking a whole day to reply to my messages." | G537: they sent a message through my channel to her and then uh she had thought that something had happened to her | H537: =IF(COUNTIFS($D$2:D537,D537,$E$2:E537,E537,$A$2:A537,A537)=1,1,0) -> 1
A538: Shania | B538: Pro | C538: Service delivery | D538: sitter-support-resources | E538: fact | F538: She describes Rover's support as having done what it reasonably could given it's a remote/virtual service, without fully resolving the underlying situation on its own: "they did the best that they could like you know because they were um you know as a virtual customer service like there's so much you can do for that situation." | G538: they did the best that they could like you know because they were um you know as a virtual customer service like there's so much you can do for that situation | H538: =IF(COUNTIFS($D$2:D538,D538,$E$2:E538,E538,$A$2:A538,A538)=1,1,0) -> 0
A539: Shania | B539: Pro | C539: Service delivery | D539: sitter-support-resources | E539: value-statement | F539: She felt supported both by Rover and, informally, by the building's cleaning staff who were also helping care for the dog during that period: "by Rover and also... by the um the cleaning lady that was in the building too because she was also taking care of the dog in the mornings." | G539: by the um the cleaning lady that was in the building too because she was also taking care of the dog in the mornings | H539: =IF(COUNTIFS($D$2:D539,D539,$E$2:E539,E539,$A$2:A539,A539)=1,1,0) -> 0
A540: Tianrui | B540: Pro | C540: Service delivery | D540: in-sit-updates-media | E540: fact | F540: TR sends owners daily updates during a sit, including photos, videos, and a text summary of how the pet has been doing ("I always send them like a daily updates on the past like including photos and a videos and a text summary about how they've been doing for today"). | G540: I always send them like a daily updates on the past like including photos and a videos and a text summary about how they've been doing for today | H540: =IF(COUNTIFS($D$2:D540,D540,$E$2:E540,E540,$A$2:A540,A540)=1,1,0) -> 1
A541: Tianrui | B541: Pro | C541: Service delivery | D541: in-sit-updates-media | E541: fact | F541: TR sees owners' quick responses to these updates as a sign of how much they care about the pet ("some owners really really care about the cats. Every time I send one, they will respond to me instantly and then from that I can know they're pretty responsive and really care about the pets"). | G541: they will respond to me instantly and then from that I can know they're pretty responsive and really care about the pets | H541: =IF(COUNTIFS($D$2:D541,D541,$E$2:E541,E541,$A$2:A541,A541)=1,1,0) -> 0
A542: Tianrui | B542: Pro | C542: Service delivery | D542: off-platform-communication-channels | E542: fact | F542: All communication during a sit happens through the Rover app/chat. | H542: =IF(COUNTIFS($D$2:D542,D542,$E$2:E542,E542,$A$2:A542,A542)=1,1,0) -> 1
A543: Tianrui | B543: Pro | C543: Service delivery | D543: in-sit-updates-media | E543: fact | F543: TR doesn't think a mandatory reporting requirement like the drop-in card is needed for boarding, since not every sitter provides the same level of text, photo, and video updates that they do ("not every sitter going to be like me who writes the text message and the photos and the videos. So I feel like something like that is not like required"). | G543: not every sitter going to be like me who writes the text message and the photos and the videos. So I feel like something like that is not like required | H543: =IF(COUNTIFS($D$2:D543,D543,$E$2:E543,E543,$A$2:A543,A543)=1,1,0) -> 0
A544: Tifany | B544: Pro | C544: Service delivery | D544: safety-risk-incidents | E544: friction | F544: She recalls a specific emergency with a dog that started falling over, vomiting, and became disoriented, leaving her to figure out on the spot whether he needed the vet ('he started like um like falling and he's he was big and he's falling and he's barfing and I'm like what on earth? And so, and he can't get up and he's all disoriented'). She says she is not certain whether that dog was a Rover client or a private one ('which has happened not with a rover client I think it was off rover but like maybe it was it was on rover'), and describes struggling in the moment to find the owner's contact information to call them while panicked ('I'm looking looking trying to find where to call this client. I can't find it, especially cuz I'm a little panicked'). | G544: I'm looking looking trying to find where to call this client. I can't find it, especially cuz I'm a little panicked | H544: =IF(COUNTIFS($D$2:D544,D544,$E$2:E544,E544,$A$2:A544,A544)=1,1,0) -> 1
A545: Tifany | B545: Pro | C545: Service delivery | D545: motivation-emotional-connection | E545: value-statement | F545: She also prefers boarding at her own home over housesitting at a client's home, for the same convenience reasons that inform how she prices the two services (see Payments and earnings for detail). | H545: =IF(COUNTIFS($D$2:D545,D545,$E$2:E545,E545,$A$2:A545,A545)=1,1,0) -> 0
A546: Tifany | B546: Pro | C546: Service delivery | D546: provider-background | E546: fact | F546: Her hands-on care work also extends to cats, farm animals, and exotic pets, as well as dogs (see Context and provider model for detail). | H546: =IF(COUNTIFS($D$2:D546,D546,$E$2:E546,E546,$A$2:A546,A546)=1,1,0) -> 0
A547: Ami | B547: Pro | C547: Client communication | D547: off-platform-communication-channels | E547: fact | F547: For her established/regular clients specifically, most communication still happens through Rover, though some of these regulars prefer to text her directly instead ("mostly through rover. Um some people will want to talk um via you know just text"). | G547: mostly through rover. Um some people will want to talk um via you know just text | H547: =IF(COUNTIFS($D$2:D547,D547,$E$2:E547,E547,$A$2:A547,A547)=1,1,0) -> 0
A548: Ami | B548: Pro | C548: Client communication | D548: meet-and-greet-process | E548: fact | F548: During a first meet-and-greet, she deliberately keeps the conversation focused on the animal rather than making small talk with the owner, such as avoiding asking about the owner's vacation plans ("I'm not there to um I'm not there to, you know, I'm not there to find out, oh, where are you going on vacation?"). | G548: I'm not there to um I'm not there to, you know, I'm not there to find out, oh, where are you going on vacation? | H548: =IF(COUNTIFS($D$2:D548,D548,$E$2:E548,E548,$A$2:A548,A548)=1,1,0) -> 0
A549: Andrew | B549: Pro | C549: Client communication | D549: off-platform-communication-channels | E549: fact | F549: Communication with clients happens almost exclusively via text message in the app ("Yes, almost exclusively through text message"). | G549: Yes, almost exclusively through text message | H549: =IF(COUNTIFS($D$2:D549,D549,$E$2:E549,E549,$A$2:A549,A549)=1,1,0) -> 1
A550: Andrew | B550: Pro | C550: Client communication | D550: off-platform-communication-channels | E550: value-statement | F550: He personally prefers texting/messaging over phone calls, viewing it as the most reliable, accountable way to communicate ("texting and and messaging is the I think the best way to do it. just sort of the ideal way for accountability"). | G550: texting and and messaging is the I think the best way to do it. just sort of the ideal way for accountability | H550: =IF(COUNTIFS($D$2:D550,D550,$E$2:E550,E550,$A$2:A550,A550)=1,1,0) -> 1
A551: Andrew | B551: Pro | C551: Client communication | D551: repeat-client-relationships | E551: fact | F551: His communication style shifts by client experience level: brief and efficient with people who already know how Rover works, but more guided and explanatory with first-timers ("Other people are just kind of like they're brand new to it. And so I kind of, you know, hold their hand through it"). | G551: Other people are just kind of like they're brand new to it. And so I kind of, you know, hold their hand through it | H551: =IF(COUNTIFS($D$2:D551,D551,$E$2:E551,E551,$A$2:A551,A551)=1,1,0) -> 1
A552: Andrew | B552: Pro | C552: Client communication | D552: messaging-platform-mechanics | E552: friction | F552: He feels pressure to respond within an hour to maintain his Star Sitter status, which becomes especially hard during high-volume periods ("respond you know within an hour to every message. Like when I was getting a ton and ton of messages, like not only was it not possible, but I was just like, I feel bad after a while doing it"). | G552: respond you know within an hour to every message. Like when I was getting a ton and ton of messages, like not only was it not possible, but I was just like, I feel bad after a while doing it | H552: =IF(COUNTIFS($D$2:D552,D552,$E$2:E552,E552,$A$2:A552,A552)=1,1,0) -> 0
A553: Anita | B553: Pro | C553: Client communication | D553: messaging-platform-mechanics | E553: friction | F553: She maintains constant text communication throughout a sit and says it worries her when a client doesn't respond to her messages, even though there is nothing she can do about it ("They check when they don't answer when I when I send them messages. That worries me"). | G553: They check when they don't answer when I when I send them messages. That worries me | H553: =IF(COUNTIFS($D$2:D553,D553,$E$2:E553,E553,$A$2:A553,A553)=1,1,0) -> 1
A554: Anita | B554: Pro | C554: Client communication | D554: off-platform-communication-channels | E554: workaround | F554: She has had clients text her at very late hours expecting round-the-clock availability, but she does not respond until the next morning rather than feeling obligated to reply immediately ("I will get text messages at 12 and midnight. I'm like, I won't see them till the next morning"). | G554: I will get text messages at 12 and midnight. I'm like, I won't see them till the next morning | H554: =IF(COUNTIFS($D$2:D554,D554,$E$2:E554,E554,$A$2:A554,A554)=1,1,0) -> 1
A555: Anita | B555: Pro | C555: Client communication | D555: off-platform-communication-channels | E555: fact | F555: She restricts client communication to the Rover platform and will not use other personal messaging apps for client contact ("Oh, no. I don't I won't allow that on my" phone). | G555: Oh, no. I don't I won't allow that on my | H555: =IF(COUNTIFS($D$2:D555,D555,$E$2:E555,E555,$A$2:A555,A555)=1,1,0) -> 1
A556: Anita | B556: Pro | C556: Client communication | D556: repeat-client-relationships | E556: value-statement | F556: Beyond active bookings, she sustains longer-term relationships with some clients through personal gestures that deepen over time, such as sharing birthdays and giving birthday and Christmas gifts ("now, like now, we share birthdays. I I give birthday presents to them and their pet. I give Christmas presents"). | G556: now, like now, we share birthdays. I I give birthday presents to them and their pet. I give Christmas presents | H556: =IF(COUNTIFS($D$2:D556,D556,$E$2:E556,E556,$A$2:A556,A556)=1,1,0) -> 1
A557: Anita | B557: Pro | C557: Client communication | D557: safety-risk-incidents | E557: workaround | F557: Early in a client relationship she is deliberately upfront to build trust quickly, for example sharing her own driver's license so clients know who she is ("I share uh my personal ID. I give them my driver's license and so they know that I'm upfront"). | G557: I share uh my personal ID. I give them my driver's license and so they know that I'm upfront | H557: =IF(COUNTIFS($D$2:D557,D557,$E$2:E557,E557,$A$2:A557,A557)=1,1,0) -> 1
A558: Anita | B558: Pro | C558: Client communication | D558: repeat-client-relationships | E558: value-statement | F558: She believes consistent, open communication throughout a stay is what keeps clients returning, illustrating this with a secondhand account of another sitter whose client got upset after the sitter was unreachable for seven hours ("as long as you keep that communication open, it will continue"; "there was a woman who said that she fell asleep for seven hours" and "the owner got mad"). | G558: as long as you keep that communication open, it will continue | H558: =IF(COUNTIFS($D$2:D558,D558,$E$2:E558,E558,$A$2:A558,A558)=1,1,0) -> 0
... A648: Erika | B648: Pro | C648: Completion and feedback | D648: repeat-client-relationships | E648: value-statement | F648: She says her regular clients specifically prefer her over having another person care for their pet ("Yeah. Now I have regular customers who definitely prefer me to take care of their babies uh uh rather than to have them with another person"). | G648: Yeah. Now I have regular customers who definitely prefer me to take care of their babies uh uh rather than to have them with another person | H648: =IF(COUNTIFS($D$2:D648,D648,$E$2:E648,E648,$A$2:A648,A648)=1,1,0) -> 1
A649: Erika | B649: Pro | C649: Completion and feedback | D649: reviews-feedback-process | E649: fact | F649: She does not describe an explicit post-sit payment-trigger step, nor does she mention leaving or receiving reviews anywhere in the interview -- neither is discussed. | H649: =IF(COUNTIFS($D$2:D649,D649,$E$2:E649,E649,$A$2:A649,A649)=1,1,0) -> 1
A650: Erika | B650: Pro | C650: Completion and feedback | D650: repeat-client-relationships | E650: fact | F650: Her relationship with clients often continues past a single sit: a regular client, the owner of a dog named Bella, keeps booking her on an ongoing basis for one or a couple of nights a week ("she pays me for one or a couple nights a week"). | G650: she pays me for one or a couple nights a week | H650: =IF(COUNTIFS($D$2:D650,D650,$E$2:E650,E650,$A$2:A650,A650)=1,1,0) -> 0
...

Sheet Friction-Need Frequency
A1: Theme | B1: Type | C1: Distinct providers (of 14 Pro) | D1: Which providers | E1: Representative observation | F1: Representative quote
A2: messaging-platform-mechanics | B2: friction | C2: =SUMIFS('Raw Atomic Data (Pro)'!$H$2:$H$978,'Raw Atomic Data (Pro)'!$D$2:$D$978,A2,'Raw Atomic Data (Pro)'!$E$2:$E$978,B2) -> 9 | D2: Ami, Andrew, Anita, Ashley P., Becky, Colin, Erika, Naomi, Tifany | E2: [Andrew] He finds it a little annoying when the app sends an automated/generated first message on a client's behalf, because the client doesn't always know what it says ("I think sometime it does the automated like the generated message like hello I'd like to I was like that's a little annoying because like they don't really know what it says"). | F2: I think sometime it does the automated like the generated message like hello I'd like to I was like that's a little annoying because like they don't really know what it says
A3: calendar-scheduling-tools | B3: need | C3: =SUMIFS('Raw Atomic Data (Pro)'!$H$2:$H$978,'Raw Atomic Data (Pro)'!$D$2:$D$978,A3,'Raw Atomic Data (Pro)'!$E$2:$E$978,B3) -> 7 | D3: Ami, Anita, Becky, Dawn, Naomi, Tianrui, Tifany | E3: [Ami] She would like Rover's calendar to sync or link directly with her personal Google Calendar so she doesn't have to manually type in every appointment ("That would be nice if it was linked because then I wouldn't have to physically, you know, write or, you know, type in five or six different appointments"). | F3: That would be nice if it was linked because then I wouldn't have to physically, you know, write or, you know, type in five or six different appointments
A4: calendar-scheduling-tools | B4: workaround | C4: =SUMIFS('Raw Atomic Data (Pro)'!$H$2:$H$978,'Raw Atomic Data (Pro)'!$D$2:$D$978,A4,'Raw Atomic Data (Pro)'!$E$2:$E$978,B4) -> 6 | D4: Anita, Ashley P., Colin, Kristin, Naomi, Tifany | E4: [Anita] She also uses Google's alarm/clock feature to make sure she gets to each appointment on time ("Google alarms, the clock to set off so I know remember to go to each next appointment"). | F4: Google alarms, the clock to set off so I know remember to go to each next appointment
A5: calendar-scheduling-tools | B5: friction | C5: =SUMIFS('Raw Atomic Data (Pro)'!$H$2:$H$978,'Raw Atomic Data (Pro)'!$D$2:$D$978,A5,'Raw Atomic Data (Pro)'!$E$2:$E$978,B5) -> 5 | D5: Becky, Kristin, Naomi, Tianrui, Tifany | E5: [Becky] She describes a past bug, lasting multiple months, where the date entered for scheduling a meet and greet in the chat would shift to the day before every time; she believes this has since been fixed ("there was a long period of time like multiple months I think where the date would always you would put in the date but it would like change to the day before every time you put the date and so it would always be wrong. Um, and that was very annoying. I think they fixed it now."). | F5: there was a long period of time like multiple months I think where the date would always you would put in the date but it would like change to the day before every time you put the date and so it would always be wrong. Um, and that was very annoying. I think they fixed it now.
A6: care-instructions-handoff | B6: workaround | C6: =SUMIFS('Raw Atomic Data (Pro)'!$H$2:$H$978,'Raw Atomic Data (Pro)'!$D$2:$D$978,A6,'Raw Atomic Data (Pro)'!$E$2:$E$978,B6) -> 5 | D6: Ami, Andrew, Anita, Bruna, Kristin | E6: [Ami] She keeps a physical "blue notebook" in which she writes down details from every meet-and-greet, including addresses, house codes, feeding schedules, and medication, while the owner talks and as she walks around the house ("Every time I get do a meet and greet, I write everything down in that" and "I know addresses um I know house codes, you know, um I know feeding schedules, uh medication, all that"). | F6: I know addresses um I know house codes, you know, um I know feeding schedules, uh medication, all that
A7: messaging-platform-mechanics | B7: need | C7: =SUMIFS('Raw Atomic Data (Pro)'!$H$2:$H$978,'Raw Atomic Data (Pro)'!$D$2:$D$978,A7,'Raw Atomic Data (Pro)'!$E$2:$E$978,B7) -> 5 | D7: Ashley P., Erika, Naomi, Tianrui, Tifany | E7: [Tianrui] TR wishes Rover's text-message notifications could display photos and videos directly, since clients who haven't downloaded the Rover app can't otherwise see media without logging into the app ("some clients just don't download the Rover app at all and they just only rely on the chats... if they can like also make the photos and a video show up on the text message interface going to be better"). | F7: if they can like also make the photos and a video show up on the text message interface going to be better
A8: payout-timing-tracking | B8: need | C8: =SUMIFS('Raw Atomic Data (Pro)'!$H$2:$H$978,'Raw Atomic Data (Pro)'!$D$2:$D$978,A8,'Raw Atomic Data (Pro)'!$E$2:$E$978,B8) -> 5 | D8: Andrew, Ashley P., Naomi, Tianrui, Tifany | E8: [Andrew] He would prefer a payout breakdown by specific date and booking rather than one lump total ("I would find that a little more useful to know to to know like not just how much is coming, but specifically when and for what"). | F8: I would find that a little more useful to know to to know like not just how much is coming, but specifically when and for what
A9: business-model-fit | B9: friction | C9: =SUMIFS('Raw Atomic Data (Pro)'!$H$2:$H$978,'Raw Atomic Data (Pro)'!$D$2:$D$978,A9,'Raw Atomic Data (Pro)'!$E$2:$E$978,B9) -> 4 | D9: Anita, Ashley P., Becky, Erika | E9: [Becky] She says the one real challenge was finding a good time to walk a dog when her work meetings started early (around 6:00 a.m.) and were busy that morning ("the only challenge is really like finding a good time to go on a walk. If I have meetings starting at 6:00 and my meetings were very busy in the morning, then like getting a good time to go on a walk was a little bit tricky."). | F9: the only challenge is really like finding a good time to go on a walk. If I have meetings starting at 6:00 and my meetings were very busy in the morning, then like getting a good time to go on a walk was a little bit tricky.
A10: safety-risk-incidents | B10: friction | C10: =SUMIFS('Raw Atomic Data (Pro)'!$H$2:$H$978,'Raw Atomic Data (Pro)'!$D$2:$D$978,A10,'Raw Atomic Data (Pro)'!$E$2:$E$978,B10) -> 4 | D10: Anita, Bruna, Naomi, Tifany | E10: [Anita] She described one meet-and-greet where an older, unsocialized dog attacked her, and she believed the owner was trying to get rid of the dog rather than find genuine care ("The dog was older and aggressive and as soon as I got there, he attacked me"; "it was a bad owner. They were trying to dump the dog"). | F10: it was a bad owner. They were trying to dump the dog
A11: care-instructions-handoff | B11: need | C11: =SUMIFS('Raw Atomic Data (Pro)'!$H$2:$H$978,'Raw Atomic Data (Pro)'!$D$2:$D$978,A11,'Raw Atomic Data (Pro)'!$E$2:$E$978,B11) -> 4 | D11: Andrew, Anita, Ashley P., Becky | E11: [Andrew] He is unsure whether Rover has a private notes feature for sitters to keep track of client/dog details themselves, and thinks it would be useful if it existed ("I don't know if there is a note feature"). | F11: I don't know if there is a note feature
A12: off-platform-communication-channels | B12: workaround | C12: =SUMIFS('Raw Atomic Data (Pro)'!$H$2:$H$978,'Raw Atomic Data (Pro)'!$D$2:$D$978,A12,'Raw Atomic Data (Pro)'!$E$2:$E$978,B12) -> 4 | D12: Anita, Colin, Erika, Kristin | E12: [Anita] She has had clients text her at very late hours expecting round-the-clock availability, but she does not respond until the next morning rather than feeling obligated to reply immediately ("I will get text messages at 12 and midnight. I'm like, I won't see them till the next morning"). | F12: I will get text messages at 12 and midnight. I'm like, I won't see them till the next morning
A13: messaging-platform-mechanics | B13: workaround | C13: =SUMIFS('Raw Atomic Data (Pro)'!$H$2:$H$978,'Raw Atomic Data (Pro)'!$D$2:$D$978,A13,'Raw Atomic Data (Pro)'!$E$2:$E$978,B13) -> 4 | D13: Ashley P., Becky, Naomi, Shania | E13: [Becky] Her general approach is to redirect Rover messages to her phone's regular text app rather than opening the Rover app, since it's easier than navigating the app's UI ("it's just easier just comes up as a text message rather than me having to open app and then navigate their UI."). | F13: it's just easier just comes up as a text message rather than me having to open app and then navigate their UI.
... A63: tipping | B63: friction | C63: =SUMIFS('Raw Atomic Data (Pro)'!$H$2:$H$978,'Raw Atomic Data (Pro)'!$D$2:$D$978,A63,'Raw Atomic Data (Pro)'!$E$2:$E$978,B63) -> 1 | D63: Ashley P. | E63: [Ashley P.] She says clients often tip her, but the tip option only becomes available after the client submits a full review first, which she believes reduces how often people tip, even though she also understands the design likely helps ensure more consistent reviews ("The problem is is they have to leave a full review basically to get to the tip part... I think that there would be the potential for more tips if it wasn't um like dug into that section, but also I understand it in a way because it it gets people to review which may not happen as consistently if it wasn't in that same area."). | F63: The problem is is they have to leave a full review basically to get to the tip part
A65: Note: counts are distinct providers who raised this theme/type at least once, not row counts. A theme with a low count may still be a real issue for that provider -- it just isn't (yet) widely shared across the Pro segment.

Sheet Leakage - By Participant
A1: Participant | B1: Status | C1: Who initiates | D1: Reason given | E1: Notes (grounded in transcript)
A2: Ami | B2: Some leakage -- 2 documented cases | C2: Client | D2: Not stated | E2: Does not proactively suggest moving off Rover; agrees if the client asks.
A3: Andrew | B3: No leakage | C3: N/A | D3: N/A | E3: Says everything is on Rover. Separately explains why he stays: Rover handles communication/scheduling/liability, and he dislikes admin paperwork and self-marketing alternatives (flyers, Nextdoor).
A4: Anita | B4: Some leakage -- owner-initiated fee-avoidance attempts | C4: Client / owner | D4: Avoid Rover's fees | E4: Frames it as outside her control ('that's up to the owner'). Says she'd only look for another platform if Rover itself shut down.
A5: Ashley P. | B5: Some leakage -- ~3 clients over time | C5: Client | D5: Avoid fees that 'go nowhere'; client still pays her the same amount | E5: Says it's always the client who raises it, never her; keeps almost all clients on Rover.
A6: Becky | B6: Recurring leakage -- multiple clients taken offline | C6: Mixed (sometimes client asks directly, sometimes mutual once familiar) | D6: Not explicitly stated beyond avoiding Rover / comfort with familiarity | E6: Acknowledges this is against Rover's rules. Charges offline clients less than the Rover listing price, splitting the difference with her own take-home.
A7: Bruna | B7: No leakage | C7: N/A | D7: N/A | E7: Rover is her only platform; gets referrals through a private trainer network but books through Rover.
A8: Colin | B8: No leakage | C8: N/A | D8: N/A | E8: Everything is done through the app.
A9: Dawn | B9: Unclear / unconfirmed | C9: N/A | D9: N/A | E9: Audio was garbled at this question in the transcript; cannot be confirmed.
A10: Erika | B10: No leakage (stated as a general rule) | C10: N/A | D10: N/A | E10: Says she never books new clients outside the app.
A11: Kristin | B11: Partial leakage -- about 10% of clients | C11: Client | D11: Preference for other channels (not fee-avoidance) -- mostly elderly clients defaulting to NextDoor, Facebook, or phone | E11: When a client reaches out off-platform first, she redirects them back to her Rover profile.
A12: Naomi | B12: No stated instance in this theme | C12: N/A | D12: N/A | E12: Runs a separate private client base in parallel (Google Calendar, spreadsheets, a payment processor), but this is not documented as Rover clients converting off-platform.
... A15: Tifany | B15: Declined -- provider deliberately keeps clients on Rover | C15: Provider (deliberate policy) | D15: N/A (provider-side reason, not a client ask) | E15: Says she's afraid of losing her standing on Rover if she moves clients off; leaves the choice to the client but doesn't encourage it.
A18: Status bucket counts (of 14 Pro providers):
A19: No leakage | B19: =COUNTIF($B$2:$B$15,"*No leakage*") -> 5
A20: Some leakage | B20: =COUNTIF($B$2:$B$15,"*Some leakage*") -> 3
A21: Partial leakage | B21: =COUNTIF($B$2:$B$15,"*Partial leakage*") -> 1
A22: Recurring leakage | B22: =COUNTIF($B$2:$B$15,"*Recurring leakage*") -> 1
A23: Declined | B23: =COUNTIF($B$2:$B$15,"*Declined*") -> 2
A24: Unclear | B24: =COUNTIF($B$2:$B$15,"*Unclear*") -> 1
A25: No stated instance | B25: =COUNTIF($B$2:$B$15,"*No stated instance*") -> 1
A26: Total (should equal 14) | B26: =SUM(B19:B25) -> 14

Sheet Leakage - Raw Evidence
A1: Participant | B1: Type | C1: Category | D1: Observation | E1: Quote
A2: Tianrui | B2: fact | C2: Context and provider model | D2: TR has never taken on private, off-platform clients — all clients come through Rover ("I don't do privately"). | E2: I don't do privately
A3: Kristin | B3: fact | C3: Client acquisition | D3: Even when a client first reaches out off-platform, she directs them back to her Rover profile to see her availability, pricing, and reviews ("here's my Rover app if you need to see my" availability, pricing, reviews). | E3: here's my Rover app if you need to see my
A4: Becky | B4: fact | C4: Payments and earnings | D4: When she takes a repeat client's booking offline, she says she charges them less than Rover would, splitting the difference between her Rover take-home and the full Rover listing price so the client pays less while she keeps more of the money ("I typically charge less than what Rover would charge, but I like split the difference between my take-home from Rover and Got over the booking the listing price. So they pay less and I get to take home"). | E4: I typically charge less than what Rover would charge, but I like split the difference between my take-home from Rover and Got over the booking the listing price. So they pay less and I get to take home
A5: Ami | B5: fact | C5: Cross-platform behavior | D5: Two of her Rover clients proposed moving their arrangement off-platform after first contacting her through Rover, and she went along with it ("We started with Rover and then they just said, 'Hey, let's just do this, you know, let's let's just do this outside of Rover.'" and "that's happened in I want to say maybe two cases"). | E5: We started with Rover and then they just said, 'Hey, let's just do this, you know, let's let's just do this outside of Rover.'
A6: Ami | B6: fact | C6: Cross-platform behavior | D6: She doesn't proactively suggest moving a relationship off Rover herself, but will agree if the client requests it ("I usually I don't say anything to the person. I if they say something to me like I'd rather do this outside of Rover then I'll be like okay we we can do that"). | E6: I usually I don't say anything to the person. I if they say something to me like I'd rather do this outside of Rover then I'll be like okay we we can do that
A7: Andrew | B7: fact | C7: Cross-platform behavior | D7: He has no off-platform clients at all; everything runs through Rover ("No, it's all on rover"). | E7: No, it's all on rover
A8: Andrew | B8: value-statement | C8: Cross-platform behavior | D8: He considered but rejected doing pet sitting independently, because Rover already handles communication, scheduling, and provides a sense of security/liability that he'd otherwise have to arrange himself ("there's just so many things I feel like Rover takes care of like a lot of little especially communication scheduling uh and just providing a sense of security and liability for both parties"). | E8: there's just so many things I feel like Rover takes care of like a lot of little especially communication scheduling uh and just providing a sense of security and liability for both parties
A9: Andrew | B9: value-statement | C9: Cross-platform behavior | D9: He compares Rover favorably to alternative self-marketing channels he considered unappealing, like flyers at the dog park or figuring out Nextdoor ("I'm like putting up flyers at the dog park. I'm trying to figure out how Next Door works as a platform. Uh and none of that's very appealing to me"). | E9: I'm like putting up flyers at the dog park. I'm trying to figure out how Next Door works as a platform. Uh and none of that's very appealing to me
A10: Andrew | B10: value-statement | C10: Cross-platform behavior | D10: He also cites avoiding administrative paperwork as a reason for staying on Rover rather than operating independently, describing himself as bad at it ("I'm also terrible at paperwork. It was like if I could just force that all off on somebody"). | E10: I'm also terrible at paperwork. It was like if I could just force that all off on somebody
A11: Anita | B11: fact | C11: Cross-platform behavior | D11: Clients have tried to move some bookings off the Rover platform directly to avoid Rover's fees; she confirms this has happened, and frames it as the owner's decision rather than something within her control ("it has happened only because the owners don't want to pay" the fees; "that's not in my control, you know, that's something it's up to the owner"). | E11: it has happened only because the owners don't want to pay
A12: Becky | B12: fact | C12: Cross-platform behavior | D12: Once she and a client are friendly and both feel comfortable, she says they can take the arrangement offline ("once we're friends, um if if everyone feels good about taking it offline, we can take it offline."). | E12: once we're friends, um if if everyone feels good about taking it offline, we can take it offline.
... A30: Ashley P. | B30: fact | C30: Cross-platform behavior | D30: In those cases, the pet parent frames it as wanting to stop paying fees that "go nowhere" while still paying her the same amount, which she describes as a "win-win" ("It's always the pet parent that's like, 'Hey,... I don't want to pay these fees that are going nowhere, and I want you to get paid the same amount.' So, it's like a win-win in those scenarios."). | E30: It's always the pet parent that's like

Sheet Theme Legend
A1: Theme | B1: Definition
A2: provider-background | B2: Background facts about who the provider is - age, family, living situation, other job, own pets - not directly about Rover.
A3: motivation-emotional-connection | B3: Why the provider does pet sitting and the personal/emotional value they get from being around animals.
A4: business-model-fit | B4: How pet sitting fits alongside the provider's other income, job, and life schedule (side income, full-time/part-time framing, flexibility).
A5: onboarding-signup-process | B5: Getting set up on Rover initially - background check, account verification, first approval, choosing Rover over alternatives.
A6: client-acquisition-discovery | B6: How new clients first find and contact the sitter, and what the sitter does to attract them.
A7: search-ranking-visibility | B7: Rover's search-ranking/algorithm and how it affects a sitter's visibility, especially for new or lower-ranked sitters.
A8: meet-and-greet-process | B8: How meet-and-greets are conducted - logistics, format, purpose, in-person vs. video.
A9: client-dog-screening-criteria | B9: The sitter's criteria and non-negotiables for accepting or declining a specific dog or client (aggression, size, breed, behavior, distance).
A10: safety-risk-incidents | B10: Physical-safety concerns and incidents involving the sitter, a dog, or an owner, and personal-safety precautions.
A11: calendar-scheduling-tools | B11: Tools and behavior for tracking availability and bookings - Rover's calendar, Google Calendar sync, calendar bugs.
A12: booking-confirmation-mechanics | B12: The mechanics of how a request becomes a confirmed (or cancelled) booking - blocking dates, mutual confirmation, cancellation rules.
... A31: daily-care-tasks | B31: Neutral facts about the concrete tasks performed during a sit - feeding, walking, medicating, cleaning.

Sheet Journey Map (Pro)
A1: Stage | B1: What this stage covers | C1: Off-platform leakage note for this stage | J1: Helper: Participant | K1: Helper: Category | L1: Helper: Theme | M1: Helper: Type | N1: Helper: Is friction/need/workaround | O1: Helper: 1st occurrence of Category+Theme+Type+Participant | P1: Helper: 1st occurrence of Theme+Participant (FNW only) | Q1: Helper: 1st occurrence of Theme+Category (FNW only) | R1: Helper: 1st occurrence of Category+Theme+Participant (FNW only) | S1: Helper: Is stage category (excludes Context/Motivation)
A2: Client acquisition | B2: How clients first find and contact the provider, before any screening or decision happens. | C2: One off-platform-clients-leakage row is tagged in this stage: Kristin describes redirecting off-platform inquiries back to her Rover profile ("here's my Rover app if you need to see my [availability, pricing, and reviews]") rather than losing the lead off-platform. This is a retention behavior at the discovery stage, not an instance of a client or booking actually leaving Rover. | J2: ='Raw Atomic Data (Pro)'!A2 -> Ami | K2: ='Raw Atomic Data (Pro)'!C2 -> Context and provider model | L2: ='Raw Atomic Data (Pro)'!D2 -> provider-background | M2: ='Raw Atomic Data (Pro)'!E2 -> fact | N2: =IF(OR(M2="friction",M2="need",M2="workaround"),1,0) -> 0 | O2: =IF(COUNTIFS($K$2:K2,K2,$L$2:L2,L2,$M$2:M2,M2,$J$2:J2,J2)=1,1,0) -> 1 | P2: =IF(AND(N2=1,S2=1,COUNTIFS($L$2:L2,L2,$J$2:J2,J2,$N$2:N2,1,$S$2:S2,1)=1),1,0) -> 0 | Q2: =IF(AND(N2=1,S2=1,COUNTIFS($L$2:L2,L2,$K$2:K2,K2,$N$2:N2,1,$S$2:S2,1)=1),1,0) -> 0 | R2: =IF(AND(N2=1,COUNTIFS($K$2:K2,K2,$L$2:L2,L2,$J$2:J2,J2,$N$2:N2,1)=1),1,0) -> 0 | S2: =IF(AND(K2<>"Context and provider model",K2<>"Motivation"),1,0) -> 0
A3: Evaluation and meet-and-greet | B3: The screening/decision moment -- how the provider decides whether to accept a specific client or pet, meet-and-greet behavior. | C3: No off-platform-clients-leakage rows are tagged in this stage. | J3: ='Raw Atomic Data (Pro)'!A3 -> Ami | K3: ='Raw Atomic Data (Pro)'!C3 -> Context and provider model | L3: ='Raw Atomic Data (Pro)'!D3 -> provider-background | M3: ='Raw Atomic Data (Pro)'!E3 -> fact | N3: =IF(OR(M3="friction",M3="need",M3="workaround"),1,0) -> 0 | O3: =IF(COUNTIFS($K$2:K3,K3,$L$2:L3,L3,$M$2:M3,M3,$J$2:J3,J3)=1,1,0) -> 0 | P3: =IF(AND(N3=1,S3=1,COUNTIFS($L$2:L3,L3,$J$2:J3,J3,$N$2:N3,1,$S$2:S3,1)=1),1,0) -> 0 | Q3: =IF(AND(N3=1,S3=1,COUNTIFS($L$2:L3,L3,$K$2:K3,K3,$N$2:N3,1,$S$2:S3,1)=1),1,0) -> 0 | R3: =IF(AND(N3=1,COUNTIFS($K$2:K3,K3,$L$2:L3,L3,$J$2:J3,J3,$N$2:N3,1)=1),1,0) -> 0 | S3: =IF(AND(K3<>"Context and provider model",K3<>"Motivation"),1,0) -> 0
A4: Booking and availability | B4: Scheduling mechanics once a booking is being arranged: calendar management, confirming dates, cancellations. | C4: No off-platform-clients-leakage rows are tagged in this stage. | J4: ='Raw Atomic Data (Pro)'!A4 -> Ami | K4: ='Raw Atomic Data (Pro)'!C4 -> Context and provider model | L4: ='Raw Atomic Data (Pro)'!D4 -> provider-background | M4: ='Raw Atomic Data (Pro)'!E4 -> fact | N4: =IF(OR(M4="friction",M4="need",M4="workaround"),1,0) -> 0 | O4: =IF(COUNTIFS($K$2:K4,K4,$L$2:L4,L4,$M$2:M4,M4,$J$2:J4,J4)=1,1,0) -> 0 | P4: =IF(AND(N4=1,S4=1,COUNTIFS($L$2:L4,L4,$J$2:J4,J4,$N$2:N4,1,$S$2:S4,1)=1),1,0) -> 0 | Q4: =IF(AND(N4=1,S4=1,COUNTIFS($L$2:L4,L4,$K$2:K4,K4,$N$2:N4,1,$S$2:S4,1)=1),1,0) -> 0 | R4: =IF(AND(N4=1,COUNTIFS($K$2:K4,K4,$L$2:L4,L4,$J$2:J4,J4,$N$2:N4,1)=1),1,0) -> 0 | S4: =IF(AND(K4<>"Context and provider model",K4<>"Motivation"),1,0) -> 0
A5: Sitting preparation | B5: Between confirmed booking and the sit starting: care instructions, medication/emergency info, keys/access. | C5: No off-platform-clients-leakage rows are tagged in this stage. | J5: ='Raw Atomic Data (Pro)'!A5 -> Ami | K5: ='Raw Atomic Data (Pro)'!C5 -> Context and provider model | L5: ='Raw Atomic Data (Pro)'!D5 -> business-model-fit | M5: ='Raw Atomic Data (Pro)'!E5 -> fact | N5: =IF(OR(M5="friction",M5="need",M5="workaround"),1,0) -> 0 | O5: =IF(COUNTIFS($K$2:K5,K5,$L$2:L5,L5,$M$2:M5,M5,$J$2:J5,J5)=1,1,0) -> 1 | P5: =IF(AND(N5=1,S5=1,COUNTIFS($L$2:L5,L5,$J$2:J5,J5,$N$2:N5,1,$S$2:S5,1)=1),1,0) -> 0 | Q5: =IF(AND(N5=1,S5=1,COUNTIFS($L$2:L5,L5,$K$2:K5,K5,$N$2:N5,1,$S$2:S5,1)=1),1,0) -> 0 | R5: =IF(AND(N5=1,COUNTIFS($K$2:K5,K5,$L$2:L5,L5,$J$2:J5,J5,$N$2:N5,1)=1),1,0) -> 0 | S5: =IF(AND(K5<>"Context and provider model",K5<>"Motivation"),1,0) -> 0
A6: Service delivery | B6: What the provider actually does during the sit: daily care tasks, on-site issue handling. | C6: No off-platform-clients-leakage rows are tagged in this stage. | J6: ='Raw Atomic Data (Pro)'!A6 -> Ami | K6: ='Raw Atomic Data (Pro)'!C6 -> Context and provider model | L6: ='Raw Atomic Data (Pro)'!D6 -> provider-background | M6: ='Raw Atomic Data (Pro)'!E6 -> fact | N6: =IF(OR(M6="friction",M6="need",M6="workaround"),1,0) -> 0 | O6: =IF(COUNTIFS($K$2:K6,K6,$L$2:L6,L6,$M$2:M6,M6,$J$2:J6,J6)=1,1,0) -> 0 | P6: =IF(AND(N6=1,S6=1,COUNTIFS($L$2:L6,L6,$J$2:J6,J6,$N$2:N6,1,$S$2:S6,1)=1),1,0) -> 0 | Q6: =IF(AND(N6=1,S6=1,COUNTIFS($L$2:L6,L6,$K$2:K6,K6,$N$2:N6,1,$S$2:S6,1)=1),1,0) -> 0 | R6: =IF(AND(N6=1,COUNTIFS($K$2:K6,K6,$L$2:L6,L6,$J$2:J6,J6,$N$2:N6,1)=1),1,0) -> 0 | S6: =IF(AND(K6<>"Context and provider model",K6<>"Motivation"),1,0) -> 0
A7: Client communication | B7: How communication style, frequency, or tone changes over a relationship or a stay's length. | C7: No off-platform-clients-leakage rows are tagged in this stage. Note this is distinct from the off-platform-communication-channels theme (channel choice -- texting/WhatsApp/etc. -- not client or booking migration), which is heavily tagged here (see 'Frictions / Needs / Workarounds by Stage' table below); channel choice and client leakage are separate coded themes and are not combined in this note. | J7: ='Raw Atomic Data (Pro)'!A7 -> Ami | K7: ='Raw Atomic Data (Pro)'!C7 -> Context and provider model | L7: ='Raw Atomic Data (Pro)'!D7 -> business-model-fit | M7: ='Raw Atomic Data (Pro)'!E7 -> value-statement | N7: =IF(OR(M7="friction",M7="need",M7="workaround"),1,0) -> 0 | O7: =IF(COUNTIFS($K$2:K7,K7,$L$2:L7,L7,$M$2:M7,M7,$J$2:J7,J7)=1,1,0) -> 1 | P7: =IF(AND(N7=1,S7=1,COUNTIFS($L$2:L7,L7,$J$2:J7,J7,$N$2:N7,1,$S$2:S7,1)=1),1,0) -> 0 | Q7: =IF(AND(N7=1,S7=1,COUNTIFS($L$2:L7,L7,$K$2:K7,K7,$N$2:N7,1,$S$2:S7,1)=1),1,0) -> 0 | R7: =IF(AND(N7=1,COUNTIFS($K$2:K7,K7,$L$2:L7,L7,$J$2:J7,J7,$N$2:N7,1)=1),1,0) -> 0 | S7: =IF(AND(K7<>"Context and provider model",K7<>"Motivation"),1,0) -> 0
A8: Completion and feedback | B8: What happens once a sit ends: payment trigger/confirmation, reviews, follow-up, relationship continuation. | C8: No off-platform-clients-leakage rows are tagged in this stage. | J8: ='Raw Atomic Data (Pro)'!A8 -> Ami | K8: ='Raw Atomic Data (Pro)'!C8 -> Context and provider model | L8: ='Raw Atomic Data (Pro)'!D8 -> onboarding-signup-process | M8: ='Raw Atomic Data (Pro)'!E8 -> value-statement | N8: =IF(OR(M8="friction",M8="need",M8="workaround"),1,0) -> 0 | O8: =IF(COUNTIFS($K$2:K8,K8,$L$2:L8,L8,$M$2:M8,M8,$J$2:J8,J8)=1,1,0) -> 1 | P8: =IF(AND(N8=1,S8=1,COUNTIFS($L$2:L8,L8,$J$2:J8,J8,$N$2:N8,1,$S$2:S8,1)=1),1,0) -> 0 | Q8: =IF(AND(N8=1,S8=1,COUNTIFS($L$2:L8,L8,$K$2:K8,K8,$N$2:N8,1,$S$2:S8,1)=1),1,0) -> 0 | R8: =IF(AND(N8=1,COUNTIFS($K$2:K8,K8,$L$2:L8,L8,$J$2:J8,J8,$N$2:N8,1)=1),1,0) -> 0 | S8: =IF(AND(K8<>"Context and provider model",K8<>"Motivation"),1,0) -> 0
A9: Payments and earnings | B9: Pricing, fees, tipping, income tracking, Rover vs. off-platform pricing. | C9: One off-platform-clients-leakage row is tagged in this stage: Becky describes charging clients she has taken offline less than the full Rover listing price, splitting the difference between that and her own Rover take-home ("I typically charge less than what Rover would charge, but I like split the difference between my take-home from Rover and [the full] booking [price]"). This is about the pricing mechanics of an already-leaked relationship, not the leakage trigger itself. | J9: ='Raw Atomic Data (Pro)'!A9 -> Ami | K9: ='Raw Atomic Data (Pro)'!C9 -> Context and provider model | L9: ='Raw Atomic Data (Pro)'!D9 -> onboarding-signup-process | M9: ='Raw Atomic Data (Pro)'!E9 -> value-statement | N9: =IF(OR(M9="friction",M9="need",M9="workaround"),1,0) -> 0 | O9: =IF(COUNTIFS($K$2:K9,K9,$L$2:L9,L9,$M$2:M9,M9,$J$2:J9,J9)=1,1,0) -> 0 | P9: =IF(AND(N9=1,S9=1,COUNTIFS($L$2:L9,L9,$J$2:J9,J9,$N$2:N9,1,$S$2:S9,1)=1),1,0) -> 0 | Q9: =IF(AND(N9=1,S9=1,COUNTIFS($L$2:L9,L9,$K$2:K9,K9,$N$2:N9,1,$S$2:S9,1)=1),1,0) -> 0 | R9: =IF(AND(N9=1,COUNTIFS($K$2:K9,K9,$L$2:L9,L9,$J$2:J9,J9,$N$2:N9,1)=1),1,0) -> 0 | S9: =IF(AND(K9<>"Context and provider model",K9<>"Motivation"),1,0) -> 0
A10: Cross-platform behavior | B10: Tools used alongside Rover, and what has moved off-Rover, under what conditions. | C10: ="This is where the off-platform-clients-leakage theme is most concentrated (23 of 29 tagged rows) and where per-participant leakage status is summarized. Across the 14 Pro providers: "&'Leakage - By Participant'!B19&" report no leakage, "&'Leakage - By Participant'!B20&" some leakage, "&'Leakage - By Participant'!B21&" partial leakage (~10% of clients, one participant), "&'Leakage - By Participant'!B22&" recurring leakage, "&'Leakage - By Participant'!B23&" explicitly declined a client request to move off-platform, "&'Leakage - By Participant'!B24&" unclear/unconfirmed (garbled transcript), and "&'Leakage - By Participant'!B25&" no stated instance. Full detail: 'Leakage - By Participant' sheet. IMPORTANT: leakage is a cross-cutting condition of the client relationship, not a single-stage event -- the same theme is also tagged in Client acquisition, Payments and earnings, and Growth and future plans (see those stages' notes in this column)." -> This is where the off-platform-clients-leakage theme is most concentrated (23 of 29 tagged rows) and where per-participant leakage status is summarized. Across the 14 Pro providers: 5 report no leakage, 3 some leakage, 1 partial leakage (~10% of clients, one participant), 1 recurring leakage, 2 explicitly declined a client request to move off-platform, 1 unclear/unconfirmed (garbled transcript), and 1 no stated instance. Full detail: 'Leakage - By Participant' sheet. IMPORTANT: leakage is a cross-cutting condition of the client relationship, not a single-stage event -- the same theme is also tagged in Client acquisition, Payments and earnings, and Growth and future plans (see those stages' notes in this column). | J10: ='Raw Atomic Data (Pro)'!A10 -> Andrew | K10: ='Raw Atomic Data (Pro)'!C10 -> Context and provider model | L10: ='Raw Atomic Data (Pro)'!D10 -> business-model-fit | M10: ='Raw Atomic Data (Pro)'!E10 -> fact | N10: =IF(OR(M10="friction",M10="need",M10="workaround"),1,0) -> 0 | O10: =IF(COUNTIFS($K$2:K10,K10,$L$2:L10,L10,$M$2:M10,M10,$J$2:J10,J10)=1,1,0) -> 1 | P10: =IF(AND(N10=1,S10=1,COUNTIFS($L$2:L10,L10,$J$2:J10,J10,$N$2:N10,1,$S$2:S10,1)=1),1,0) -> 0 | Q10: =IF(AND(N10=1,S10=1,COUNTIFS($L$2:L10,L10,$K$2:K10,K10,$N$2:N10,1,$S$2:S10,1)=1),1,0) -> 0 | R10: =IF(AND(N10=1,COUNTIFS($K$2:K10,K10,$L$2:L10,L10,$J$2:J10,J10,$N$2:N10,1)=1),1,0) -> 0 | S10: =IF(AND(K10<>"Context and provider model",K10<>"Motivation"),1,0) -> 0
A11: Growth and future plans | B11: Desired trajectory, scaling intentions, what would keep the provider on Rover long-term. | C11: Three off-platform-clients-leakage rows are tagged in this stage, but framed as commitment to Rover rather than attrition: Anita ("If not, I would have to go find another one"; "once I got signed on to Rover, I didn't look elsewhere") and Kristin ("Rover does the advertising for you... there's no reason to change that") both describe staying on Rover rather than switching platforms or going independent. Same theme, opposite direction from leakage -- included here because both concern the provider's relationship to Rover versus alternatives. | J11: ='Raw Atomic Data (Pro)'!A11 -> Andrew | K11: ='Raw Atomic Data (Pro)'!C11 -> Context and provider model | L11: ='Raw Atomic Data (Pro)'!D11 -> provider-background | M11: ='Raw Atomic Data (Pro)'!E11 -> fact | N11: =IF(OR(M11="friction",M11="need",M11="workaround"),1,0) -> 0 | O11: =IF(COUNTIFS($K$2:K11,K11,$L$2:L11,L11,$M$2:M11,M11,$J$2:J11,J11)=1,1,0) -> 1 | P11: =IF(AND(N11=1,S11=1,COUNTIFS($L$2:L11,L11,$J$2:J11,J11,$N$2:N11,1,$S$2:S11,1)=1),1,0) -> 0 | Q11: =IF(AND(N11=1,S11=1,COUNTIFS($L$2:L11,L11,$K$2:K11,K11,$N$2:N11,1,$S$2:S11,1)=1),1,0) -> 0 | R11: =IF(AND(N11=1,COUNTIFS($K$2:K11,K11,$L$2:L11,L11,$J$2:J11,J11,$N$2:N11,1)=1),1,0) -> 0 | S11: =IF(AND(K11<>"Context and provider model",K11<>"Motivation"),1,0) -> 0
J12: ='Raw Atomic Data (Pro)'!A12 -> Andrew | K12: ='Raw Atomic Data (Pro)'!C12 -> Context and provider model | L12: ='Raw Atomic Data (Pro)'!D12 -> capacity-multi-pet-management | M12: ='Raw Atomic Data (Pro)'!E12 -> fact | N12: =IF(OR(M12="friction",M12="need",M12="workaround"),1,0) -> 0 | O12: =IF(COUNTIFS($K$2:K12,K12,$L$2:L12,L12,$M$2:M12,M12,$J$2:J12,J12)=1,1,0) -> 1 | P12: =IF(AND(N12=1,S12=1,COUNTIFS($L$2:L12,L12,$J$2:J12,J12,$N$2:N12,1,$S$2:S12,1)=1),1,0) -> 0 | Q12: =IF(AND(N12=1,S12=1,COUNTIFS($L$2:L12,L12,$K$2:K12,K12,$N$2:N12,1,$S$2:S12,1)=1),1,0) -> 0 | R12: =IF(AND(N12=1,COUNTIFS($K$2:K12,K12,$L$2:L12,L12,$J$2:J12,J12,$N$2:N12,1)=1),1,0) -> 0 | S12: =IF(AND(K12<>"Context and provider model",K12<>"Motivation"),1,0) -> 0
A13: How to read this sheet: Section 1 is the sequential stage backbone (same 10 categories used to tag the raw transcripts). Section 2 lists every friction, need, and workaround tagged in each stage, with a live distinct-provider count pulled straight from Raw Atomic Data (Pro) -- workarounds were tagged in the source data but omitted from the first-draft map; they are included here. Section 3 rolls up themes that were tagged as a friction/need/workaround in MORE THAN ONE stage -- i.e. cross-cutting issues (like messaging mechanics or the meet-and-greet scheduling problem) that a stage-by-stage read alone would fragment and undercount. All counts in Sections 2-3 are live formulas built from a calculation-helper block in hidden columns J:S of this sheet, which mirror Raw Atomic Data (Pro) row-for-row -- unhide to audit. 'Context and provider model' and 'Motivation' categories are excluded throughout since they are background/outlook, not sequential workflow steps. | J13: ='Raw Atomic Data (Pro)'!A13 -> Andrew | K13: ='Raw Atomic Data (Pro)'!C13 -> Context and provider model | L13: ='Raw Atomic Data (Pro)'!D13 -> provider-background | M13: ='Raw Atomic Data (Pro)'!E13 -> fact | N13: =IF(OR(M13="friction",M13="need",M13="workaround"),1,0) -> 0 | O13: =IF(COUNTIFS($K$2:K13,K13,$L$2:L13,L13,$M$2:M13,M13,$J$2:J13,J13)=1,1,0) -> 0 | P13: =IF(AND(N13=1,S13=1,COUNTIFS($L$2:L13,L13,$J$2:J13,J13,$N$2:N13,1,$S$2:S13,1)=1),1,0) -> 0 | Q13: =IF(AND(N13=1,S13=1,COUNTIFS($L$2:L13,L13,$K$2:K13,K13,$N$2:N13,1,$S$2:S13,1)=1),1,0) -> 0 | R13: =IF(AND(N13=1,COUNTIFS($K$2:K13,K13,$L$2:L13,L13,$J$2:J13,J13,$N$2:N13,1)=1),1,0) -> 0 | S13: =IF(AND(K13<>"Context and provider model",K13<>"Motivation"),1,0) -> 0
J14: ='Raw Atomic Data (Pro)'!A14 -> Andrew | K14: ='Raw Atomic Data (Pro)'!C14 -> Context and provider model | L14: ='Raw Atomic Data (Pro)'!D14 -> business-model-fit | M14: ='Raw Atomic Data (Pro)'!E14 -> fact | N14: =IF(OR(M14="friction",M14="need",M14="workaround"),1,0) -> 0 | O14: =IF(COUNTIFS($K$2:K14,K14,$L$2:L14,L14,$M$2:M14,M14,$J$2:J14,J14)=1,1,0) -> 0 | P14: =IF(AND(N14=1,S14=1,COUNTIFS($L$2:L14,L14,$J$2:J14,J14,$N$2:N14,1,$S$2:S14,1)=1),1,0) -> 0 | Q14: =IF(AND(N14=1,S14=1,COUNTIFS($L$2:L14,L14,$K$2:K14,K14,$N$2:N14,1,$S$2:S14,1)=1),1,0) -> 0 | R14: =IF(AND(N14=1,COUNTIFS($K$2:K14,K14,$L$2:L14,L14,$J$2:J14,J14,$N$2:N14,1)=1),1,0) -> 0 | S14: =IF(AND(K14<>"Context and provider model",K14<>"Motivation"),1,0) -> 0
A15: Frictions, Needs & Workarounds by Stage (one row per Stage x Theme x Type tagged in Raw Atomic Data (Pro)) | J15: ='Raw Atomic Data (Pro)'!A15 -> Andrew | K15: ='Raw Atomic Data (Pro)'!C15 -> Context and provider model | L15: ='Raw Atomic Data (Pro)'!D15 -> provider-background | M15: ='Raw Atomic Data (Pro)'!E15 -> fact | N15: =IF(OR(M15="friction",M15="need",M15="workaround"),1,0) -> 0 | O15: =IF(COUNTIFS($K$2:K15,K15,$L$2:L15,L15,$M$2:M15,M15,$J$2:J15,J15)=1,1,0) -> 0 | P15: =IF(AND(N15=1,S15=1,COUNTIFS($L$2:L15,L15,$J$2:J15,J15,$N$2:N15,1,$S$2:S15,1)=1),1,0) -> 0 | Q15: =IF(AND(N15=1,S15=1,COUNTIFS($L$2:L15,L15,$K$2:K15,K15,$N$2:N15,1,$S$2:S15,1)=1),1,0) -> 0 | R15: =IF(AND(N15=1,COUNTIFS($K$2:K15,K15,$L$2:L15,L15,$J$2:J15,J15,$N$2:N15,1)=1),1,0) -> 0 | S15: =IF(AND(K15<>"Context and provider model",K15<>"Motivation"),1,0) -> 0
A16: Stage | B16: Theme | C16: Type | D16: Distinct providers (of 14 Pro) | E16: Cross-cutting across stages? | F16: Which providers (this stage) | G16: Representative observation | H16: Representative quote | J16: ='Raw Atomic Data (Pro)'!A16 -> Andrew | K16: ='Raw Atomic Data (Pro)'!C16 -> Context and provider model | L16: ='Raw Atomic Data (Pro)'!D16 -> capacity-multi-pet-management | M16: ='Raw Atomic Data (Pro)'!E16 -> fact | N16: =IF(OR(M16="friction",M16="need",M16="workaround"),1,0) -> 0 | O16: =IF(COUNTIFS($K$2:K16,K16,$L$2:L16,L16,$M$2:M16,M16,$J$2:J16,J16)=1,1,0) -> 0 | P16: =IF(AND(N16=1,S16=1,COUNTIFS($L$2:L16,L16,$J$2:J16,J16,$N$2:N16,1,$S$2:S16,1)=1),1,0) -> 0 | Q16: =IF(AND(N16=1,S16=1,COUNTIFS($L$2:L16,L16,$K$2:K16,K16,$N$2:N16,1,$S$2:S16,1)=1),1,0) -> 0 | R16: =IF(AND(N16=1,COUNTIFS($K$2:K16,K16,$L$2:L16,L16,$J$2:J16,J16,$N$2:N16,1)=1),1,0) -> 0 | S16: =IF(AND(K16<>"Context and provider model",K16<>"Motivation"),1,0) -> 0
A17: Client acquisition | B17: client-acquisition-discovery | C17: friction | D17: =SUMIFS($O$2:$O$978,$K$2:$K$978,$A17,$L$2:$L$978,$B17,$M$2:$M$978,$C17) -> 2 | E17: =IF(SUMIFS($Q$2:$Q$978,$L$2:$L$978,$B17)>1,"Yes -- also friction/need/workaround in "&(SUMIFS($Q$2:$Q$978,$L$2:$L$978,$B17)-1)&" other stage(s); see Section 3","No -- stage-specific in this dataset") -> Yes -- also friction/need/workaround in 2 other stage(s); see Section 3 | F17: Ashley P., Naomi | G17: [Naomi] A share of Rover message requests don't convert, including people who 'ghost' after messaging, which she says leads her to contact multiple prospects to fill her available slots and can result in overbooking ("there's a lot of people who just have like they'll send a request and it'll never come through so that's why you sometimes end up over booked because you have to talk to multiple people if you want to get to your number"). | H17: there's a lot of people who just have like they'll send a request and it'll never come through so that's why you sometimes end up over booked because you have to talk to multiple people if you want to get to your number | J17: ='Raw Atomic Data (Pro)'!A17 -> Andrew | K17: ='Raw Atomic Data (Pro)'!C17 -> Context and provider model | L17: ='Raw Atomic Data (Pro)'!D17 -> provider-background | M17: ='Raw Atomic Data (Pro)'!E17 -> fact | N17: =IF(OR(M17="friction",M17="need",M17="workaround"),1,0) -> 0 | O17: =IF(COUNTIFS($K$2:K17,K17,$L$2:L17,L17,$M$2:M17,M17,$J$2:J17,J17)=1,1,0) -> 0 | P17: =IF(AND(N17=1,S17=1,COUNTIFS($L$2:L17,L17,$J$2:J17,J17,$N$2:N17,1,$S$2:S17,1)=1),1,0) -> 0 | Q17: =IF(AND(N17=1,S17=1,COUNTIFS($L$2:L17,L17,$K$2:K17,K17,$N$2:N17,1,$S$2:S17,1)=1),1,0) -> 0 | R17: =IF(AND(N17=1,COUNTIFS($K$2:K17,K17,$L$2:L17,L17,$J$2:J17,J17,$N$2:N17,1)=1),1,0) -> 0 | S17: =IF(AND(K17<>"Context and provider model",K17<>"Motivation"),1,0) -> 0
A18: Client acquisition | B18: messaging-platform-mechanics | C18: friction | D18: =SUMIFS($O$2:$O$978,$K$2:$K$978,$A18,$L$2:$L$978,$B18,$M$2:$M$978,$C18) -> 1 | E18: =IF(SUMIFS($Q$2:$Q$978,$L$2:$L$978,$B18)>1,"Yes -- also friction/need/workaround in "&(SUMIFS($Q$2:$Q$978,$L$2:$L$978,$B18)-1)&" other stage(s); see Section 3","No -- stage-specific in this dataset") -> Yes -- also friction/need/workaround in 5 other stage(s); see Section 3 | F18: Andrew | G18: [Andrew] He finds it a little annoying when the app sends an automated/generated first message on a client's behalf, because the client doesn't always know what it says ("I think sometime it does the automated like the generated message like hello I'd like to I was like that's a little annoying because like they don't really know what it says"). | H18: I think sometime it does the automated like the generated message like hello I'd like to I was like that's a little annoying because like they don't really know what it says | J18: ='Raw Atomic Data (Pro)'!A18 -> Andrew | K18: ='Raw Atomic Data (Pro)'!C18 -> Context and provider model | L18: ='Raw Atomic Data (Pro)'!D18 -> provider-background | M18: ='Raw Atomic Data (Pro)'!E18 -> fact | N18: =IF(OR(M18="friction",M18="need",M18="workaround"),1,0) -> 0 | O18: =IF(COUNTIFS($K$2:K18,K18,$L$2:L18,L18,$M$2:M18,M18,$J$2:J18,J18)=1,1,0) -> 0 | P18: =IF(AND(N18=1,S18=1,COUNTIFS($L$2:L18,L18,$J$2:J18,J18,$N$2:N18,1,$S$2:S18,1)=1),1,0) -> 0 | Q18: =IF(AND(N18=1,S18=1,COUNTIFS($L$2:L18,L18,$K$2:K18,K18,$N$2:N18,1,$S$2:S18,1)=1),1,0) -> 0 | R18: =IF(AND(N18=1,COUNTIFS($K$2:K18,K18,$L$2:L18,L18,$J$2:J18,J18,$N$2:N18,1)=1),1,0) -> 0 | S18: =IF(AND(K18<>"Context and provider model",K18<>"Motivation"),1,0) -> 0
A19: Client acquisition | B19: pricing-rate-setting | C19: friction | D19: =SUMIFS($O$2:$O$978,$K$2:$K$978,$A19,$L$2:$L$978,$B19,$M$2:$M$978,$C19) -> 1 | E19: =IF(SUMIFS($Q$2:$Q$978,$L$2:$L$978,$B19)>1,"Yes -- also friction/need/workaround in "&(SUMIFS($Q$2:$Q$978,$L$2:$L$978,$B19)-1)&" other stage(s); see Section 3","No -- stage-specific in this dataset") -> Yes -- also friction/need/workaround in 1 other stage(s); see Section 3 | F19: Bruna | G19: [Bruna] She occasionally gets dog-walking or drop-in requests through Rover but doesn't pursue or advertise that service, saying it's not worth her time given the pay ("it's just time consuming and the tickets not that high... the diversification just not worth it"). | H19: it's just time consuming and the tickets not that high | J19: ='Raw Atomic Data (Pro)'!A19 -> Andrew | K19: ='Raw Atomic Data (Pro)'!C19 -> Context and provider model | L19: ='Raw Atomic Data (Pro)'!D19 -> provider-background | M19: ='Raw Atomic Data (Pro)'!E19 -> fact | N19: =IF(OR(M19="friction",M19="need",M19="workaround"),1,0) -> 0 | O19: =IF(COUNTIFS($K$2:K19,K19,$L$2:L19,L19,$M$2:M19,M19,$J$2:J19,J19)=1,1,0) -> 0 | P19: =IF(AND(N19=1,S19=1,COUNTIFS($L$2:L19,L19,$J$2:J19,J19,$N$2:N19,1,$S$2:S19,1)=1),1,0) -> 0 | Q19: =IF(AND(N19=1,S19=1,COUNTIFS($L$2:L19,L19,$K$2:K19,K19,$N$2:N19,1,$S$2:S19,1)=1),1,0) -> 0 | R19: =IF(AND(N19=1,COUNTIFS($K$2:K19,K19,$L$2:L19,L19,$J$2:J19,J19,$N$2:N19,1)=1),1,0) -> 0 | S19: =IF(AND(K19<>"Context and provider model",K19<>"Motivation"),1,0) -> 0
A20: Client acquisition | B20: search-ranking-visibility | C20: friction | D20: =SUMIFS($O$2:$O$978,$K$2:$K$978,$A20,$L$2:$L$978,$B20,$M$2:$M$978,$C20) -> 1 | E20: =IF(SUMIFS($Q$2:$Q$978,$L$2:$L$978,$B20)>1,"Yes -- also friction/need/workaround in "&(SUMIFS($Q$2:$Q$978,$L$2:$L$978,$B20)-1)&" other stage(s); see Section 3","No -- stage-specific in this dataset") -> Yes -- also friction/need/workaround in 2 other stage(s); see Section 3 | F20: Tianrui | G20: [Tianrui] As a new sitter, TR found themselves ranked around 20th to 30th in Rover's search results, which they say most clients never scroll far enough to see ("I was like rank 20 at like 30 something like that which is pretty difficult to see because most people will not scroll down all the way to like second third page to see me"). | H20: I was like rank 20 at like 30 something like that which is pretty difficult to see because most people will not scroll down all the way to like second third page to see me | J20: ='Raw Atomic Data (Pro)'!A20 -> Anita | K20: ='Raw Atomic Data (Pro)'!C20 -> Context and provider model | L20: ='Raw Atomic Data (Pro)'!D20 -> provider-background | M20: ='Raw Atomic Data (Pro)'!E20 -> fact | N20: =IF(OR(M20="friction",M20="need",M20="workaround"),1,0) -> 0 | O20: =IF(COUNTIFS($K$2:K20,K20,$L$2:L20,L20,$M$2:M20,M20,$J$2:J20,J20)=1,1,0) -> 1 | P20: =IF(AND(N20=1,S20=1,COUNTIFS($L$2:L20,L20,$J$2:J20,J20,$N$2:N20,1,$S$2:S20,1)=1),1,0) -> 0 | Q20: =IF(AND(N20=1,S20=1,COUNTIFS($L$2:L20,L20,$K$2:K20,K20,$N$2:N20,1,$S$2:S20,1)=1),1,0) -> 0 | R20: =IF(AND(N20=1,COUNTIFS($K$2:K20,K20,$L$2:L20,L20,$J$2:J20,J20,$N$2:N20,1)=1),1,0) -> 0 | S20: =IF(AND(K20<>"Context and provider model",K20<>"Motivation"),1,0) -> 0
A21: Client acquisition | B21: profile-information-completeness | C21: need | D21: =SUMIFS($O$2:$O$978,$K$2:$K$978,$A21,$L$2:$L$978,$B21,$M$2:$M$978,$C21) -> 1 | E21: =IF(SUMIFS($Q$2:$Q$978,$L$2:$L$978,$B21)>1,"Yes -- also friction/need/workaround in "&(SUMIFS($Q$2:$Q$978,$L$2:$L$978,$B21)-1)&" other stage(s); see Section 3","No -- stage-specific in this dataset") -> Yes -- also friction/need/workaround in 2 other stage(s); see Section 3 | F21: Becky | G21: [Becky] Her suggested improvement at this stage is making some profile information mandatory so it isn't a completely blank dog intro ("making some of the information on the profile mandatory so it's not like a completely blank um dog intro."). | H21: making some of the information on the profile mandatory so it's not like a completely blank um dog intro. | J21: ='Raw Atomic Data (Pro)'!A21 -> Anita | K21: ='Raw Atomic Data (Pro)'!C21 -> Context and provider model | L21: ='Raw Atomic Data (Pro)'!D21 -> provider-background | M21: ='Raw Atomic Data (Pro)'!E21 -> fact | N21: =IF(OR(M21="friction",M21="need",M21="workaround"),1,0) -> 0 | O21: =IF(COUNTIFS($K$2:K21,K21,$L$2:L21,L21,$M$2:M21,M21,$J$2:J21,J21)=1,1,0) -> 0 | P21: =IF(AND(N21=1,S21=1,COUNTIFS($L$2:L21,L21,$J$2:J21,J21,$N$2:N21,1,$S$2:S21,1)=1),1,0) -> 0 | Q21: =IF(AND(N21=1,S21=1,COUNTIFS($L$2:L21,L21,$K$2:K21,K21,$N$2:N21,1,$S$2:S21,1)=1),1,0) -> 0 | R21: =IF(AND(N21=1,COUNTIFS($K$2:K21,K21,$L$2:L21,L21,$J$2:J21,J21,$N$2:N21,1)=1),1,0) -> 0 | S21: =IF(AND(K21<>"Context and provider model",K21<>"Motivation"),1,0) -> 0
A22: Client acquisition | B22: search-ranking-visibility | C22: need | D22: =SUMIFS($O$2:$O$978,$K$2:$K$978,$A22,$L$2:$L$978,$B22,$M$2:$M$978,$C22) -> 1 | E22: =IF(SUMIFS($Q$2:$Q$978,$L$2:$L$978,$B22)>1,"Yes -- also friction/need/workaround in "&(SUMIFS($Q$2:$Q$978,$L$2:$L$978,$B22)-1)&" other stage(s); see Section 3","No -- stage-specific in this dataset") -> Yes -- also friction/need/workaround in 2 other stage(s); see Section 3 | F22: Tianrui | G22: [Tianrui] TR wishes Rover would periodically feature new sitters on the first results page instead of ranking almost entirely by reviews, repeat clients, and profile-update frequency ("if Rover can randomly put some new sitters on the first page, you probably going to be help a lot"). | H22: if Rover can randomly put some new sitters on the first page, you probably going to be help a lot | J22: ='Raw Atomic Data (Pro)'!A22 -> Anita | K22: ='Raw Atomic Data (Pro)'!C22 -> Context and provider model | L22: ='Raw Atomic Data (Pro)'!D22 -> provider-background | M22: ='Raw Atomic Data (Pro)'!E22 -> need | N22: =IF(OR(M22="friction",M22="need",M22="workaround"),1,0) -> 1 | O22: =IF(COUNTIFS($K$2:K22,K22,$L$2:L22,L22,$M$2:M22,M22,$J$2:J22,J22)=1,1,0) -> 1 | P22: =IF(AND(N22=1,S22=1,COUNTIFS($L$2:L22,L22,$J$2:J22,J22,$N$2:N22,1,$S$2:S22,1)=1),1,0) -> 0 | Q22: =IF(AND(N22=1,S22=1,COUNTIFS($L$2:L22,L22,$K$2:K22,K22,$N$2:N22,1,$S$2:S22,1)=1),1,0) -> 0 | R22: =IF(AND(N22=1,COUNTIFS($K$2:K22,K22,$L$2:L22,L22,$J$2:J22,J22,$N$2:N22,1)=1),1,0) -> 1 | S22: =IF(AND(K22<>"Context and provider model",K22<>"Motivation"),1,0) -> 0
A23: Client acquisition | B23: booking-confirmation-mechanics | C23: workaround | D23: =SUMIFS($O$2:$O$978,$K$2:$K$978,$A23,$L$2:$L$978,$B23,$M$2:$M$978,$C23) -> 1 | E23: =IF(SUMIFS($Q$2:$Q$978,$L$2:$L$978,$B23)>1,"Yes -- also friction/need/workaround in "&(SUMIFS($Q$2:$Q$978,$L$2:$L$978,$B23)-1)&" other stage(s); see Section 3","No -- stage-specific in this dataset") -> Yes -- also friction/need/workaround in 2 other stage(s); see Section 3 | F23: Dawn | G23: [Dawn] If someone reaches out about a booking far in the future without firm dates, she asks them to archive the conversation and contact her again once they have specific dates, so the inquiry doesn't sit on her calendar prematurely ("I will want them to archive it or whatever and contact me later so it doesn't like mess up my calendar"). | H23: I will want them to archive it or whatever and contact me later so it doesn't like mess up my calendar | J23: ='Raw Atomic Data (Pro)'!A23 -> Anita | K23: ='Raw Atomic Data (Pro)'!C23 -> Context and provider model | L23: ='Raw Atomic Data (Pro)'!D23 -> provider-background | M23: ='Raw Atomic Data (Pro)'!E23 -> fact | N23: =IF(OR(M23="friction",M23="need",M23="workaround"),1,0) -> 0 | O23: =IF(COUNTIFS($K$2:K23,K23,$L$2:L23,L23,$M$2:M23,M23,$J$2:J23,J23)=1,1,0) -> 0 | P23: =IF(AND(N23=1,S23=1,COUNTIFS($L$2:L23,L23,$J$2:J23,J23,$N$2:N23,1,$S$2:S23,1)=1),1,0) -> 0 | Q23: =IF(AND(N23=1,S23=1,COUNTIFS($L$2:L23,L23,$K$2:K23,K23,$N$2:N23,1,$S$2:S23,1)=1),1,0) -> 0 | R23: =IF(AND(N23=1,COUNTIFS($K$2:K23,K23,$L$2:L23,L23,$J$2:J23,J23,$N$2:N23,1)=1),1,0) -> 0 | S23: =IF(AND(K23<>"Context and provider model",K23<>"Motivation"),1,0) -> 0
A24: Client acquisition | B24: client-acquisition-discovery | C24: workaround | D24: =SUMIFS($O$2:$O$978,$K$2:$K$978,$A24,$L$2:$L$978,$B24,$M$2:$M$978,$C24) -> 1 | E24: =IF(SUMIFS($Q$2:$Q$978,$L$2:$L$978,$B24)>1,"Yes -- also friction/need/workaround in "&(SUMIFS($Q$2:$Q$978,$L$2:$L$978,$B24)-1)&" other stage(s); see Section 3","No -- stage-specific in this dataset") -> Yes -- also friction/need/workaround in 2 other stage(s); see Section 3 | F24: Tianrui | G24: [Tianrui] For new-client inquiries, TR uses a standardized, pre-written response saved in a notebook that they copy and paste ("I actually prepared a standardized language I use for them like I put into a notebook"). | H24: I actually prepared a standardized language I use for them like I put into a notebook | J24: ='Raw Atomic Data (Pro)'!A24 -> Anita | K24: ='Raw Atomic Data (Pro)'!C24 -> Context and provider model | L24: ='Raw Atomic Data (Pro)'!D24 -> provider-background | M24: ='Raw Atomic Data (Pro)'!E24 -> fact | N24: =IF(OR(M24="friction",M24="need",M24="workaround"),1,0) -> 0 | O24: =IF(COUNTIFS($K$2:K24,K24,$L$2:L24,L24,$M$2:M24,M24,$J$2:J24,J24)=1,1,0) -> 0 | P24: =IF(AND(N24=1,S24=1,COUNTIFS($L$2:L24,L24,$J$2:J24,J24,$N$2:N24,1,$S$2:S24,1)=1),1,0) -> 0 | Q24: =IF(AND(N24=1,S24=1,COUNTIFS($L$2:L24,L24,$K$2:K24,K24,$N$2:N24,1,$S$2:S24,1)=1),1,0) -> 0 | R24: =IF(AND(N24=1,COUNTIFS($K$2:K24,K24,$L$2:L24,L24,$J$2:J24,J24,$N$2:N24,1)=1),1,0) -> 0 | S24: =IF(AND(K24<>"Context and provider model",K24<>"Motivation"),1,0) -> 0
A25: Client acquisition | B25: search-ranking-visibility | C25: workaround | D25: =SUMIFS($O$2:$O$978,$K$2:$K$978,$A25,$L$2:$L$978,$B25,$M$2:$M$978,$C25) -> 1 | E25: =IF(SUMIFS($Q$2:$Q$978,$L$2:$L$978,$B25)>1,"Yes -- also friction/need/workaround in "&(SUMIFS($Q$2:$Q$978,$L$2:$L$978,$B25)-1)&" other stage(s); see Section 3","No -- stage-specific in this dataset") -> Yes -- also friction/need/workaround in 2 other stage(s); see Section 3 | F25: Tianrui | G25: [Tianrui] TR looked at Rover from the client side to understand how the search ranking worked, which is how they identified that ranking depends heavily on reviews, repeat clients, and calendar-update frequency ("I actually try to uh use Rover from the client side and then I realized Rover do rank people like uh first one, second one, third one"). | H25: I actually try to uh use Rover from the client side and then I realized Rover do rank people like uh first one, second one, third one | J25: ='Raw Atomic Data (Pro)'!A25 -> Anita | K25: ='Raw Atomic Data (Pro)'!C25 -> Context and provider model | L25: ='Raw Atomic Data (Pro)'!D25 -> business-model-fit | M25: ='Raw Atomic Data (Pro)'!E25 -> fact | N25: =IF(OR(M25="friction",M25="need",M25="workaround"),1,0) -> 0 | O25: =IF(COUNTIFS($K$2:K25,K25,$L$2:L25,L25,$M$2:M25,M25,$J$2:J25,J25)=1,1,0) -> 1 | P25: =IF(AND(N25=1,S25=1,COUNTIFS($L$2:L25,L25,$J$2:J25,J25,$N$2:N25,1,$S$2:S25,1)=1),1,0) -> 0 | Q25: =IF(AND(N25=1,S25=1,COUNTIFS($L$2:L25,L25,$K$2:K25,K25,$N$2:N25,1,$S$2:S25,1)=1),1,0) -> 0 | R25: =IF(AND(N25=1,COUNTIFS($K$2:K25,K25,$L$2:L25,L25,$J$2:J25,J25,$N$2:N25,1)=1),1,0) -> 0 | S25: =IF(AND(K25<>"Context and provider model",K25<>"Motivation"),1,0) -> 0
A26: Evaluation and meet-and-greet | B26: safety-risk-incidents | C26: friction | D26: =SUMIFS($O$2:$O$978,$K$2:$K$978,$A26,$L$2:$L$978,$B26,$M$2:$M$978,$C26) -> 2 | E26: =IF(SUMIFS($Q$2:$Q$978,$L$2:$L$978,$B26)>1,"Yes -- also friction/need/workaround in "&(SUMIFS($Q$2:$Q$978,$L$2:$L$978,$B26)-1)&" other stage(s); see Section 3","No -- stage-specific in this dataset") -> Yes -- also friction/need/workaround in 4 other stage(s); see Section 3 | F26: Anita, Naomi | G26: [Anita] She described one meet-and-greet where an older, unsocialized dog attacked her, and she believed the owner was trying to get rid of the dog rather than find genuine care ("The dog was older and aggressive and as soon as I got there, he attacked me"; "it was a bad owner. They were trying to dump the dog"). | H26: it was a bad owner. They were trying to dump the dog | J26: ='Raw Atomic Data (Pro)'!A26 -> Anita | K26: ='Raw Atomic Data (Pro)'!C26 -> Context and provider model | L26: ='Raw Atomic Data (Pro)'!D26 -> provider-background | M26: ='Raw Atomic Data (Pro)'!E26 -> fact | N26: =IF(OR(M26="friction",M26="need",M26="workaround"),1,0) -> 0 | O26: =IF(COUNTIFS($K$2:K26,K26,$L$2:L26,L26,$M$2:M26,M26,$J$2:J26,J26)=1,1,0) -> 0 | P26: =IF(AND(N26=1,S26=1,COUNTIFS($L$2:L26,L26,$J$2:J26,J26,$N$2:N26,1,$S$2:S26,1)=1),1,0) -> 0 | Q26: =IF(AND(N26=1,S26=1,COUNTIFS($L$2:L26,L26,$K$2:K26,K26,$N$2:N26,1,$S$2:S26,1)=1),1,0) -> 0 | R26: =IF(AND(N26=1,COUNTIFS($K$2:K26,K26,$L$2:L26,L26,$J$2:J26,J26,$N$2:N26,1)=1),1,0) -> 0 | S26: =IF(AND(K26<>"Context and provider model",K26<>"Motivation"),1,0) -> 0
A27: Evaluation and meet-and-greet | B27: care-instructions-handoff | C27: friction | D27: =SUMIFS($O$2:$O$978,$K$2:$K$978,$A27,$L$2:$L$978,$B27,$M$2:$M$978,$C27) -> 1 | E27: =IF(SUMIFS($Q$2:$Q$978,$L$2:$L$978,$B27)>1,"Yes -- also friction/need/workaround in "&(SUMIFS($Q$2:$Q$978,$L$2:$L$978,$B27)-1)&" other stage(s); see Section 3","No -- stage-specific in this dataset") -> Yes -- also friction/need/workaround in 2 other stage(s); see Section 3 | F27: Kristin | G27: [Kristin] She says most clients going on vacation don't have the most important information (food, meds, leashes, vet) organized in one place, so she also asks about lower-priority preferences like a pet's favorite toy or bed, or where a cat likes to hide ("most people when they're going on vacation don't get all these things prepared in one location and those are the most important. But then like offsides like their favorite toy, their favorite bed... where they like to hide"). | H27: most people when they're going on vacation don't get all these things prepared in one location and those are the most important. But then like offsides like their favorite toy, their favorite bed | J27: ='Raw Atomic Data (Pro)'!A27 -> Anita | K27: ='Raw Atomic Data (Pro)'!C27 -> Context and provider model | L27: ='Raw Atomic Data (Pro)'!D27 -> repeat-client-relationships | M27: ='Raw Atomic Data (Pro)'!E27 -> fact | N27: =IF(OR(M27="friction",M27="need",M27="workaround"),1,0) -> 0 | O27: =IF(COUNTIFS($K$2:K27,K27,$L$2:L27,L27,$M$2:M27,M27,$J$2:J27,J27)=1,1,0) -> 1 | P27: =IF(AND(N27=1,S27=1,COUNTIFS($L$2:L27,L27,$J$2:J27,J27,$N$2:N27,1,$S$2:S27,1)=1),1,0) -> 0 | Q27: =IF(AND(N27=1,S27=1,COUNTIFS($L$2:L27,L27,$K$2:K27,K27,$N$2:N27,1,$S$2:S27,1)=1),1,0) -> 0 | R27: =IF(AND(N27=1,COUNTIFS($K$2:K27,K27,$L$2:L27,L27,$J$2:J27,J27,$N$2:N27,1)=1),1,0) -> 0 | S27: =IF(AND(K27<>"Context and provider model",K27<>"Motivation"),1,0) -> 0
A28: Evaluation and meet-and-greet | B28: client-dog-screening-criteria | C28: friction | D28: =SUMIFS($O$2:$O$978,$K$2:$K$978,$A28,$L$2:$L$978,$B28,$M$2:$M$978,$C28) -> 1 | E28: =IF(SUMIFS($Q$2:$Q$978,$L$2:$L$978,$B28)>1,"Yes -- also friction/need/workaround in "&(SUMIFS($Q$2:$Q$978,$L$2:$L$978,$B28)-1)&" other stage(s); see Section 3","No -- stage-specific in this dataset") -> No -- stage-specific in this dataset | F28: Kristin | G28: [Kristin] Deciding to decline a client or dog that's not a good fit was hard for her early on; she believes "Not all not all money is good money." and thinks Rover could help newer sitters with this by framing it as acceptable and normal. | H28: Not all not all money is good money. | J28: ='Raw Atomic Data (Pro)'!A28 -> Becky | K28: ='Raw Atomic Data (Pro)'!C28 -> Context and provider model | L28: ='Raw Atomic Data (Pro)'!D28 -> provider-background | M28: ='Raw Atomic Data (Pro)'!E28 -> fact | N28: =IF(OR(M28="friction",M28="need",M28="workaround"),1,0) -> 0 | O28: =IF(COUNTIFS($K$2:K28,K28,$L$2:L28,L28,$M$2:M28,M28,$J$2:J28,J28)=1,1,0) -> 1 | P28: =IF(AND(N28=1,S28=1,COUNTIFS($L$2:L28,L28,$J$2:J28,J28,$N$2:N28,1,$S$2:S28,1)=1),1,0) -> 0 | Q28: =IF(AND(N28=1,S28=1,COUNTIFS($L$2:L28,L28,$K$2:K28,K28,$N$2:N28,1,$S$2:S28,1)=1),1,0) -> 0 | R28: =IF(AND(N28=1,COUNTIFS($K$2:K28,K28,$L$2:L28,L28,$J$2:J28,J28,$N$2:N28,1)=1),1,0) -> 0 | S28: =IF(AND(K28<>"Context and provider model",K28<>"Motivation"),1,0) -> 0
... A102: Growth and future plans | B102: sitter-community-network | C102: need | D102: =SUMIFS($O$2:$O$978,$K$2:$K$978,$A102,$L$2:$L$978,$B102,$M$2:$M$978,$C102) -> 2 | E102: =IF(SUMIFS($Q$2:$Q$978,$L$2:$L$978,$B102)>1,"Yes -- also friction/need/workaround in "&(SUMIFS($Q$2:$Q$978,$L$2:$L$978,$B102)-1)&" other stage(s); see Section 3","No -- stage-specific in this dataset") -> No -- stage-specific in this dataset | F102: Bruna, Kristin | G102: [Bruna] She thinks a Rover networking/community feature for sitters would be valuable for sharing knowledge about handling difficult cases, such as dogs with separation anxiety or pacing ("I think a community would be great"). | H102: I think a community would be great | J102: ='Raw Atomic Data (Pro)'!A102 -> Tianrui | K102: ='Raw Atomic Data (Pro)'!C102 -> Context and provider model | L102: ='Raw Atomic Data (Pro)'!D102 -> provider-background | M102: ='Raw Atomic Data (Pro)'!E102 -> fact | N102: =IF(OR(M102="friction",M102="need",M102="workaround"),1,0) -> 0 | O102: =IF(COUNTIFS($K$2:K102,K102,$L$2:L102,L102,$M$2:M102,M102,$J$2:J102,J102)=1,1,0) -> 0 | P102: =IF(AND(N102=1,S102=1,COUNTIFS($L$2:L102,L102,$J$2:J102,J102,$N$2:N102,1,$S$2:S102,1)=1),1,0) -> 0 | Q102: =IF(AND(N102=1,S102=1,COUNTIFS($L$2:L102,L102,$K$2:K102,K102,$N$2:N102,1,$S$2:S102,1)=1),1,0) -> 0 | R102: =IF(AND(N102=1,COUNTIFS($K$2:K102,K102,$L$2:L102,L102,$J$2:J102,J102,$N$2:N102,1)=1),1,0) -> 0 | S102: =IF(AND(K102<>"Context and provider model",K102<>"Motivation"),1,0) -> 0
A103: Growth and future plans | B103: calendar-scheduling-tools | C103: need | D103: =SUMIFS($O$2:$O$978,$K$2:$K$978,$A103,$L$2:$L$978,$B103,$M$2:$M$978,$C103) -> 1 | E103: =IF(SUMIFS($Q$2:$Q$978,$L$2:$L$978,$B103)>1,"Yes -- also friction/need/workaround in "&(SUMIFS($Q$2:$Q$978,$L$2:$L$978,$B103)-1)&" other stage(s); see Section 3","No -- stage-specific in this dataset") -> Yes -- also friction/need/workaround in 1 other stage(s); see Section 3 | F103: Tifany | G103: [Tifany] Part of her ideal platform includes a visually clearer calendar tool that shows what type of booking is blocking a given day, a request covered in full under Booking and availability. | J103: ='Raw Atomic Data (Pro)'!A103 -> Tianrui | K103: ='Raw Atomic Data (Pro)'!C103 -> Context and provider model | L103: ='Raw Atomic Data (Pro)'!D103 -> repeat-client-relationships | M103: ='Raw Atomic Data (Pro)'!E103 -> fact | N103: =IF(OR(M103="friction",M103="need",M103="workaround"),1,0) -> 0 | O103: =IF(COUNTIFS($K$2:K103,K103,$L$2:L103,L103,$M$2:M103,M103,$J$2:J103,J103)=1,1,0) -> 1 | P103: =IF(AND(N103=1,S103=1,COUNTIFS($L$2:L103,L103,$J$2:J103,J103,$N$2:N103,1,$S$2:S103,1)=1),1,0) -> 0 | Q103: =IF(AND(N103=1,S103=1,COUNTIFS($L$2:L103,L103,$K$2:K103,K103,$N$2:N103,1,$S$2:S103,1)=1),1,0) -> 0 | R103: =IF(AND(N103=1,COUNTIFS($K$2:K103,K103,$L$2:L103,L103,$J$2:J103,J103,$N$2:N103,1)=1),1,0) -> 0 | S103: =IF(AND(K103<>"Context and provider model",K103<>"Motivation"),1,0) -> 0
A104: Growth and future plans | B104: daily-care-tasks | C104: need | D104: =SUMIFS($O$2:$O$978,$K$2:$K$978,$A104,$L$2:$L$978,$B104,$M$2:$M$978,$C104) -> 1 | E104: =IF(SUMIFS($Q$2:$Q$978,$L$2:$L$978,$B104)>1,"Yes -- also friction/need/workaround in "&(SUMIFS($Q$2:$Q$978,$L$2:$L$978,$B104)-1)&" other stage(s); see Section 3","No -- stage-specific in this dataset") -> Yes -- also friction/need/workaround in 2 other stage(s); see Section 3 | F104: Ashley P. | G104: [Ashley P.] She'd want more flexible or shorter check-in visit lengths available for low-maintenance pets instead of being locked into a fixed visit duration, a point detailed further under Service delivery ("having a different option for that kind of check-in I think would be something that I would change for sure like in my petsitting app."). | H104: having a different option for that kind of check-in I think would be something that I would change for sure like in my petsitting app. | J104: ='Raw Atomic Data (Pro)'!A104 -> Tianrui | K104: ='Raw Atomic Data (Pro)'!C104 -> Context and provider model | L104: ='Raw Atomic Data (Pro)'!D104 -> provider-background | M104: ='Raw Atomic Data (Pro)'!E104 -> fact | N104: =IF(OR(M104="friction",M104="need",M104="workaround"),1,0) -> 0 | O104: =IF(COUNTIFS($K$2:K104,K104,$L$2:L104,L104,$M$2:M104,M104,$J$2:J104,J104)=1,1,0) -> 0 | P104: =IF(AND(N104=1,S104=1,COUNTIFS($L$2:L104,L104,$J$2:J104,J104,$N$2:N104,1,$S$2:S104,1)=1),1,0) -> 0 | Q104: =IF(AND(N104=1,S104=1,COUNTIFS($L$2:L104,L104,$K$2:K104,K104,$N$2:N104,1,$S$2:S104,1)=1),1,0) -> 0 | R104: =IF(AND(N104=1,COUNTIFS($K$2:K104,K104,$L$2:L104,L104,$J$2:J104,J104,$N$2:N104,1)=1),1,0) -> 0 | S104: =IF(AND(K104<>"Context and provider model",K104<>"Motivation"),1,0) -> 0
A105: Growth and future plans | B105: payout-timing-tracking | C105: need | D105: =SUMIFS($O$2:$O$978,$K$2:$K$978,$A105,$L$2:$L$978,$B105,$M$2:$M$978,$C105) -> 1 | E105: =IF(SUMIFS($Q$2:$Q$978,$L$2:$L$978,$B105)>1,"Yes -- also friction/need/workaround in "&(SUMIFS($Q$2:$Q$978,$L$2:$L$978,$B105)-1)&" other stage(s); see Section 3","No -- stage-specific in this dataset") -> Yes -- also friction/need/workaround in 2 other stage(s); see Section 3 | F105: Tifany | G105: [Tifany] She envisions an ideal platform with much faster payouts, released within about 24 hours instead of the current delay, which she describes as usually around five days though it has varied (see Payments and earnings for detail). | J105: ='Raw Atomic Data (Pro)'!A105 -> Tianrui | K105: ='Raw Atomic Data (Pro)'!C105 -> Context and provider model | L105: ='Raw Atomic Data (Pro)'!D105 -> provider-background | M105: ='Raw Atomic Data (Pro)'!E105 -> fact | N105: =IF(OR(M105="friction",M105="need",M105="workaround"),1,0) -> 0 | O105: =IF(COUNTIFS($K$2:K105,K105,$L$2:L105,L105,$M$2:M105,M105,$J$2:J105,J105)=1,1,0) -> 0 | P105: =IF(AND(N105=1,S105=1,COUNTIFS($L$2:L105,L105,$J$2:J105,J105,$N$2:N105,1,$S$2:S105,1)=1),1,0) -> 0 | Q105: =IF(AND(N105=1,S105=1,COUNTIFS($L$2:L105,L105,$K$2:K105,K105,$N$2:N105,1,$S$2:S105,1)=1),1,0) -> 0 | R105: =IF(AND(N105=1,COUNTIFS($K$2:K105,K105,$L$2:L105,L105,$J$2:J105,J105,$N$2:N105,1)=1),1,0) -> 0 | S105: =IF(AND(K105<>"Context and provider model",K105<>"Motivation"),1,0) -> 0
A106: Growth and future plans | B106: reviews-feedback-process | C106: need | D106: =SUMIFS($O$2:$O$978,$K$2:$K$978,$A106,$L$2:$L$978,$B106,$M$2:$M$978,$C106) -> 1 | E106: =IF(SUMIFS($Q$2:$Q$978,$L$2:$L$978,$B106)>1,"Yes -- also friction/need/workaround in "&(SUMIFS($Q$2:$Q$978,$L$2:$L$978,$B106)-1)&" other stage(s); see Section 3","No -- stage-specific in this dataset") -> Yes -- also friction/need/workaround in 1 other stage(s); see Section 3 | F106: Tianrui | G106: [Tianrui] For the future, TR would like Rover itself to incentivize clients (e.g. with a discount) to leave reviews, so that sitters aren't the ones having to offer discounts to get reviews ("I hope the platform can offer incentive for the clients be like all right uh leave the review for the sitter and then we can like next time we can give you like a more some kind of discounts"). | H106: I hope the platform can offer incentive for the clients be like all right uh leave the review for the sitter and then we can like next time we can give you like a more some kind of discounts | J106: ='Raw Atomic Data (Pro)'!A106 -> Tianrui | K106: ='Raw Atomic Data (Pro)'!C106 -> Context and provider model | L106: ='Raw Atomic Data (Pro)'!D106 -> provider-background | M106: ='Raw Atomic Data (Pro)'!E106 -> fact | N106: =IF(OR(M106="friction",M106="need",M106="workaround"),1,0) -> 0 | O106: =IF(COUNTIFS($K$2:K106,K106,$L$2:L106,L106,$M$2:M106,M106,$J$2:J106,J106)=1,1,0) -> 0 | P106: =IF(AND(N106=1,S106=1,COUNTIFS($L$2:L106,L106,$J$2:J106,J106,$N$2:N106,1,$S$2:S106,1)=1),1,0) -> 0 | Q106: =IF(AND(N106=1,S106=1,COUNTIFS($L$2:L106,L106,$K$2:K106,K106,$N$2:N106,1,$S$2:S106,1)=1),1,0) -> 0 | R106: =IF(AND(N106=1,COUNTIFS($K$2:K106,K106,$L$2:L106,L106,$J$2:J106,J106,$N$2:N106,1)=1),1,0) -> 0 | S106: =IF(AND(K106<>"Context and provider model",K106<>"Motivation"),1,0) -> 0
A107: Growth and future plans | B107: safety-risk-incidents | C107: need | D107: =SUMIFS($O$2:$O$978,$K$2:$K$978,$A107,$L$2:$L$978,$B107,$M$2:$M$978,$C107) -> 1 | E107: =IF(SUMIFS($Q$2:$Q$978,$L$2:$L$978,$B107)>1,"Yes -- also friction/need/workaround in "&(SUMIFS($Q$2:$Q$978,$L$2:$L$978,$B107)-1)&" other stage(s); see Section 3","No -- stage-specific in this dataset") -> Yes -- also friction/need/workaround in 4 other stage(s); see Section 3 | F107: Tianrui | G107: [Tianrui] TR wants more sitter-protective safety features, such as a dedicated call/support line sitters could use if something comes up during a sit, given the risk of having shared their address ("maybe like some calling and then more ready call line would be better for the sitter in which like anything come up they can just like call and then figure out the way"). | H107: maybe like some calling and then more ready call line would be better for the sitter | J107: ='Raw Atomic Data (Pro)'!A107 -> Tianrui | K107: ='Raw Atomic Data (Pro)'!C107 -> Context and provider model | L107: ='Raw Atomic Data (Pro)'!D107 -> motivation-emotional-connection | M107: ='Raw Atomic Data (Pro)'!E107 -> fact | N107: =IF(OR(M107="friction",M107="need",M107="workaround"),1,0) -> 0 | O107: =IF(COUNTIFS($K$2:K107,K107,$L$2:L107,L107,$M$2:M107,M107,$J$2:J107,J107)=1,1,0) -> 1 | P107: =IF(AND(N107=1,S107=1,COUNTIFS($L$2:L107,L107,$J$2:J107,J107,$N$2:N107,1,$S$2:S107,1)=1),1,0) -> 0 | Q107: =IF(AND(N107=1,S107=1,COUNTIFS($L$2:L107,L107,$K$2:K107,K107,$N$2:N107,1,$S$2:S107,1)=1),1,0) -> 0 | R107: =IF(AND(N107=1,COUNTIFS($K$2:K107,K107,$L$2:L107,L107,$J$2:J107,J107,$N$2:N107,1)=1),1,0) -> 0 | S107: =IF(AND(K107<>"Context and provider model",K107<>"Motivation"),1,0) -> 0
A108: Growth and future plans | B108: search-ranking-visibility | C108: need | D108: =SUMIFS($O$2:$O$978,$K$2:$K$978,$A108,$L$2:$L$978,$B108,$M$2:$M$978,$C108) -> 1 | E108: =IF(SUMIFS($Q$2:$Q$978,$L$2:$L$978,$B108)>1,"Yes -- also friction/need/workaround in "&(SUMIFS($Q$2:$Q$978,$L$2:$L$978,$B108)-1)&" other stage(s); see Section 3","No -- stage-specific in this dataset") -> Yes -- also friction/need/workaround in 2 other stage(s); see Section 3 | F108: Tianrui | G108: [Tianrui] TR would like a feature letting sitters indicate whether they want more clients or are satisfied with their current volume, which would raise or lower their platform ranking accordingly, rather than a sitter's rank dropping simply because they decline bookings ("if the sitter choose like oh I'm really happy with that right now no more new clients I'm done and then a thinking rover can just like lower the rank of this person a little bit more... for those who thinking that they can take more they can just like fill up saying like oh yeah I'm down to take more give me more like that then they can like even higher up the rank"). | H108: if the sitter choose like oh I'm really happy with that right now no more new clients I'm done | J108: ='Raw Atomic Data (Pro)'!A108 -> Tianrui | K108: ='Raw Atomic Data (Pro)'!C108 -> Context and provider model | L108: ='Raw Atomic Data (Pro)'!D108 -> motivation-emotional-connection | M108: ='Raw Atomic Data (Pro)'!E108 -> value-statement | N108: =IF(OR(M108="friction",M108="need",M108="workaround"),1,0) -> 0 | O108: =IF(COUNTIFS($K$2:K108,K108,$L$2:L108,L108,$M$2:M108,M108,$J$2:J108,J108)=1,1,0) -> 1 | P108: =IF(AND(N108=1,S108=1,COUNTIFS($L$2:L108,L108,$J$2:J108,J108,$N$2:N108,1,$S$2:S108,1)=1),1,0) -> 0 | Q108: =IF(AND(N108=1,S108=1,COUNTIFS($L$2:L108,L108,$K$2:K108,K108,$N$2:N108,1,$S$2:S108,1)=1),1,0) -> 0 | R108: =IF(AND(N108=1,COUNTIFS($K$2:K108,K108,$L$2:L108,L108,$J$2:J108,J108,$N$2:N108,1)=1),1,0) -> 0 | S108: =IF(AND(K108<>"Context and provider model",K108<>"Motivation"),1,0) -> 0
A109: Growth and future plans | B109: sitter-support-resources | C109: need | D109: =SUMIFS($O$2:$O$978,$K$2:$K$978,$A109,$L$2:$L$978,$B109,$M$2:$M$978,$C109) -> 1 | E109: =IF(SUMIFS($Q$2:$Q$978,$L$2:$L$978,$B109)>1,"Yes -- also friction/need/workaround in "&(SUMIFS($Q$2:$Q$978,$L$2:$L$978,$B109)-1)&" other stage(s); see Section 3","No -- stage-specific in this dataset") -> Yes -- also friction/need/workaround in 2 other stage(s); see Section 3 | F109: Ami | G109: [Ami] She'd find a quick-reference format for training content useful, even something as simple as a single-sheet PDF listing signs to watch for, like stress or overheating signals ("12 signs of uh stress in in animals" and "a a a single sheet PDF, you know, just being able to access and go"). | H109: a a a single sheet PDF, you know, just being able to access and go | J109: ='Raw Atomic Data (Pro)'!A109 -> Tifany | K109: ='Raw Atomic Data (Pro)'!C109 -> Context and provider model | L109: ='Raw Atomic Data (Pro)'!D109 -> provider-background | M109: ='Raw Atomic Data (Pro)'!E109 -> fact | N109: =IF(OR(M109="friction",M109="need",M109="workaround"),1,0) -> 0 | O109: =IF(COUNTIFS($K$2:K109,K109,$L$2:L109,L109,$M$2:M109,M109,$J$2:J109,J109)=1,1,0) -> 1 | P109: =IF(AND(N109=1,S109=1,COUNTIFS($L$2:L109,L109,$J$2:J109,J109,$N$2:N109,1,$S$2:S109,1)=1),1,0) -> 0 | Q109: =IF(AND(N109=1,S109=1,COUNTIFS($L$2:L109,L109,$K$2:K109,K109,$N$2:N109,1,$S$2:S109,1)=1),1,0) -> 0 | R109: =IF(AND(N109=1,COUNTIFS($K$2:K109,K109,$L$2:L109,L109,$J$2:J109,J109,$N$2:N109,1)=1),1,0) -> 0 | S109: =IF(AND(K109<>"Context and provider model",K109<>"Motivation"),1,0) -> 0
J110: ='Raw Atomic Data (Pro)'!A110 -> Tifany | K110: ='Raw Atomic Data (Pro)'!C110 -> Context and provider model | L110: ='Raw Atomic Data (Pro)'!D110 -> business-model-fit | M110: ='Raw Atomic Data (Pro)'!E110 -> fact | N110: =IF(OR(M110="friction",M110="need",M110="workaround"),1,0) -> 0 | O110: =IF(COUNTIFS($K$2:K110,K110,$L$2:L110,L110,$M$2:M110,M110,$J$2:J110,J110)=1,1,0) -> 1 | P110: =IF(AND(N110=1,S110=1,COUNTIFS($L$2:L110,L110,$J$2:J110,J110,$N$2:N110,1,$S$2:S110,1)=1),1,0) -> 0 | Q110: =IF(AND(N110=1,S110=1,COUNTIFS($L$2:L110,L110,$K$2:K110,K110,$N$2:N110,1,$S$2:S110,1)=1),1,0) -> 0 | R110: =IF(AND(N110=1,COUNTIFS($K$2:K110,K110,$L$2:L110,L110,$J$2:J110,J110,$N$2:N110,1)=1),1,0) -> 0 | S110: =IF(AND(K110<>"Context and provider model",K110<>"Motivation"),1,0) -> 0
A111: Note: 'Distinct providers' counts how many of the 14 Pro providers raised that theme, as that type, at least once in that stage -- same distinct-provider methodology as the Friction-Need Frequency sheet, computed live from Raw Atomic Data (Pro) via the hidden helper columns, not hand-counted. 'Cross-cutting' flags themes whose friction/need/workaround rows appear in more than one stage in this list (see Section 3 for the full breakdown by stage). | J111: ='Raw Atomic Data (Pro)'!A111 -> Tifany | K111: ='Raw Atomic Data (Pro)'!C111 -> Context and provider model | L111: ='Raw Atomic Data (Pro)'!D111 -> provider-background | M111: ='Raw Atomic Data (Pro)'!E111 -> fact | N111: =IF(OR(M111="friction",M111="need",M111="workaround"),1,0) -> 0 | O111: =IF(COUNTIFS($K$2:K111,K111,$L$2:L111,L111,$M$2:M111,M111,$J$2:J111,J111)=1,1,0) -> 0 | P111: =IF(AND(N111=1,S111=1,COUNTIFS($L$2:L111,L111,$J$2:J111,J111,$N$2:N111,1,$S$2:S111,1)=1),1,0) -> 0 | Q111: =IF(AND(N111=1,S111=1,COUNTIFS($L$2:L111,L111,$K$2:K111,K111,$N$2:N111,1,$S$2:S111,1)=1),1,0) -> 0 | R111: =IF(AND(N111=1,COUNTIFS($K$2:K111,K111,$L$2:L111,L111,$J$2:J111,J111,$N$2:N111,1)=1),1,0) -> 0 | S111: =IF(AND(K111<>"Context and provider model",K111<>"Motivation"),1,0) -> 0
J112: ='Raw Atomic Data (Pro)'!A112 -> Tifany | K112: ='Raw Atomic Data (Pro)'!C112 -> Context and provider model | L112: ='Raw Atomic Data (Pro)'!D112 -> provider-background | M112: ='Raw Atomic Data (Pro)'!E112 -> fact | N112: =IF(OR(M112="friction",M112="need",M112="workaround"),1,0) -> 0 | O112: =IF(COUNTIFS($K$2:K112,K112,$L$2:L112,L112,$M$2:M112,M112,$J$2:J112,J112)=1,1,0) -> 0 | P112: =IF(AND(N112=1,S112=1,COUNTIFS($L$2:L112,L112,$J$2:J112,J112,$N$2:N112,1,$S$2:S112,1)=1),1,0) -> 0 | Q112: =IF(AND(N112=1,S112=1,COUNTIFS($L$2:L112,L112,$K$2:K112,K112,$N$2:N112,1,$S$2:S112,1)=1),1,0) -> 0 | R112: =IF(AND(N112=1,COUNTIFS($K$2:K112,K112,$L$2:L112,L112,$J$2:J112,J112,$N$2:N112,1)=1),1,0) -> 0 | S112: =IF(AND(K112<>"Context and provider model",K112<>"Motivation"),1,0) -> 0
A113: Cross-Cutting Frictions, Needs & Workarounds (themes tagged in more than one stage) | J113: ='Raw Atomic Data (Pro)'!A113 -> Tifany | K113: ='Raw Atomic Data (Pro)'!C113 -> Context and provider model | L113: ='Raw Atomic Data (Pro)'!D113 -> provider-background | M113: ='Raw Atomic Data (Pro)'!E113 -> fact | N113: =IF(OR(M113="friction",M113="need",M113="workaround"),1,0) -> 0 | O113: =IF(COUNTIFS($K$2:K113,K113,$L$2:L113,L113,$M$2:M113,M113,$J$2:J113,J113)=1,1,0) -> 0 | P113: =IF(AND(N113=1,S113=1,COUNTIFS($L$2:L113,L113,$J$2:J113,J113,$N$2:N113,1,$S$2:S113,1)=1),1,0) -> 0 | Q113: =IF(AND(N113=1,S113=1,COUNTIFS($L$2:L113,L113,$K$2:K113,K113,$N$2:N113,1,$S$2:S113,1)=1),1,0) -> 0 | R113: =IF(AND(N113=1,COUNTIFS($K$2:K113,K113,$L$2:L113,L113,$J$2:J113,J113,$N$2:N113,1)=1),1,0) -> 0 | S113: =IF(AND(K113<>"Context and provider model",K113<>"Motivation"),1,0) -> 0
A114: Theme | B114: Theme definition | C114: Type(s) tagged | D114: Stages spanned (n) | E114: Which stages (distinct providers per stage) | F114: Total distinct Pro providers (any stage, any FNW type) | J114: ='Raw Atomic Data (Pro)'!A114 -> Tifany | K114: ='Raw Atomic Data (Pro)'!C114 -> Context and provider model | L114: ='Raw Atomic Data (Pro)'!D114 -> provider-background | M114: ='Raw Atomic Data (Pro)'!E114 -> fact | N114: =IF(OR(M114="friction",M114="need",M114="workaround"),1,0) -> 0 | O114: =IF(COUNTIFS($K$2:K114,K114,$L$2:L114,L114,$M$2:M114,M114,$J$2:J114,J114)=1,1,0) -> 0 | P114: =IF(AND(N114=1,S114=1,COUNTIFS($L$2:L114,L114,$J$2:J114,J114,$N$2:N114,1,$S$2:S114,1)=1),1,0) -> 0 | Q114: =IF(AND(N114=1,S114=1,COUNTIFS($L$2:L114,L114,$K$2:K114,K114,$N$2:N114,1,$S$2:S114,1)=1),1,0) -> 0 | R114: =IF(AND(N114=1,COUNTIFS($K$2:K114,K114,$L$2:L114,L114,$J$2:J114,J114,$N$2:N114,1)=1),1,0) -> 0 | S114: =IF(AND(K114<>"Context and provider model",K114<>"Motivation"),1,0) -> 0
A115: messaging-platform-mechanics | B115: =IFERROR(INDEX('Theme Legend'!$B$2:$B$31,MATCH($A115,'Theme Legend'!$A$2:$A$31,0)),"") -> Mechanics, bugs, and preferences around the in-app messaging system itself - chat structure, autosave, notification timing, response-time pressure. | C115: =IF(SUMIFS($O$2:$O$978,$L$2:$L$978,$A115,$M$2:$M$978,"friction",$K$2:$K$978,"<>Context and provider model",$K$2:$K$978,"<>Motivation")>0,"friction; ","")&IF(SUMIFS($O$2:$O$978,$L$2:$L$978,$A115,$M$2:$M$978,"need",$K$2:$K$978,"<>Context and provider model",$K$2:$K$978,"<>Motivation")>0,"need; ","")&IF(SUMIFS($O$2:$O$978,$L$2:$L$978,$A115,$M$2:$M$978,"workaround",$K$2:$K$978,"<>Context and provider model",$K$2:$K$978,"<>Motivation")>0,"workaround; ","") -> friction; need; workaround; | D115: =SUMIFS($Q$2:$Q$978,$L$2:$L$978,$A115) -> 6 | E115: =IF((SUMIFS($R$2:$R$978,$K$2:$K$978,"Client acquisition",$L$2:$L$978,$A115))>0,"Client acquisition ("&(SUMIFS($R$2:$R$978,$K$2:$K$978,"Client acquisition",$L$2:$L$978,$A115))&"); ","")&IF((SUMIFS($R$2:$R$978,$K$2:$K$978,"Evaluation and meet-and-greet",$L$2:$L$978,$A115))>0,"Evaluation and meet-and-greet ("&(SUMIFS($R$2:$R$978,$K$2:$K$978,"Evaluation and meet-and-greet",$L$2:$L$978,$A115))&"); ","")&IF((SUMIFS($R$2:$R$978,$K$2:$K$978,"Booking and availability",$L$2:$L$978,$A115))>0,"Booking and availability ("&(SUMIFS($R$2:$R$978,$K$2:$K$978,"Booking and availability",$L$2:$L$978,$A115))&"); ","")&IF((SUMIFS($R$2:$R$978,$K$2:$K$978,"Sitting preparation",$L$2:$L$978,$A115))>0,"Sitting preparation ("&(SUMIFS($R$2:$R$978,$K$2:$K$978,"Sitting preparation",$L$2:$L$978,$A115))&"); ","")&IF((SUMIFS($R$2:$R$978,$K$2:$K$978,"Service delivery",$L$2:$L$978,$A115))>0,"Service delivery ("&(SUMIFS($R$2:$R$978,$K$2:$K$978,"Service delivery",$L$2:$L$978,$A115))&"); ","")&IF((SUMIFS($R$2:$R$978,$K$2:$K$978,"Client communication",$L$2:$L$978,$A115))>0,"Client communication ("&(SUMIFS($R$2:$R$978,$K$2:$K$978,"Client communication",$L$2:$L$978,$A115))&"); ","")&IF((SUMIFS($R$2:$R$978,$K$2:$K$978,"Completion and feedback",$L$2:$L$978,$A115))>0,"Completion and feedback ("&(SUMIFS($R$2:$R$978,$K$2:$K$978,"Completion and feedback",$L$2:$L$978,$A115))&"); ","")&IF((SUMIFS($R$2:$R$978,$K$2:$K$978,"Payments and earnings",$L$2:$L$978,$A115))>0,"Payments and earnings ("&(SUMIFS($R$2:$R$978,$K$2:$K$978,"Payments and earnings",$L$2:$L$978,$A115))&"); ","")&IF((SUMIFS($R$2:$R$978,$K$2:$K$978,"Cross-platform behavior",$L$2:$L$978,$A115))>0,"Cross-platform behavior ("&(SUMIFS($R$2:$R$978,$K$2:$K$978,"Cross-platform behavior",$L$2:$L$978,$A115))&"); ","")&IF((SUMIFS($R$2:$R$978,$K$2:$K$978,"Growth and future plans",$L$2:$L$978,$A115))>0,"Growth and future plans ("&(SUMIFS($R$2:$R$978,$K$2:$K$978,"Growth and future plans",$L$2:$L$978,$A115))&"); ","") -> Client acquisition (1); Evaluation and meet-and-greet (1); Sitting preparation (1); Service delivery (2); Client communication (9); Growth and future plans (4); | F115: =SUMIFS($P$2:$P$978,$L$2:$L$978,$A115) -> 11 | J115: ='Raw Atomic Data (Pro)'!A115 -> Tifany | K115: ='Raw Atomic Data (Pro)'!C115 -> Context and provider model | L115: ='Raw Atomic Data (Pro)'!D115 -> provider-background | M115: ='Raw Atomic Data (Pro)'!E115 -> fact | N115: =IF(OR(M115="friction",M115="need",M115="workaround"),1,0) -> 0 | O115: =IF(COUNTIFS($K$2:K115,K115,$L$2:L115,L115,$M$2:M115,M115,$J$2:J115,J115)=1,1,0) -> 0 | P115: =IF(AND(N115=1,S115=1,COUNTIFS($L$2:L115,L115,$J$2:J115,J115,$N$2:N115,1,$S$2:S115,1)=1),1,0) -> 0 | Q115: =IF(AND(N115=1,S115=1,COUNTIFS($L$2:L115,L115,$K$2:K115,K115,$N$2:N115,1,$S$2:S115,1)=1),1,0) -> 0 | R115: =IF(AND(N115=1,COUNTIFS($K$2:K115,K115,$L$2:L115,L115,$J$2:J115,J115,$N$2:N115,1)=1),1,0) -> 0 | S115: =IF(AND(K115<>"Context and provider model",K115<>"Motivation"),1,0) -> 0
A116: calendar-scheduling-tools | B116: =IFERROR(INDEX('Theme Legend'!$B$2:$B$31,MATCH($A116,'Theme Legend'!$A$2:$A$31,0)),"") -> Tools and behavior for tracking availability and bookings - Rover's calendar, Google Calendar sync, calendar bugs. | C116: =IF(SUMIFS($O$2:$O$978,$L$2:$L$978,$A116,$M$2:$M$978,"friction",$K$2:$K$978,"<>Context and provider model",$K$2:$K$978,"<>Motivation")>0,"friction; ","")&IF(SUMIFS($O$2:$O$978,$L$2:$L$978,$A116,$M$2:$M$978,"need",$K$2:$K$978,"<>Context and provider model",$K$2:$K$978,"<>Motivation")>0,"need; ","")&IF(SUMIFS($O$2:$O$978,$L$2:$L$978,$A116,$M$2:$M$978,"workaround",$K$2:$K$978,"<>Context and provider model",$K$2:$K$978,"<>Motivation")>0,"workaround; ","") -> friction; need; workaround; | D116: =SUMIFS($Q$2:$Q$978,$L$2:$L$978,$A116) -> 2 | E116: =IF((SUMIFS($R$2:$R$978,$K$2:$K$978,"Client acquisition",$L$2:$L$978,$A116))>0,"Client acquisition ("&(SUMIFS($R$2:$R$978,$K$2:$K$978,"Client acquisition",$L$2:$L$978,$A116))&"); ","")&IF((SUMIFS($R$2:$R$978,$K$2:$K$978,"Evaluation and meet-and-greet",$L$2:$L$978,$A116))>0,"Evaluation and meet-and-greet ("&(SUMIFS($R$2:$R$978,$K$2:$K$978,"Evaluation and meet-and-greet",$L$2:$L$978,$A116))&"); ","")&IF((SUMIFS($R$2:$R$978,$K$2:$K$978,"Booking and availability",$L$2:$L$978,$A116))>0,"Booking and availability ("&(SUMIFS($R$2:$R$978,$K$2:$K$978,"Booking and availability",$L$2:$L$978,$A116))&"); ","")&IF((SUMIFS($R$2:$R$978,$K$2:$K$978,"Sitting preparation",$L$2:$L$978,$A116))>0,"Sitting preparation ("&(SUMIFS($R$2:$R$978,$K$2:$K$978,"Sitting preparation",$L$2:$L$978,$A116))&"); ","")&IF((SUMIFS($R$2:$R$978,$K$2:$K$978,"Service delivery",$L$2:$L$978,$A116))>0,"Service delivery ("&(SUMIFS($R$2:$R$978,$K$2:$K$978,"Service delivery",$L$2:$L$978,$A116))&"); ","")&IF((SUMIFS($R$2:$R$978,$K$2:$K$978,"Client communication",$L$2:$L$978,$A116))>0,"Client communication ("&(SUMIFS($R$2:$R$978,$K$2:$K$978,"Client communication",$L$2:$L$978,$A116))&"); ","")&IF((SUMIFS($R$2:$R$978,$K$2:$K$978,"Completion and feedback",$L$2:$L$978,$A116))>0,"Completion and feedback ("&(SUMIFS($R$2:$R$978,$K$2:$K$978,"Completion and feedback",$L$2:$L$978,$A116))&"); ","")&IF((SUMIFS($R$2:$R$978,$K$2:$K$978,"Payments and earnings",$L$2:$L$978,$A116))>0,"Payments and earnings ("&(SUMIFS($R$2:$R$978,$K$2:$K$978,"Payments and earnings",$L$2:$L$978,$A116))&"); ","")&IF((SUMIFS($R$2:$R$978,$K$2:$K$978,"Cross-platform behavior",$L$2:$L$978,$A116))>0,"Cross-platform behavior ("&(SUMIFS($R$2:$R$978,$K$2:$K$978,"Cross-platform behavior",$L$2:$L$978,$A116))&"); ","")&IF((SUMIFS($R$2:$R$978,$K$2:$K$978,"Growth and future plans",$L$2:$L$978,$A116))>0,"Growth and future plans ("&(SUMIFS($R$2:$R$978,$K$2:$K$978,"Growth and future plans",$L$2:$L$978,$A116))&"); ","") -> Booking and availability (10); Growth and future plans (1); | F116: =SUMIFS($P$2:$P$978,$L$2:$L$978,$A116) -> 10 | J116: ='Raw Atomic Data (Pro)'!A116 -> Tifany | K116: ='Raw Atomic Data (Pro)'!C116 -> Context and provider model | L116: ='Raw Atomic Data (Pro)'!D116 -> business-model-fit | M116: ='Raw Atomic Data (Pro)'!E116 -> fact | N116: =IF(OR(M116="friction",M116="need",M116="workaround"),1,0) -> 0 | O116: =IF(COUNTIFS($K$2:K116,K116,$L$2:L116,L116,$M$2:M116,M116,$J$2:J116,J116)=1,1,0) -> 0 | P116: =IF(AND(N116=1,S116=1,COUNTIFS($L$2:L116,L116,$J$2:J116,J116,$N$2:N116,1,$S$2:S116,1)=1),1,0) -> 0 | Q116: =IF(AND(N116=1,S116=1,COUNTIFS($L$2:L116,L116,$K$2:K116,K116,$N$2:N116,1,$S$2:S116,1)=1),1,0) -> 0 | R116: =IF(AND(N116=1,COUNTIFS($K$2:K116,K116,$L$2:L116,L116,$J$2:J116,J116,$N$2:N116,1)=1),1,0) -> 0 | S116: =IF(AND(K116<>"Context and provider model",K116<>"Motivation"),1,0) -> 0
A117: care-instructions-handoff | B117: =IFERROR(INDEX('Theme Legend'!$B$2:$B$31,MATCH($A117,'Theme Legend'!$A$2:$A$31,0)),"") -> Gathering and recording a pet's care instructions (feeding, meds, routine) before or at the start of a sit. | C117: =IF(SUMIFS($O$2:$O$978,$L$2:$L$978,$A117,$M$2:$M$978,"friction",$K$2:$K$978,"<>Context and provider model",$K$2:$K$978,"<>Motivation")>0,"friction; ","")&IF(SUMIFS($O$2:$O$978,$L$2:$L$978,$A117,$M$2:$M$978,"need",$K$2:$K$978,"<>Context and provider model",$K$2:$K$978,"<>Motivation")>0,"need; ","")&IF(SUMIFS($O$2:$O$978,$L$2:$L$978,$A117,$M$2:$M$978,"workaround",$K$2:$K$978,"<>Context and provider model",$K$2:$K$978,"<>Motivation")>0,"workaround; ","") -> friction; need; workaround; | D117: =SUMIFS($Q$2:$Q$978,$L$2:$L$978,$A117) -> 3 | E117: =IF((SUMIFS($R$2:$R$978,$K$2:$K$978,"Client acquisition",$L$2:$L$978,$A117))>0,"Client acquisition ("&(SUMIFS($R$2:$R$978,$K$2:$K$978,"Client acquisition",$L$2:$L$978,$A117))&"); ","")&IF((SUMIFS($R$2:$R$978,$K$2:$K$978,"Evaluation and meet-and-greet",$L$2:$L$978,$A117))>0,"Evaluation and meet-and-greet ("&(SUMIFS($R$2:$R$978,$K$2:$K$978,"Evaluation and meet-and-greet",$L$2:$L$978,$A117))&"); ","")&IF((SUMIFS($R$2:$R$978,$K$2:$K$978,"Booking and availability",$L$2:$L$978,$A117))>0,"Booking and availability ("&(SUMIFS($R$2:$R$978,$K$2:$K$978,"Booking and availability",$L$2:$L$978,$A117))&"); ","")&IF((SUMIFS($R$2:$R$978,$K$2:$K$978,"Sitting preparation",$L$2:$L$978,$A117))>0,"Sitting preparation ("&(SUMIFS($R$2:$R$978,$K$2:$K$978,"Sitting preparation",$L$2:$L$978,$A117))&"); ","")&IF((SUMIFS($R$2:$R$978,$K$2:$K$978,"Service delivery",$L$2:$L$978,$A117))>0,"Service delivery ("&(SUMIFS($R$2:$R$978,$K$2:$K$978,"Service delivery",$L$2:$L$978,$A117))&"); ","")&IF((SUMIFS($R$2:$R$978,$K$2:$K$978,"Client communication",$L$2:$L$978,$A117))>0,"Client communication ("&(SUMIFS($R$2:$R$978,$K$2:$K$978,"Client communication",$L$2:$L$978,$A117))&"); ","")&IF((SUMIFS($R$2:$R$978,$K$2:$K$978,"Completion and feedback",$L$2:$L$978,$A117))>0,"Completion and feedback ("&(SUMIFS($R$2:$R$978,$K$2:$K$978,"Completion and feedback",$L$2:$L$978,$A117))&"); ","")&IF((SUMIFS($R$2:$R$978,$K$2:$K$978,"Payments and earnings",$L$2:$L$978,$A117))>0,"Payments and earnings ("&(SUMIFS($R$2:$R$978,$K$2:$K$978,"Payments and earnings",$L$2:$L$978,$A117))&"); ","")&IF((SUMIFS($R$2:$R$978,$K$2:$K$978,"Cross-platform behavior",$L$2:$L$978,$A117))>0,"Cross-platform behavior ("&(SUMIFS($R$2:$R$978,$K$2:$K$978,"Cross-platform behavior",$L$2:$L$978,$A117))&"); ","")&IF((SUMIFS($R$2:$R$978,$K$2:$K$978,"Growth and future plans",$L$2:$L$978,$A117))>0,"Growth and future plans ("&(SUMIFS($R$2:$R$978,$K$2:$K$978,"Growth and future plans",$L$2:$L$978,$A117))&"); ","") -> Evaluation and meet-and-greet (1); Sitting preparation (7); Completion and feedback (1); | F117: =SUMIFS($P$2:$P$978,$L$2:$L$978,$A117) -> 7 | J117: ='Raw Atomic Data (Pro)'!A117 -> Ami | K117: ='Raw Atomic Data (Pro)'!C117 -> Motivation | L117: ='Raw Atomic Data (Pro)'!D117 -> motivation-emotional-connection | M117: ='Raw Atomic Data (Pro)'!E117 -> value-statement | N117: =IF(OR(M117="friction",M117="need",M117="workaround"),1,0) -> 0 | O117: =IF(COUNTIFS($K$2:K117,K117,$L$2:L117,L117,$M$2:M117,M117,$J$2:J117,J117)=1,1,0) -> 1 | P117: =IF(AND(N117=1,S117=1,COUNTIFS($L$2:L117,L117,$J$2:J117,J117,$N$2:N117,1,$S$2:S117,1)=1),1,0) -> 0 | Q117: =IF(AND(N117=1,S117=1,COUNTIFS($L$2:L117,L117,$K$2:K117,K117,$N$2:N117,1,$S$2:S117,1)=1),1,0) -> 0 | R117: =IF(AND(N117=1,COUNTIFS($K$2:K117,K117,$L$2:L117,L117,$J$2:J117,J117,$N$2:N117,1)=1),1,0) -> 0 | S117: =IF(AND(K117<>"Context and provider model",K117<>"Motivation"),1,0) -> 0
A118: client-acquisition-discovery | B118: =IFERROR(INDEX('Theme Legend'!$B$2:$B$31,MATCH($A118,'Theme Legend'!$A$2:$A$31,0)),"") -> How new clients first find and contact the sitter, and what the sitter does to attract them. | C118: =IF(SUMIFS($O$2:$O$978,$L$2:$L$978,$A118,$M$2:$M$978,"friction",$K$2:$K$978,"<>Context and provider model",$K$2:$K$978,"<>Motivation")>0,"friction; ","")&IF(SUMIFS($O$2:$O$978,$L$2:$L$978,$A118,$M$2:$M$978,"need",$K$2:$K$978,"<>Context and provider model",$K$2:$K$978,"<>Motivation")>0,"need; ","")&IF(SUMIFS($O$2:$O$978,$L$2:$L$978,$A118,$M$2:$M$978,"workaround",$K$2:$K$978,"<>Context and provider model",$K$2:$K$978,"<>Motivation")>0,"workaround; ","") -> friction; need; workaround; | D118: =SUMIFS($Q$2:$Q$978,$L$2:$L$978,$A118) -> 3 | E118: =IF((SUMIFS($R$2:$R$978,$K$2:$K$978,"Client acquisition",$L$2:$L$978,$A118))>0,"Client acquisition ("&(SUMIFS($R$2:$R$978,$K$2:$K$978,"Client acquisition",$L$2:$L$978,$A118))&"); ","")&IF((SUMIFS($R$2:$R$978,$K$2:$K$978,"Evaluation and meet-and-greet",$L$2:$L$978,$A118))>0,"Evaluation and meet-and-greet ("&(SUMIFS($R$2:$R$978,$K$2:$K$978,"Evaluation and meet-and-greet",$L$2:$L$978,$A118))&"); ","")&IF((SUMIFS($R$2:$R$978,$K$2:$K$978,"Booking and availability",$L$2:$L$978,$A118))>0,"Booking and availability ("&(SUMIFS($R$2:$R$978,$K$2:$K$978,"Booking and availability",$L$2:$L$978,$A118))&"); ","")&IF((SUMIFS($R$2:$R$978,$K$2:$K$978,"Sitting preparation",$L$2:$L$978,$A118))>0,"Sitting preparation ("&(SUMIFS($R$2:$R$978,$K$2:$K$978,"Sitting preparation",$L$2:$L$978,$A118))&"); ","")&IF((SUMIFS($R$2:$R$978,$K$2:$K$978,"Service delivery",$L$2:$L$978,$A118))>0,"Service delivery ("&(SUMIFS($R$2:$R$978,$K$2:$K$978,"Service delivery",$L$2:$L$978,$A118))&"); ","")&IF((SUMIFS($R$2:$R$978,$K$2:$K$978,"Client communication",$L$2:$L$978,$A118))>0,"Client communication ("&(SUMIFS($R$2:$R$978,$K$2:$K$978,"Client communication",$L$2:$L$978,$A118))&"); ","")&IF((SUMIFS($R$2:$R$978,$K$2:$K$978,"Completion and feedback",$L$2:$L$978,$A118))>0,"Completion and feedback ("&(SUMIFS($R$2:$R$978,$K$2:$K$978,"Completion and feedback",$L$2:$L$978,$A118))&"); ","")&IF((SUMIFS($R$2:$R$978,$K$2:$K$978,"Payments and earnings",$L$2:$L$978,$A118))>0,"Payments and earnings ("&(SUMIFS($R$2:$R$978,$K$2:$K$978,"Payments and earnings",$L$2:$L$978,$A118))&"); ","")&IF((SUMIFS($R$2:$R$978,$K$2:$K$978,"Cross-platform behavior",$L$2:$L$978,$A118))>0,"Cross-platform behavior ("&(SUMIFS($R$2:$R$978,$K$2:$K$978,"Cross-platform behavior",$L$2:$L$978,$A118))&"); ","")&IF((SUMIFS($R$2:$R$978,$K$2:$K$978,"Growth and future plans",$L$2:$L$978,$A118))>0,"Growth and future plans ("&(SUMIFS($R$2:$R$978,$K$2:$K$978,"Growth and future plans",$L$2:$L$978,$A118))&"); ","") -> Client acquisition (3); Payments and earnings (1); Growth and future plans (2); | F118: =SUMIFS($P$2:$P$978,$L$2:$L$978,$A118) -> 6 | J118: ='Raw Atomic Data (Pro)'!A118 -> Ami | K118: ='Raw Atomic Data (Pro)'!C118 -> Motivation | L118: ='Raw Atomic Data (Pro)'!D118 -> motivation-emotional-connection | M118: ='Raw Atomic Data (Pro)'!E118 -> value-statement | N118: =IF(OR(M118="friction",M118="need",M118="workaround"),1,0) -> 0 | O118: =IF(COUNTIFS($K$2:K118,K118,$L$2:L118,L118,$M$2:M118,M118,$J$2:J118,J118)=1,1,0) -> 0 | P118: =IF(AND(N118=1,S118=1,COUNTIFS($L$2:L118,L118,$J$2:J118,J118,$N$2:N118,1,$S$2:S118,1)=1),1,0) -> 0 | Q118: =IF(AND(N118=1,S118=1,COUNTIFS($L$2:L118,L118,$K$2:K118,K118,$N$2:N118,1,$S$2:S118,1)=1),1,0) -> 0 | R118: =IF(AND(N118=1,COUNTIFS($K$2:K118,K118,$L$2:L118,L118,$J$2:J118,J118,$N$2:N118,1)=1),1,0) -> 0 | S118: =IF(AND(K118<>"Context and provider model",K118<>"Motivation"),1,0) -> 0
A119: payout-timing-tracking | B119: =IFERROR(INDEX('Theme Legend'!$B$2:$B$31,MATCH($A119,'Theme Legend'!$A$2:$A$31,0)),"") -> The timing of getting paid out, and visibility into pending versus earned income. | C119: =IF(SUMIFS($O$2:$O$978,$L$2:$L$978,$A119,$M$2:$M$978,"friction",$K$2:$K$978,"<>Context and provider model",$K$2:$K$978,"<>Motivation")>0,"friction; ","")&IF(SUMIFS($O$2:$O$978,$L$2:$L$978,$A119,$M$2:$M$978,"need",$K$2:$K$978,"<>Context and provider model",$K$2:$K$978,"<>Motivation")>0,"need; ","")&IF(SUMIFS($O$2:$O$978,$L$2:$L$978,$A119,$M$2:$M$978,"workaround",$K$2:$K$978,"<>Context and provider model",$K$2:$K$978,"<>Motivation")>0,"workaround; ","") -> friction; need; workaround; | D119: =SUMIFS($Q$2:$Q$978,$L$2:$L$978,$A119) -> 3 | E119: =IF((SUMIFS($R$2:$R$978,$K$2:$K$978,"Client acquisition",$L$2:$L$978,$A119))>0,"Client acquisition ("&(SUMIFS($R$2:$R$978,$K$2:$K$978,"Client acquisition",$L$2:$L$978,$A119))&"); ","")&IF((SUMIFS($R$2:$R$978,$K$2:$K$978,"Evaluation and meet-and-greet",$L$2:$L$978,$A119))>0,"Evaluation and meet-and-greet ("&(SUMIFS($R$2:$R$978,$K$2:$K$978,"Evaluation and meet-and-greet",$L$2:$L$978,$A119))&"); ","")&IF((SUMIFS($R$2:$R$978,$K$2:$K$978,"Booking and availability",$L$2:$L$978,$A119))>0,"Booking and availability ("&(SUMIFS($R$2:$R$978,$K$2:$K$978,"Booking and availability",$L$2:$L$978,$A119))&"); ","")&IF((SUMIFS($R$2:$R$978,$K$2:$K$978,"Sitting preparation",$L$2:$L$978,$A119))>0,"Sitting preparation ("&(SUMIFS($R$2:$R$978,$K$2:$K$978,"Sitting preparation",$L$2:$L$978,$A119))&"); ","")&IF((SUMIFS($R$2:$R$978,$K$2:$K$978,"Service delivery",$L$2:$L$978,$A119))>0,"Service delivery ("&(SUMIFS($R$2:$R$978,$K$2:$K$978,"Service delivery",$L$2:$L$978,$A119))&"); ","")&IF((SUMIFS($R$2:$R$978,$K$2:$K$978,"Client communication",$L$2:$L$978,$A119))>0,"Client communication ("&(SUMIFS($R$2:$R$978,$K$2:$K$978,"Client communication",$L$2:$L$978,$A119))&"); ","")&IF((SUMIFS($R$2:$R$978,$K$2:$K$978,"Completion and feedback",$L$2:$L$978,$A119))>0,"Completion and feedback ("&(SUMIFS($R$2:$R$978,$K$2:$K$978,"Completion and feedback",$L$2:$L$978,$A119))&"); ","")&IF((SUMIFS($R$2:$R$978,$K$2:$K$978,"Payments and earnings",$L$2:$L$978,$A119))>0,"Payments and earnings ("&(SUMIFS($R$2:$R$978,$K$2:$K$978,"Payments and earnings",$L$2:$L$978,$A119))&"); ","")&IF((SUMIFS($R$2:$R$978,$K$2:$K$978,"Cross-platform behavior",$L$2:$L$978,$A119))>0,"Cross-platform behavior ("&(SUMIFS($R$2:$R$978,$K$2:$K$978,"Cross-platform behavior",$L$2:$L$978,$A119))&"); ","")&IF((SUMIFS($R$2:$R$978,$K$2:$K$978,"Growth and future plans",$L$2:$L$978,$A119))>0,"Growth and future plans ("&(SUMIFS($R$2:$R$978,$K$2:$K$978,"Growth and future plans",$L$2:$L$978,$A119))&"); ","") -> Completion and feedback (1); Payments and earnings (5); Growth and future plans (1); | F119: =SUMIFS($P$2:$P$978,$L$2:$L$978,$A119) -> 6 | J119: ='Raw Atomic Data (Pro)'!A119 -> Ami | K119: ='Raw Atomic Data (Pro)'!C119 -> Motivation | L119: ='Raw Atomic Data (Pro)'!D119 -> motivation-emotional-connection | M119: ='Raw Atomic Data (Pro)'!E119 -> value-statement | N119: =IF(OR(M119="friction",M119="need",M119="workaround"),1,0) -> 0 | O119: =IF(COUNTIFS($K$2:K119,K119,$L$2:L119,L119,$M$2:M119,M119,$J$2:J119,J119)=1,1,0) -> 0 | P119: =IF(AND(N119=1,S119=1,COUNTIFS($L$2:L119,L119,$J$2:J119,J119,$N$2:N119,1,$S$2:S119,1)=1),1,0) -> 0 | Q119: =IF(AND(N119=1,S119=1,COUNTIFS($L$2:L119,L119,$K$2:K119,K119,$N$2:N119,1,$S$2:S119,1)=1),1,0) -> 0 | R119: =IF(AND(N119=1,COUNTIFS($K$2:K119,K119,$L$2:L119,L119,$J$2:J119,J119,$N$2:N119,1)=1),1,0) -> 0 | S119: =IF(AND(K119<>"Context and provider model",K119<>"Motivation"),1,0) -> 0
A120: pricing-rate-setting | B120: =IFERROR(INDEX('Theme Legend'!$B$2:$B$31,MATCH($A120,'Theme Legend'!$A$2:$A$31,0)),"") -> How sitters set, and change, their own service rates. | C120: =IF(SUMIFS($O$2:$O$978,$L$2:$L$978,$A120,$M$2:$M$978,"friction",$K$2:$K$978,"<>Context and provider model",$K$2:$K$978,"<>Motivation")>0,"friction; ","")&IF(SUMIFS($O$2:$O$978,$L$2:$L$978,$A120,$M$2:$M$978,"need",$K$2:$K$978,"<>Context and provider model",$K$2:$K$978,"<>Motivation")>0,"need; ","")&IF(SUMIFS($O$2:$O$978,$L$2:$L$978,$A120,$M$2:$M$978,"workaround",$K$2:$K$978,"<>Context and provider model",$K$2:$K$978,"<>Motivation")>0,"workaround; ","") -> friction; workaround; | D120: =SUMIFS($Q$2:$Q$978,$L$2:$L$978,$A120) -> 2 | E120: =IF((SUMIFS($R$2:$R$978,$K$2:$K$978,"Client acquisition",$L$2:$L$978,$A120))>0,"Client acquisition ("&(SUMIFS($R$2:$R$978,$K$2:$K$978,"Client acquisition",$L$2:$L$978,$A120))&"); ","")&IF((SUMIFS($R$2:$R$978,$K$2:$K$978,"Evaluation and meet-and-greet",$L$2:$L$978,$A120))>0,"Evaluation and meet-and-greet ("&(SUMIFS($R$2:$R$978,$K$2:$K$978,"Evaluation and meet-and-greet",$L$2:$L$978,$A120))&"); ","")&IF((SUMIFS($R$2:$R$978,$K$2:$K$978,"Booking and availability",$L$2:$L$978,$A120))>0,"Booking and availability ("&(SUMIFS($R$2:$R$978,$K$2:$K$978,"Booking and availability",$L$2:$L$978,$A120))&"); ","")&IF((SUMIFS($R$2:$R$978,$K$2:$K$978,"Sitting preparation",$L$2:$L$978,$A120))>0,"Sitting preparation ("&(SUMIFS($R$2:$R$978,$K$2:$K$978,"Sitting preparation",$L$2:$L$978,$A120))&"); ","")&IF((SUMIFS($R$2:$R$978,$K$2:$K$978,"Service delivery",$L$2:$L$978,$A120))>0,"Service delivery ("&(SUMIFS($R$2:$R$978,$K$2:$K$978,"Service delivery",$L$2:$L$978,$A120))&"); ","")&IF((SUMIFS($R$2:$R$978,$K$2:$K$978,"Client communication",$L$2:$L$978,$A120))>0,"Client communication ("&(SUMIFS($R$2:$R$978,$K$2:$K$978,"Client communication",$L$2:$L$978,$A120))&"); ","")&IF((SUMIFS($R$2:$R$978,$K$2:$K$978,"Completion and feedback",$L$2:$L$978,$A120))>0,"Completion and feedback ("&(SUMIFS($R$2:$R$978,$K$2:$K$978,"Completion and feedback",$L$2:$L$978,$A120))&"); ","")&IF((SUMIFS($R$2:$R$978,$K$2:$K$978,"Payments and earnings",$L$2:$L$978,$A120))>0,"Payments and earnings ("&(SUMIFS($R$2:$R$978,$K$2:$K$978,"Payments and earnings",$L$2:$L$978,$A120))&"); ","")&IF((SUMIFS($R$2:$R$978,$K$2:$K$978,"Cross-platform behavior",$L$2:$L$978,$A120))>0,"Cross-platform behavior ("&(SUMIFS($R$2:$R$978,$K$2:$K$978,"Cross-platform behavior",$L$2:$L$978,$A120))&"); ","")&IF((SUMIFS($R$2:$R$978,$K$2:$K$978,"Growth and future plans",$L$2:$L$978,$A120))>0,"Growth and future plans ("&(SUMIFS($R$2:$R$978,$K$2:$K$978,"Growth and future plans",$L$2:$L$978,$A120))&"); ","") -> Client acquisition (1); Payments and earnings (4); | F120: =SUMIFS($P$2:$P$978,$L$2:$L$978,$A120) -> 5 | J120: ='Raw Atomic Data (Pro)'!A120 -> Andrew | K120: ='Raw Atomic Data (Pro)'!C120 -> Motivation | L120: ='Raw Atomic Data (Pro)'!D120 -> motivation-emotional-connection | M120: ='Raw Atomic Data (Pro)'!E120 -> value-statement | N120: =IF(OR(M120="friction",M120="need",M120="workaround"),1,0) -> 0 | O120: =IF(COUNTIFS($K$2:K120,K120,$L$2:L120,L120,$M$2:M120,M120,$J$2:J120,J120)=1,1,0) -> 1 | P120: =IF(AND(N120=1,S120=1,COUNTIFS($L$2:L120,L120,$J$2:J120,J120,$N$2:N120,1,$S$2:S120,1)=1),1,0) -> 0 | Q120: =IF(AND(N120=1,S120=1,COUNTIFS($L$2:L120,L120,$K$2:K120,K120,$N$2:N120,1,$S$2:S120,1)=1),1,0) -> 0 | R120: =IF(AND(N120=1,COUNTIFS($K$2:K120,K120,$L$2:L120,L120,$J$2:J120,J120,$N$2:N120,1)=1),1,0) -> 0 | S120: =IF(AND(K120<>"Context and provider model",K120<>"Motivation"),1,0) -> 0
A121: safety-risk-incidents | B121: =IFERROR(INDEX('Theme Legend'!$B$2:$B$31,MATCH($A121,'Theme Legend'!$A$2:$A$31,0)),"") -> Physical-safety concerns and incidents involving the sitter, a dog, or an owner, and personal-safety precautions. | C121: =IF(SUMIFS($O$2:$O$978,$L$2:$L$978,$A121,$M$2:$M$978,"friction",$K$2:$K$978,"<>Context and provider model",$K$2:$K$978,"<>Motivation")>0,"friction; ","")&IF(SUMIFS($O$2:$O$978,$L$2:$L$978,$A121,$M$2:$M$978,"need",$K$2:$K$978,"<>Context and provider model",$K$2:$K$978,"<>Motivation")>0,"need; ","")&IF(SUMIFS($O$2:$O$978,$L$2:$L$978,$A121,$M$2:$M$978,"workaround",$K$2:$K$978,"<>Context and provider model",$K$2:$K$978,"<>Motivation")>0,"workaround; ","") -> friction; need; workaround; | D121: =SUMIFS($Q$2:$Q$978,$L$2:$L$978,$A121) -> 5 | E121: =IF((SUMIFS($R$2:$R$978,$K$2:$K$978,"Client acquisition",$L$2:$L$978,$A121))>0,"Client acquisition ("&(SUMIFS($R$2:$R$978,$K$2:$K$978,"Client acquisition",$L$2:$L$978,$A121))&"); ","")&IF((SUMIFS($R$2:$R$978,$K$2:$K$978,"Evaluation and meet-and-greet",$L$2:$L$978,$A121))>0,"Evaluation and meet-and-greet ("&(SUMIFS($R$2:$R$978,$K$2:$K$978,"Evaluation and meet-and-greet",$L$2:$L$978,$A121))&"); ","")&IF((SUMIFS($R$2:$R$978,$K$2:$K$978,"Booking and availability",$L$2:$L$978,$A121))>0,"Booking and availability ("&(SUMIFS($R$2:$R$978,$K$2:$K$978,"Booking and availability",$L$2:$L$978,$A121))&"); ","")&IF((SUMIFS($R$2:$R$978,$K$2:$K$978,"Sitting preparation",$L$2:$L$978,$A121))>0,"Sitting preparation ("&(SUMIFS($R$2:$R$978,$K$2:$K$978,"Sitting preparation",$L$2:$L$978,$A121))&"); ","")&IF((SUMIFS($R$2:$R$978,$K$2:$K$978,"Service delivery",$L$2:$L$978,$A121))>0,"Service delivery ("&(SUMIFS($R$2:$R$978,$K$2:$K$978,"Service delivery",$L$2:$L$978,$A121))&"); ","")&IF((SUMIFS($R$2:$R$978,$K$2:$K$978,"Client communication",$L$2:$L$978,$A121))>0,"Client communication ("&(SUMIFS($R$2:$R$978,$K$2:$K$978,"Client communication",$L$2:$L$978,$A121))&"); ","")&IF((SUMIFS($R$2:$R$978,$K$2:$K$978,"Completion and feedback",$L$2:$L$978,$A121))>0,"Completion and feedback ("&(SUMIFS($R$2:$R$978,$K$2:$K$978,"Completion and feedback",$L$2:$L$978,$A121))&"); ","")&IF((SUMIFS($R$2:$R$978,$K$2:$K$978,"Payments and earnings",$L$2:$L$978,$A121))>0,"Payments and earnings ("&(SUMIFS($R$2:$R$978,$K$2:$K$978,"Payments and earnings",$L$2:$L$978,$A121))&"); ","")&IF((SUMIFS($R$2:$R$978,$K$2:$K$978,"Cross-platform behavior",$L$2:$L$978,$A121))>0,"Cross-platform behavior ("&(SUMIFS($R$2:$R$978,$K$2:$K$978,"Cross-platform behavior",$L$2:$L$978,$A121))&"); ","")&IF((SUMIFS($R$2:$R$978,$K$2:$K$978,"Growth and future plans",$L$2:$L$978,$A121))>0,"Growth and future plans ("&(SUMIFS($R$2:$R$978,$K$2:$K$978,"Growth and future plans",$L$2:$L$978,$A121))&"); ","") -> Evaluation and meet-and-greet (3); Sitting preparation (1); Service delivery (2); Client communication (1); Growth and future plans (1); | F121: =SUMIFS($P$2:$P$978,$L$2:$L$978,$A121) -> 5 | J121: ='Raw Atomic Data (Pro)'!A121 -> Andrew | K121: ='Raw Atomic Data (Pro)'!C121 -> Motivation | L121: ='Raw Atomic Data (Pro)'!D121 -> motivation-emotional-connection | M121: ='Raw Atomic Data (Pro)'!E121 -> value-statement | N121: =IF(OR(M121="friction",M121="need",M121="workaround"),1,0) -> 0 | O121: =IF(COUNTIFS($K$2:K121,K121,$L$2:L121,L121,$M$2:M121,M121,$J$2:J121,J121)=1,1,0) -> 0 | P121: =IF(AND(N121=1,S121=1,COUNTIFS($L$2:L121,L121,$J$2:J121,J121,$N$2:N121,1,$S$2:S121,1)=1),1,0) -> 0 | Q121: =IF(AND(N121=1,S121=1,COUNTIFS($L$2:L121,L121,$K$2:K121,K121,$N$2:N121,1,$S$2:S121,1)=1),1,0) -> 0 | R121: =IF(AND(N121=1,COUNTIFS($K$2:K121,K121,$L$2:L121,L121,$J$2:J121,J121,$N$2:N121,1)=1),1,0) -> 0 | S121: =IF(AND(K121<>"Context and provider model",K121<>"Motivation"),1,0) -> 0
A122: profile-information-completeness | B122: =IFERROR(INDEX('Theme Legend'!$B$2:$B$31,MATCH($A122,'Theme Legend'!$A$2:$A$31,0)),"") -> The completeness and quality of client or pet profile information available before or during a sit. | C122: =IF(SUMIFS($O$2:$O$978,$L$2:$L$978,$A122,$M$2:$M$978,"friction",$K$2:$K$978,"<>Context and provider model",$K$2:$K$978,"<>Motivation")>0,"friction; ","")&IF(SUMIFS($O$2:$O$978,$L$2:$L$978,$A122,$M$2:$M$978,"need",$K$2:$K$978,"<>Context and provider model",$K$2:$K$978,"<>Motivation")>0,"need; ","")&IF(SUMIFS($O$2:$O$978,$L$2:$L$978,$A122,$M$2:$M$978,"workaround",$K$2:$K$978,"<>Context and provider model",$K$2:$K$978,"<>Motivation")>0,"workaround; ","") -> friction; need; | D122: =SUMIFS($Q$2:$Q$978,$L$2:$L$978,$A122) -> 3 | E122: =IF((SUMIFS($R$2:$R$978,$K$2:$K$978,"Client acquisition",$L$2:$L$978,$A122))>0,"Client acquisition ("&(SUMIFS($R$2:$R$978,$K$2:$K$978,"Client acquisition",$L$2:$L$978,$A122))&"); ","")&IF((SUMIFS($R$2:$R$978,$K$2:$K$978,"Evaluation and meet-and-greet",$L$2:$L$978,$A122))>0,"Evaluation and meet-and-greet ("&(SUMIFS($R$2:$R$978,$K$2:$K$978,"Evaluation and meet-and-greet",$L$2:$L$978,$A122))&"); ","")&IF((SUMIFS($R$2:$R$978,$K$2:$K$978,"Booking and availability",$L$2:$L$978,$A122))>0,"Booking and availability ("&(SUMIFS($R$2:$R$978,$K$2:$K$978,"Booking and availability",$L$2:$L$978,$A122))&"); ","")&IF((SUMIFS($R$2:$R$978,$K$2:$K$978,"Sitting preparation",$L$2:$L$978,$A122))>0,"Sitting preparation ("&(SUMIFS($R$2:$R$978,$K$2:$K$978,"Sitting preparation",$L$2:$L$978,$A122))&"); ","")&IF((SUMIFS($R$2:$R$978,$K$2:$K$978,"Service delivery",$L$2:$L$978,$A122))>0,"Service delivery ("&(SUMIFS($R$2:$R$978,$K$2:$K$978,"Service delivery",$L$2:$L$978,$A122))&"); ","")&IF((SUMIFS($R$2:$R$978,$K$2:$K$978,"Client communication",$L$2:$L$978,$A122))>0,"Client communication ("&(SUMIFS($R$2:$R$978,$K$2:$K$978,"Client communication",$L$2:$L$978,$A122))&"); ","")&IF((SUMIFS($R$2:$R$978,$K$2:$K$978,"Completion and feedback",$L$2:$L$978,$A122))>0,"Completion and feedback ("&(SUMIFS($R$2:$R$978,$K$2:$K$978,"Completion and feedback",$L$2:$L$978,$A122))&"); ","")&IF((SUMIFS($R$2:$R$978,$K$2:$K$978,"Payments and earnings",$L$2:$L$978,$A122))>0,"Payments and earnings ("&(SUMIFS($R$2:$R$978,$K$2:$K$978,"Payments and earnings",$L$2:$L$978,$A122))&"); ","")&IF((SUMIFS($R$2:$R$978,$K$2:$K$978,"Cross-platform behavior",$L$2:$L$978,$A122))>0,"Cross-platform behavior ("&(SUMIFS($R$2:$R$978,$K$2:$K$978,"Cross-platform behavior",$L$2:$L$978,$A122))&"); ","")&IF((SUMIFS($R$2:$R$978,$K$2:$K$978,"Growth and future plans",$L$2:$L$978,$A122))>0,"Growth and future plans ("&(SUMIFS($R$2:$R$978,$K$2:$K$978,"Growth and future plans",$L$2:$L$978,$A122))&"); ","") -> Client acquisition (1); Evaluation and meet-and-greet (1); Sitting preparation (2); | F122: =SUMIFS($P$2:$P$978,$L$2:$L$978,$A122) -> 4 | J122: ='Raw Atomic Data (Pro)'!A122 -> Andrew | K122: ='Raw Atomic Data (Pro)'!C122 -> Motivation | L122: ='Raw Atomic Data (Pro)'!D122 -> motivation-emotional-connection | M122: ='Raw Atomic Data (Pro)'!E122 -> value-statement | N122: =IF(OR(M122="friction",M122="need",M122="workaround"),1,0) -> 0 | O122: =IF(COUNTIFS($K$2:K122,K122,$L$2:L122,L122,$M$2:M122,M122,$J$2:J122,J122)=1,1,0) -> 0 | P122: =IF(AND(N122=1,S122=1,COUNTIFS($L$2:L122,L122,$J$2:J122,J122,$N$2:N122,1,$S$2:S122,1)=1),1,0) -> 0 | Q122: =IF(AND(N122=1,S122=1,COUNTIFS($L$2:L122,L122,$K$2:K122,K122,$N$2:N122,1,$S$2:S122,1)=1),1,0) -> 0 | R122: =IF(AND(N122=1,COUNTIFS($K$2:K122,K122,$L$2:L122,L122,$J$2:J122,J122,$N$2:N122,1)=1),1,0) -> 0 | S122: =IF(AND(K122<>"Context and provider model",K122<>"Motivation"),1,0) -> 0
A123: booking-confirmation-mechanics | B123: =IFERROR(INDEX('Theme Legend'!$B$2:$B$31,MATCH($A123,'Theme Legend'!$A$2:$A$31,0)),"") -> The mechanics of how a request becomes a confirmed (or cancelled) booking - blocking dates, mutual confirmation, cancellation rules. | C123: =IF(SUMIFS($O$2:$O$978,$L$2:$L$978,$A123,$M$2:$M$978,"friction",$K$2:$K$978,"<>Context and provider model",$K$2:$K$978,"<>Motivation")>0,"friction; ","")&IF(SUMIFS($O$2:$O$978,$L$2:$L$978,$A123,$M$2:$M$978,"need",$K$2:$K$978,"<>Context and provider model",$K$2:$K$978,"<>Motivation")>0,"need; ","")&IF(SUMIFS($O$2:$O$978,$L$2:$L$978,$A123,$M$2:$M$978,"workaround",$K$2:$K$978,"<>Context and provider model",$K$2:$K$978,"<>Motivation")>0,"workaround; ","") -> friction; need; workaround; | D123: =SUMIFS($Q$2:$Q$978,$L$2:$L$978,$A123) -> 3 | E123: =IF((SUMIFS($R$2:$R$978,$K$2:$K$978,"Client acquisition",$L$2:$L$978,$A123))>0,"Client acquisition ("&(SUMIFS($R$2:$R$978,$K$2:$K$978,"Client acquisition",$L$2:$L$978,$A123))&"); ","")&IF((SUMIFS($R$2:$R$978,$K$2:$K$978,"Evaluation and meet-and-greet",$L$2:$L$978,$A123))>0,"Evaluation and meet-and-greet ("&(SUMIFS($R$2:$R$978,$K$2:$K$978,"Evaluation and meet-and-greet",$L$2:$L$978,$A123))&"); ","")&IF((SUMIFS($R$2:$R$978,$K$2:$K$978,"Booking and availability",$L$2:$L$978,$A123))>0,"Booking and availability ("&(SUMIFS($R$2:$R$978,$K$2:$K$978,"Booking and availability",$L$2:$L$978,$A123))&"); ","")&IF((SUMIFS($R$2:$R$978,$K$2:$K$978,"Sitting preparation",$L$2:$L$978,$A123))>0,"Sitting preparation ("&(SUMIFS($R$2:$R$978,$K$2:$K$978,"Sitting preparation",$L$2:$L$978,$A123))&"); ","")&IF((SUMIFS($R$2:$R$978,$K$2:$K$978,"Service delivery",$L$2:$L$978,$A123))>0,"Service delivery ("&(SUMIFS($R$2:$R$978,$K$2:$K$978,"Service delivery",$L$2:$L$978,$A123))&"); ","")&IF((SUMIFS($R$2:$R$978,$K$2:$K$978,"Client communication",$L$2:$L$978,$A123))>0,"Client communication ("&(SUMIFS($R$2:$R$978,$K$2:$K$978,"Client communication",$L$2:$L$978,$A123))&"); ","")&IF((SUMIFS($R$2:$R$978,$K$2:$K$978,"Completion and feedback",$L$2:$L$978,$A123))>0,"Completion and feedback ("&(SUMIFS($R$2:$R$978,$K$2:$K$978,"Completion and feedback",$L$2:$L$978,$A123))&"); ","")&IF((SUMIFS($R$2:$R$978,$K$2:$K$978,"Payments and earnings",$L$2:$L$978,$A123))>0,"Payments and earnings ("&(SUMIFS($R$2:$R$978,$K$2:$K$978,"Payments and earnings",$L$2:$L$978,$A123))&"); ","")&IF((SUMIFS($R$2:$R$978,$K$2:$K$978,"Cross-platform behavior",$L$2:$L$978,$A123))>0,"Cross-platform behavior ("&(SUMIFS($R$2:$R$978,$K$2:$K$978,"Cross-platform behavior",$L$2:$L$978,$A123))&"); ","")&IF((SUMIFS($R$2:$R$978,$K$2:$K$978,"Growth and future plans",$L$2:$L$978,$A123))>0,"Growth and future plans ("&(SUMIFS($R$2:$R$978,$K$2:$K$978,"Growth and future plans",$L$2:$L$978,$A123))&"); ","") -> Client acquisition (1); Booking and availability (2); Payments and earnings (2); | F123: =SUMIFS($P$2:$P$978,$L$2:$L$978,$A123) -> 4 | J123: ='Raw Atomic Data (Pro)'!A123 -> Andrew | K123: ='Raw Atomic Data (Pro)'!C123 -> Motivation | L123: ='Raw Atomic Data (Pro)'!D123 -> motivation-emotional-connection | M123: ='Raw Atomic Data (Pro)'!E123 -> value-statement | N123: =IF(OR(M123="friction",M123="need",M123="workaround"),1,0) -> 0 | O123: =IF(COUNTIFS($K$2:K123,K123,$L$2:L123,L123,$M$2:M123,M123,$J$2:J123,J123)=1,1,0) -> 0 | P123: =IF(AND(N123=1,S123=1,COUNTIFS($L$2:L123,L123,$J$2:J123,J123,$N$2:N123,1,$S$2:S123,1)=1),1,0) -> 0 | Q123: =IF(AND(N123=1,S123=1,COUNTIFS($L$2:L123,L123,$K$2:K123,K123,$N$2:N123,1,$S$2:S123,1)=1),1,0) -> 0 | R123: =IF(AND(N123=1,COUNTIFS($K$2:K123,K123,$L$2:L123,L123,$J$2:J123,J123,$N$2:N123,1)=1),1,0) -> 0 | S123: =IF(AND(K123<>"Context and provider model",K123<>"Motivation"),1,0) -> 0
A124: daily-care-tasks | B124: =IFERROR(INDEX('Theme Legend'!$B$2:$B$31,MATCH($A124,'Theme Legend'!$A$2:$A$31,0)),"") -> Neutral facts about the concrete tasks performed during a sit - feeding, walking, medicating, cleaning. | C124: =IF(SUMIFS($O$2:$O$978,$L$2:$L$978,$A124,$M$2:$M$978,"friction",$K$2:$K$978,"<>Context and provider model",$K$2:$K$978,"<>Motivation")>0,"friction; ","")&IF(SUMIFS($O$2:$O$978,$L$2:$L$978,$A124,$M$2:$M$978,"need",$K$2:$K$978,"<>Context and provider model",$K$2:$K$978,"<>Motivation")>0,"need; ","")&IF(SUMIFS($O$2:$O$978,$L$2:$L$978,$A124,$M$2:$M$978,"workaround",$K$2:$K$978,"<>Context and provider model",$K$2:$K$978,"<>Motivation")>0,"workaround; ","") -> friction; need; workaround; | D124: =SUMIFS($Q$2:$Q$978,$L$2:$L$978,$A124) -> 3 | E124: =IF((SUMIFS($R$2:$R$978,$K$2:$K$978,"Client acquisition",$L$2:$L$978,$A124))>0,"Client acquisition ("&(SUMIFS($R$2:$R$978,$K$2:$K$978,"Client acquisition",$L$2:$L$978,$A124))&"); ","")&IF((SUMIFS($R$2:$R$978,$K$2:$K$978,"Evaluation and meet-and-greet",$L$2:$L$978,$A124))>0,"Evaluation and meet-and-greet ("&(SUMIFS($R$2:$R$978,$K$2:$K$978,"Evaluation and meet-and-greet",$L$2:$L$978,$A124))&"); ","")&IF((SUMIFS($R$2:$R$978,$K$2:$K$978,"Booking and availability",$L$2:$L$978,$A124))>0,"Booking and availability ("&(SUMIFS($R$2:$R$978,$K$2:$K$978,"Booking and availability",$L$2:$L$978,$A124))&"); ","")&IF((SUMIFS($R$2:$R$978,$K$2:$K$978,"Sitting preparation",$L$2:$L$978,$A124))>0,"Sitting preparation ("&(SUMIFS($R$2:$R$978,$K$2:$K$978,"Sitting preparation",$L$2:$L$978,$A124))&"); ","")&IF((SUMIFS($R$2:$R$978,$K$2:$K$978,"Service delivery",$L$2:$L$978,$A124))>0,"Service delivery ("&(SUMIFS($R$2:$R$978,$K$2:$K$978,"Service delivery",$L$2:$L$978,$A124))&"); ","")&IF((SUMIFS($R$2:$R$978,$K$2:$K$978,"Client communication",$L$2:$L$978,$A124))>0,"Client communication ("&(SUMIFS($R$2:$R$978,$K$2:$K$978,"Client communication",$L$2:$L$978,$A124))&"); ","")&IF((SUMIFS($R$2:$R$978,$K$2:$K$978,"Completion and feedback",$L$2:$L$978,$A124))>0,"Completion and feedback ("&(SUMIFS($R$2:$R$978,$K$2:$K$978,"Completion and feedback",$L$2:$L$978,$A124))&"); ","")&IF((SUMIFS($R$2:$R$978,$K$2:$K$978,"Payments and earnings",$L$2:$L$978,$A124))>0,"Payments and earnings ("&(SUMIFS($R$2:$R$978,$K$2:$K$978,"Payments and earnings",$L$2:$L$978,$A124))&"); ","")&IF((SUMIFS($R$2:$R$978,$K$2:$K$978,"Cross-platform behavior",$L$2:$L$978,$A124))>0,"Cross-platform behavior ("&(SUMIFS($R$2:$R$978,$K$2:$K$978,"Cross-platform behavior",$L$2:$L$978,$A124))&"); ","")&IF((SUMIFS($R$2:$R$978,$K$2:$K$978,"Growth and future plans",$L$2:$L$978,$A124))>0,"Growth and future plans ("&(SUMIFS($R$2:$R$978,$K$2:$K$978,"Growth and future plans",$L$2:$L$978,$A124))&"); ","") -> Service delivery (3); Completion and feedback (1); Growth and future plans (1); | F124: =SUMIFS($P$2:$P$978,$L$2:$L$978,$A124) -> 4 | J124: ='Raw Atomic Data (Pro)'!A124 -> Andrew | K124: ='Raw Atomic Data (Pro)'!C124 -> Motivation | L124: ='Raw Atomic Data (Pro)'!D124 -> motivation-emotional-connection | M124: ='Raw Atomic Data (Pro)'!E124 -> value-statement | N124: =IF(OR(M124="friction",M124="need",M124="workaround"),1,0) -> 0 | O124: =IF(COUNTIFS($K$2:K124,K124,$L$2:L124,L124,$M$2:M124,M124,$J$2:J124,J124)=1,1,0) -> 0 | P124: =IF(AND(N124=1,S124=1,COUNTIFS($L$2:L124,L124,$J$2:J124,J124,$N$2:N124,1,$S$2:S124,1)=1),1,0) -> 0 | Q124: =IF(AND(N124=1,S124=1,COUNTIFS($L$2:L124,L124,$K$2:K124,K124,$N$2:N124,1,$S$2:S124,1)=1),1,0) -> 0 | R124: =IF(AND(N124=1,COUNTIFS($K$2:K124,K124,$L$2:L124,L124,$J$2:J124,J124,$N$2:N124,1)=1),1,0) -> 0 | S124: =IF(AND(K124<>"Context and provider model",K124<>"Motivation"),1,0) -> 0
A125: off-platform-communication-channels | B125: =IFERROR(INDEX('Theme Legend'!$B$2:$B$31,MATCH($A125,'Theme Legend'!$A$2:$A$31,0)),"") -> Sitters or clients using channels other than Rover chat to communicate, such as texting, WhatsApp, or Messenger. | C125: =IF(SUMIFS($O$2:$O$978,$L$2:$L$978,$A125,$M$2:$M$978,"friction",$K$2:$K$978,"<>Context and provider model",$K$2:$K$978,"<>Motivation")>0,"friction; ","")&IF(SUMIFS($O$2:$O$978,$L$2:$L$978,$A125,$M$2:$M$978,"need",$K$2:$K$978,"<>Context and provider model",$K$2:$K$978,"<>Motivation")>0,"need; ","")&IF(SUMIFS($O$2:$O$978,$L$2:$L$978,$A125,$M$2:$M$978,"workaround",$K$2:$K$978,"<>Context and provider model",$K$2:$K$978,"<>Motivation")>0,"workaround; ","") -> workaround; | D125: =SUMIFS($Q$2:$Q$978,$L$2:$L$978,$A125) -> 2 | E125: =IF((SUMIFS($R$2:$R$978,$K$2:$K$978,"Client acquisition",$L$2:$L$978,$A125))>0,"Client acquisition ("&(SUMIFS($R$2:$R$978,$K$2:$K$978,"Client acquisition",$L$2:$L$978,$A125))&"); ","")&IF((SUMIFS($R$2:$R$978,$K$2:$K$978,"Evaluation and meet-and-greet",$L$2:$L$978,$A125))>0,"Evaluation and meet-and-greet ("&(SUMIFS($R$2:$R$978,$K$2:$K$978,"Evaluation and meet-and-greet",$L$2:$L$978,$A125))&"); ","")&IF((SUMIFS($R$2:$R$978,$K$2:$K$978,"Booking and availability",$L$2:$L$978,$A125))>0,"Booking and availability ("&(SUMIFS($R$2:$R$978,$K$2:$K$978,"Booking and availability",$L$2:$L$978,$A125))&"); ","")&IF((SUMIFS($R$2:$R$978,$K$2:$K$978,"Sitting preparation",$L$2:$L$978,$A125))>0,"Sitting preparation ("&(SUMIFS($R$2:$R$978,$K$2:$K$978,"Sitting preparation",$L$2:$L$978,$A125))&"); ","")&IF((SUMIFS($R$2:$R$978,$K$2:$K$978,"Service delivery",$L$2:$L$978,$A125))>0,"Service delivery ("&(SUMIFS($R$2:$R$978,$K$2:$K$978,"Service delivery",$L$2:$L$978,$A125))&"); ","")&IF((SUMIFS($R$2:$R$978,$K$2:$K$978,"Client communication",$L$2:$L$978,$A125))>0,"Client communication ("&(SUMIFS($R$2:$R$978,$K$2:$K$978,"Client communication",$L$2:$L$978,$A125))&"); ","")&IF((SUMIFS($R$2:$R$978,$K$2:$K$978,"Completion and feedback",$L$2:$L$978,$A125))>0,"Completion and feedback ("&(SUMIFS($R$2:$R$978,$K$2:$K$978,"Completion and feedback",$L$2:$L$978,$A125))&"); ","")&IF((SUMIFS($R$2:$R$978,$K$2:$K$978,"Payments and earnings",$L$2:$L$978,$A125))>0,"Payments and earnings ("&(SUMIFS($R$2:$R$978,$K$2:$K$978,"Payments and earnings",$L$2:$L$978,$A125))&"); ","")&IF((SUMIFS($R$2:$R$978,$K$2:$K$978,"Cross-platform behavior",$L$2:$L$978,$A125))>0,"Cross-platform behavior ("&(SUMIFS($R$2:$R$978,$K$2:$K$978,"Cross-platform behavior",$L$2:$L$978,$A125))&"); ","")&IF((SUMIFS($R$2:$R$978,$K$2:$K$978,"Growth and future plans",$L$2:$L$978,$A125))>0,"Growth and future plans ("&(SUMIFS($R$2:$R$978,$K$2:$K$978,"Growth and future plans",$L$2:$L$978,$A125))&"); ","") -> Client communication (3); Cross-platform behavior (1); | F125: =SUMIFS($P$2:$P$978,$L$2:$L$978,$A125) -> 4 | J125: ='Raw Atomic Data (Pro)'!A125 -> Andrew | K125: ='Raw Atomic Data (Pro)'!C125 -> Motivation | L125: ='Raw Atomic Data (Pro)'!D125 -> motivation-emotional-connection | M125: ='Raw Atomic Data (Pro)'!E125 -> fact | N125: =IF(OR(M125="friction",M125="need",M125="workaround"),1,0) -> 0 | O125: =IF(COUNTIFS($K$2:K125,K125,$L$2:L125,L125,$M$2:M125,M125,$J$2:J125,J125)=1,1,0) -> 1 | P125: =IF(AND(N125=1,S125=1,COUNTIFS($L$2:L125,L125,$J$2:J125,J125,$N$2:N125,1,$S$2:S125,1)=1),1,0) -> 0 | Q125: =IF(AND(N125=1,S125=1,COUNTIFS($L$2:L125,L125,$K$2:K125,K125,$N$2:N125,1,$S$2:S125,1)=1),1,0) -> 0 | R125: =IF(AND(N125=1,COUNTIFS($K$2:K125,K125,$L$2:L125,L125,$J$2:J125,J125,$N$2:N125,1)=1),1,0) -> 0 | S125: =IF(AND(K125<>"Context and provider model",K125<>"Motivation"),1,0) -> 0
A126: reviews-feedback-process | B126: =IFERROR(INDEX('Theme Legend'!$B$2:$B$31,MATCH($A126,'Theme Legend'!$A$2:$A$31,0)),"") -> Leaving and receiving reviews and ratings, and concerns about their honesty, visibility, or fairness. | C126: =IF(SUMIFS($O$2:$O$978,$L$2:$L$978,$A126,$M$2:$M$978,"friction",$K$2:$K$978,"<>Context and provider model",$K$2:$K$978,"<>Motivation")>0,"friction; ","")&IF(SUMIFS($O$2:$O$978,$L$2:$L$978,$A126,$M$2:$M$978,"need",$K$2:$K$978,"<>Context and provider model",$K$2:$K$978,"<>Motivation")>0,"need; ","")&IF(SUMIFS($O$2:$O$978,$L$2:$L$978,$A126,$M$2:$M$978,"workaround",$K$2:$K$978,"<>Context and provider model",$K$2:$K$978,"<>Motivation")>0,"workaround; ","") -> friction; need; workaround; | D126: =SUMIFS($Q$2:$Q$978,$L$2:$L$978,$A126) -> 2 | E126: =IF((SUMIFS($R$2:$R$978,$K$2:$K$978,"Client acquisition",$L$2:$L$978,$A126))>0,"Client acquisition ("&(SUMIFS($R$2:$R$978,$K$2:$K$978,"Client acquisition",$L$2:$L$978,$A126))&"); ","")&IF((SUMIFS($R$2:$R$978,$K$2:$K$978,"Evaluation and meet-and-greet",$L$2:$L$978,$A126))>0,"Evaluation and meet-and-greet ("&(SUMIFS($R$2:$R$978,$K$2:$K$978,"Evaluation and meet-and-greet",$L$2:$L$978,$A126))&"); ","")&IF((SUMIFS($R$2:$R$978,$K$2:$K$978,"Booking and availability",$L$2:$L$978,$A126))>0,"Booking and availability ("&(SUMIFS($R$2:$R$978,$K$2:$K$978,"Booking and availability",$L$2:$L$978,$A126))&"); ","")&IF((SUMIFS($R$2:$R$978,$K$2:$K$978,"Sitting preparation",$L$2:$L$978,$A126))>0,"Sitting preparation ("&(SUMIFS($R$2:$R$978,$K$2:$K$978,"Sitting preparation",$L$2:$L$978,$A126))&"); ","")&IF((SUMIFS($R$2:$R$978,$K$2:$K$978,"Service delivery",$L$2:$L$978,$A126))>0,"Service delivery ("&(SUMIFS($R$2:$R$978,$K$2:$K$978,"Service delivery",$L$2:$L$978,$A126))&"); ","")&IF((SUMIFS($R$2:$R$978,$K$2:$K$978,"Client communication",$L$2:$L$978,$A126))>0,"Client communication ("&(SUMIFS($R$2:$R$978,$K$2:$K$978,"Client communication",$L$2:$L$978,$A126))&"); ","")&IF((SUMIFS($R$2:$R$978,$K$2:$K$978,"Completion and feedback",$L$2:$L$978,$A126))>0,"Completion and feedback ("&(SUMIFS($R$2:$R$978,$K$2:$K$978,"Completion and feedback",$L$2:$L$978,$A126))&"); ","")&IF((SUMIFS($R$2:$R$978,$K$2:$K$978,"Payments and earnings",$L$2:$L$978,$A126))>0,"Payments and earnings ("&(SUMIFS($R$2:$R$978,$K$2:$K$978,"Payments and earnings",$L$2:$L$978,$A126))&"); ","")&IF((SUMIFS($R$2:$R$978,$K$2:$K$978,"Cross-platform behavior",$L$2:$L$978,$A126))>0,"Cross-platform behavior ("&(SUMIFS($R$2:$R$978,$K$2:$K$978,"Cross-platform behavior",$L$2:$L$978,$A126))&"); ","")&IF((SUMIFS($R$2:$R$978,$K$2:$K$978,"Growth and future plans",$L$2:$L$978,$A126))>0,"Growth and future plans ("&(SUMIFS($R$2:$R$978,$K$2:$K$978,"Growth and future plans",$L$2:$L$978,$A126))&"); ","") -> Completion and feedback (4); Growth and future plans (1); | F126: =SUMIFS($P$2:$P$978,$L$2:$L$978,$A126) -> 4 | J126: ='Raw Atomic Data (Pro)'!A126 -> Anita | K126: ='Raw Atomic Data (Pro)'!C126 -> Motivation | L126: ='Raw Atomic Data (Pro)'!D126 -> motivation-emotional-connection | M126: ='Raw Atomic Data (Pro)'!E126 -> value-statement | N126: =IF(OR(M126="friction",M126="need",M126="workaround"),1,0) -> 0 | O126: =IF(COUNTIFS($K$2:K126,K126,$L$2:L126,L126,$M$2:M126,M126,$J$2:J126,J126)=1,1,0) -> 1 | P126: =IF(AND(N126=1,S126=1,COUNTIFS($L$2:L126,L126,$J$2:J126,J126,$N$2:N126,1,$S$2:S126,1)=1),1,0) -> 0 | Q126: =IF(AND(N126=1,S126=1,COUNTIFS($L$2:L126,L126,$K$2:K126,K126,$N$2:N126,1,$S$2:S126,1)=1),1,0) -> 0 | R126: =IF(AND(N126=1,COUNTIFS($K$2:K126,K126,$L$2:L126,L126,$J$2:J126,J126,$N$2:N126,1)=1),1,0) -> 0 | S126: =IF(AND(K126<>"Context and provider model",K126<>"Motivation"),1,0) -> 0
... A132: search-ranking-visibility | B132: =IFERROR(INDEX('Theme Legend'!$B$2:$B$31,MATCH($A132,'Theme Legend'!$A$2:$A$31,0)),"") -> Rover's search-ranking/algorithm and how it affects a sitter's visibility, especially for new or lower-ranked sitters. | C132: =IF(SUMIFS($O$2:$O$978,$L$2:$L$978,$A132,$M$2:$M$978,"friction",$K$2:$K$978,"<>Context and provider model",$K$2:$K$978,"<>Motivation")>0,"friction; ","")&IF(SUMIFS($O$2:$O$978,$L$2:$L$978,$A132,$M$2:$M$978,"need",$K$2:$K$978,"<>Context and provider model",$K$2:$K$978,"<>Motivation")>0,"need; ","")&IF(SUMIFS($O$2:$O$978,$L$2:$L$978,$A132,$M$2:$M$978,"workaround",$K$2:$K$978,"<>Context and provider model",$K$2:$K$978,"<>Motivation")>0,"workaround; ","") -> friction; need; workaround; | D132: =SUMIFS($Q$2:$Q$978,$L$2:$L$978,$A132) -> 3 | E132: =IF((SUMIFS($R$2:$R$978,$K$2:$K$978,"Client acquisition",$L$2:$L$978,$A132))>0,"Client acquisition ("&(SUMIFS($R$2:$R$978,$K$2:$K$978,"Client acquisition",$L$2:$L$978,$A132))&"); ","")&IF((SUMIFS($R$2:$R$978,$K$2:$K$978,"Evaluation and meet-and-greet",$L$2:$L$978,$A132))>0,"Evaluation and meet-and-greet ("&(SUMIFS($R$2:$R$978,$K$2:$K$978,"Evaluation and meet-and-greet",$L$2:$L$978,$A132))&"); ","")&IF((SUMIFS($R$2:$R$978,$K$2:$K$978,"Booking and availability",$L$2:$L$978,$A132))>0,"Booking and availability ("&(SUMIFS($R$2:$R$978,$K$2:$K$978,"Booking and availability",$L$2:$L$978,$A132))&"); ","")&IF((SUMIFS($R$2:$R$978,$K$2:$K$978,"Sitting preparation",$L$2:$L$978,$A132))>0,"Sitting preparation ("&(SUMIFS($R$2:$R$978,$K$2:$K$978,"Sitting preparation",$L$2:$L$978,$A132))&"); ","")&IF((SUMIFS($R$2:$R$978,$K$2:$K$978,"Service delivery",$L$2:$L$978,$A132))>0,"Service delivery ("&(SUMIFS($R$2:$R$978,$K$2:$K$978,"Service delivery",$L$2:$L$978,$A132))&"); ","")&IF((SUMIFS($R$2:$R$978,$K$2:$K$978,"Client communication",$L$2:$L$978,$A132))>0,"Client communication ("&(SUMIFS($R$2:$R$978,$K$2:$K$978,"Client communication",$L$2:$L$978,$A132))&"); ","")&IF((SUMIFS($R$2:$R$978,$K$2:$K$978,"Completion and feedback",$L$2:$L$978,$A132))>0,"Completion and feedback ("&(SUMIFS($R$2:$R$978,$K$2:$K$978,"Completion and feedback",$L$2:$L$978,$A132))&"); ","")&IF((SUMIFS($R$2:$R$978,$K$2:$K$978,"Payments and earnings",$L$2:$L$978,$A132))>0,"Payments and earnings ("&(SUMIFS($R$2:$R$978,$K$2:$K$978,"Payments and earnings",$L$2:$L$978,$A132))&"); ","")&IF((SUMIFS($R$2:$R$978,$K$2:$K$978,"Cross-platform behavior",$L$2:$L$978,$A132))>0,"Cross-platform behavior ("&(SUMIFS($R$2:$R$978,$K$2:$K$978,"Cross-platform behavior",$L$2:$L$978,$A132))&"); ","")&IF((SUMIFS($R$2:$R$978,$K$2:$K$978,"Growth and future plans",$L$2:$L$978,$A132))>0,"Growth and future plans ("&(SUMIFS($R$2:$R$978,$K$2:$K$978,"Growth and future plans",$L$2:$L$978,$A132))&"); ","") -> Client acquisition (1); Booking and availability (1); Growth and future plans (1); | F132: =SUMIFS($P$2:$P$978,$L$2:$L$978,$A132) -> 1 | J132: ='Raw Atomic Data (Pro)'!A132 -> Becky | K132: ='Raw Atomic Data (Pro)'!C132 -> Motivation | L132: ='Raw Atomic Data (Pro)'!D132 -> motivation-emotional-connection | M132: ='Raw Atomic Data (Pro)'!E132 -> value-statement | N132: =IF(OR(M132="friction",M132="need",M132="workaround"),1,0) -> 0 | O132: =IF(COUNTIFS($K$2:K132,K132,$L$2:L132,L132,$M$2:M132,M132,$J$2:J132,J132)=1,1,0) -> 1 | P132: =IF(AND(N132=1,S132=1,COUNTIFS($L$2:L132,L132,$J$2:J132,J132,$N$2:N132,1,$S$2:S132,1)=1),1,0) -> 0 | Q132: =IF(AND(N132=1,S132=1,COUNTIFS($L$2:L132,L132,$K$2:K132,K132,$N$2:N132,1,$S$2:S132,1)=1),1,0) -> 0 | R132: =IF(AND(N132=1,COUNTIFS($K$2:K132,K132,$L$2:L132,L132,$J$2:J132,J132,$N$2:N132,1)=1),1,0) -> 0 | S132: =IF(AND(K132<>"Context and provider model",K132<>"Motivation"),1,0) -> 0
J133: ='Raw Atomic Data (Pro)'!A133 -> Becky | K133: ='Raw Atomic Data (Pro)'!C133 -> Motivation | L133: ='Raw Atomic Data (Pro)'!D133 -> motivation-emotional-connection | M133: ='Raw Atomic Data (Pro)'!E133 -> value-statement | N133: =IF(OR(M133="friction",M133="need",M133="workaround"),1,0) -> 0 | O133: =IF(COUNTIFS($K$2:K133,K133,$L$2:L133,L133,$M$2:M133,M133,$J$2:J133,J133)=1,1,0) -> 0 | P133: =IF(AND(N133=1,S133=1,COUNTIFS($L$2:L133,L133,$J$2:J133,J133,$N$2:N133,1,$S$2:S133,1)=1),1,0) -> 0 | Q133: =IF(AND(N133=1,S133=1,COUNTIFS($L$2:L133,L133,$K$2:K133,K133,$N$2:N133,1,$S$2:S133,1)=1),1,0) -> 0 | R133: =IF(AND(N133=1,COUNTIFS($K$2:K133,K133,$L$2:L133,L133,$J$2:J133,J133,$N$2:N133,1)=1),1,0) -> 0 | S133: =IF(AND(K133<>"Context and provider model",K133<>"Motivation"),1,0) -> 0
A134: Note: 'Total distinct Pro providers (any stage, any FNW type)' counts each provider once even if they raised the same theme as more than one type (e.g. both a friction and a need) or in more than one stage -- it is a true distinct-provider count across the whole journey, not a sum of the per-stage counts in the previous column. The per-stage counts in 'Which stages' are themselves also true distinct-provider counts (a provider raising the same theme as both a friction and a need within one stage is counted once for that stage, not twice). All counts on this sheet are live formulas referencing Raw Atomic Data (Pro) through the hidden helper columns J:S (S excludes the background Context/Motivation categories from all counts on this sheet); they recompute automatically if the raw data changes. | J134: ='Raw Atomic Data (Pro)'!A134 -> Becky | K134: ='Raw Atomic Data (Pro)'!C134 -> Motivation | L134: ='Raw Atomic Data (Pro)'!D134 -> motivation-emotional-connection | M134: ='Raw Atomic Data (Pro)'!E134 -> value-statement | N134: =IF(OR(M134="friction",M134="need",M134="workaround"),1,0) -> 0 | O134: =IF(COUNTIFS($K$2:K134,K134,$L$2:L134,L134,$M$2:M134,M134,$J$2:J134,J134)=1,1,0) -> 0 | P134: =IF(AND(N134=1,S134=1,COUNTIFS($L$2:L134,L134,$J$2:J134,J134,$N$2:N134,1,$S$2:S134,1)=1),1,0) -> 0 | Q134: =IF(AND(N134=1,S134=1,COUNTIFS($L$2:L134,L134,$K$2:K134,K134,$N$2:N134,1,$S$2:S134,1)=1),1,0) -> 0 | R134: =IF(AND(N134=1,COUNTIFS($K$2:K134,K134,$L$2:L134,L134,$J$2:J134,J134,$N$2:N134,1)=1),1,0) -> 0 | S134: =IF(AND(K134<>"Context and provider model",K134<>"Motivation"),1,0) -> 0
J135: ='Raw Atomic Data (Pro)'!A135 -> Becky | K135: ='Raw Atomic Data (Pro)'!C135 -> Motivation | L135: ='Raw Atomic Data (Pro)'!D135 -> motivation-emotional-connection | M135: ='Raw Atomic Data (Pro)'!E135 -> fact | N135: =IF(OR(M135="friction",M135="need",M135="workaround"),1,0) -> 0 | O135: =IF(COUNTIFS($K$2:K135,K135,$L$2:L135,L135,$M$2:M135,M135,$J$2:J135,J135)=1,1,0) -> 0 | P135: =IF(AND(N135=1,S135=1,COUNTIFS($L$2:L135,L135,$J$2:J135,J135,$N$2:N135,1,$S$2:S135,1)=1),1,0) -> 0 | Q135: =IF(AND(N135=1,S135=1,COUNTIFS($L$2:L135,L135,$K$2:K135,K135,$N$2:N135,1,$S$2:S135,1)=1),1,0) -> 0 | R135: =IF(AND(N135=1,COUNTIFS($K$2:K135,K135,$L$2:L135,L135,$J$2:J135,J135,$N$2:N135,1)=1),1,0) -> 0 | S135: =IF(AND(K135<>"Context and provider model",K135<>"Motivation"),1,0) -> 0
J136: ='Raw Atomic Data (Pro)'!A136 -> Becky | K136: ='Raw Atomic Data (Pro)'!C136 -> Motivation | L136: ='Raw Atomic Data (Pro)'!D136 -> motivation-emotional-connection | M136: ='Raw Atomic Data (Pro)'!E136 -> value-statement | N136: =IF(OR(M136="friction",M136="need",M136="workaround"),1,0) -> 0 | O136: =IF(COUNTIFS($K$2:K136,K136,$L$2:L136,L136,$M$2:M136,M136,$J$2:J136,J136)=1,1,0) -> 0 | P136: =IF(AND(N136=1,S136=1,COUNTIFS($L$2:L136,L136,$J$2:J136,J136,$N$2:N136,1,$S$2:S136,1)=1),1,0) -> 0 | Q136: =IF(AND(N136=1,S136=1,COUNTIFS($L$2:L136,L136,$K$2:K136,K136,$N$2:N136,1,$S$2:S136,1)=1),1,0) -> 0 | R136: =IF(AND(N136=1,COUNTIFS($K$2:K136,K136,$L$2:L136,L136,$J$2:J136,J136,$N$2:N136,1)=1),1,0) -> 0 | S136: =IF(AND(K136<>"Context and provider model",K136<>"Motivation"),1,0) -> 0
J137: ='Raw Atomic Data (Pro)'!A137 -> Becky | K137: ='Raw Atomic Data (Pro)'!C137 -> Motivation | L137: ='Raw Atomic Data (Pro)'!D137 -> motivation-emotional-connection | M137: ='Raw Atomic Data (Pro)'!E137 -> fact | N137: =IF(OR(M137="friction",M137="need",M137="workaround"),1,0) -> 0 | O137: =IF(COUNTIFS($K$2:K137,K137,$L$2:L137,L137,$M$2:M137,M137,$J$2:J137,J137)=1,1,0) -> 0 | P137: =IF(AND(N137=1,S137=1,COUNTIFS($L$2:L137,L137,$J$2:J137,J137,$N$2:N137,1,$S$2:S137,1)=1),1,0) -> 0 | Q137: =IF(AND(N137=1,S137=1,COUNTIFS($L$2:L137,L137,$K$2:K137,K137,$N$2:N137,1,$S$2:S137,1)=1),1,0) -> 0 | R137: =IF(AND(N137=1,COUNTIFS($K$2:K137,K137,$L$2:L137,L137,$J$2:J137,J137,$N$2:N137,1)=1),1,0) -> 0 | S137: =IF(AND(K137<>"Context and provider model",K137<>"Motivation"),1,0) -> 0
J138: ='Raw Atomic Data (Pro)'!A138 -> Becky | K138: ='Raw Atomic Data (Pro)'!C138 -> Motivation | L138: ='Raw Atomic Data (Pro)'!D138 -> motivation-emotional-connection | M138: ='Raw Atomic Data (Pro)'!E138 -> value-statement | N138: =IF(OR(M138="friction",M138="need",M138="workaround"),1,0) -> 0 | O138: =IF(COUNTIFS($K$2:K138,K138,$L$2:L138,L138,$M$2:M138,M138,$J$2:J138,J138)=1,1,0) -> 0 | P138: =IF(AND(N138=1,S138=1,COUNTIFS($L$2:L138,L138,$J$2:J138,J138,$N$2:N138,1,$S$2:S138,1)=1),1,0) -> 0 | Q138: =IF(AND(N138=1,S138=1,COUNTIFS($L$2:L138,L138,$K$2:K138,K138,$N$2:N138,1,$S$2:S138,1)=1),1,0) -> 0 | R138: =IF(AND(N138=1,COUNTIFS($K$2:K138,K138,$L$2:L138,L138,$J$2:J138,J138,$N$2:N138,1)=1),1,0) -> 0 | S138: =IF(AND(K138<>"Context and provider model",K138<>"Motivation"),1,0) -> 0
J139: ='Raw Atomic Data (Pro)'!A139 -> Becky | K139: ='Raw Atomic Data (Pro)'!C139 -> Motivation | L139: ='Raw Atomic Data (Pro)'!D139 -> motivation-emotional-connection | M139: ='Raw Atomic Data (Pro)'!E139 -> value-statement | N139: =IF(OR(M139="friction",M139="need",M139="workaround"),1,0) -> 0 | O139: =IF(COUNTIFS($K$2:K139,K139,$L$2:L139,L139,$M$2:M139,M139,$J$2:J139,J139)=1,1,0) -> 0 | P139: =IF(AND(N139=1,S139=1,COUNTIFS($L$2:L139,L139,$J$2:J139,J139,$N$2:N139,1,$S$2:S139,1)=1),1,0) -> 0 | Q139: =IF(AND(N139=1,S139=1,COUNTIFS($L$2:L139,L139,$K$2:K139,K139,$N$2:N139,1,$S$2:S139,1)=1),1,0) -> 0 | R139: =IF(AND(N139=1,COUNTIFS($K$2:K139,K139,$L$2:L139,L139,$J$2:J139,J139,$N$2:N139,1)=1),1,0) -> 0 | S139: =IF(AND(K139<>"Context and provider model",K139<>"Motivation"),1,0) -> 0
J140: ='Raw Atomic Data (Pro)'!A140 -> Bruna | K140: ='Raw Atomic Data (Pro)'!C140 -> Motivation | L140: ='Raw Atomic Data (Pro)'!D140 -> motivation-emotional-connection | M140: ='Raw Atomic Data (Pro)'!E140 -> fact | N140: =IF(OR(M140="friction",M140="need",M140="workaround"),1,0) -> 0 | O140: =IF(COUNTIFS($K$2:K140,K140,$L$2:L140,L140,$M$2:M140,M140,$J$2:J140,J140)=1,1,0) -> 1 | P140: =IF(AND(N140=1,S140=1,COUNTIFS($L$2:L140,L140,$J$2:J140,J140,$N$2:N140,1,$S$2:S140,1)=1),1,0) -> 0 | Q140: =IF(AND(N140=1,S140=1,COUNTIFS($L$2:L140,L140,$K$2:K140,K140,$N$2:N140,1,$S$2:S140,1)=1),1,0) -> 0 | R140: =IF(AND(N140=1,COUNTIFS($K$2:K140,K140,$L$2:L140,L140,$J$2:J140,J140,$N$2:N140,1)=1),1,0) -> 0 | S140: =IF(AND(K140<>"Context and provider model",K140<>"Motivation"),1,0) -> 0
J141: ='Raw Atomic Data (Pro)'!A141 -> Bruna | K141: ='Raw Atomic Data (Pro)'!C141 -> Motivation | L141: ='Raw Atomic Data (Pro)'!D141 -> motivation-emotional-connection | M141: ='Raw Atomic Data (Pro)'!E141 -> fact | N141: =IF(OR(M141="friction",M141="need",M141="workaround"),1,0) -> 0 | O141: =IF(COUNTIFS($K$2:K141,K141,$L$2:L141,L141,$M$2:M141,M141,$J$2:J141,J141)=1,1,0) -> 0 | P141: =IF(AND(N141=1,S141=1,COUNTIFS($L$2:L141,L141,$J$2:J141,J141,$N$2:N141,1,$S$2:S141,1)=1),1,0) -> 0 | Q141: =IF(AND(N141=1,S141=1,COUNTIFS($L$2:L141,L141,$K$2:K141,K141,$N$2:N141,1,$S$2:S141,1)=1),1,0) -> 0 | R141: =IF(AND(N141=1,COUNTIFS($K$2:K141,K141,$L$2:L141,L141,$J$2:J141,J141,$N$2:N141,1)=1),1,0) -> 0 | S141: =IF(AND(K141<>"Context and provider model",K141<>"Motivation"),1,0) -> 0
J142: ='Raw Atomic Data (Pro)'!A142 -> Bruna | K142: ='Raw Atomic Data (Pro)'!C142 -> Motivation | L142: ='Raw Atomic Data (Pro)'!D142 -> motivation-emotional-connection | M142: ='Raw Atomic Data (Pro)'!E142 -> value-statement | N142: =IF(OR(M142="friction",M142="need",M142="workaround"),1,0) -> 0 | O142: =IF(COUNTIFS($K$2:K142,K142,$L$2:L142,L142,$M$2:M142,M142,$J$2:J142,J142)=1,1,0) -> 1 | P142: =IF(AND(N142=1,S142=1,COUNTIFS($L$2:L142,L142,$J$2:J142,J142,$N$2:N142,1,$S$2:S142,1)=1),1,0) -> 0 | Q142: =IF(AND(N142=1,S142=1,COUNTIFS($L$2:L142,L142,$K$2:K142,K142,$N$2:N142,1,$S$2:S142,1)=1),1,0) -> 0 | R142: =IF(AND(N142=1,COUNTIFS($K$2:K142,K142,$L$2:L142,L142,$J$2:J142,J142,$N$2:N142,1)=1),1,0) -> 0 | S142: =IF(AND(K142<>"Context and provider model",K142<>"Motivation"),1,0) -> 0
J143: ='Raw Atomic Data (Pro)'!A143 -> Bruna | K143: ='Raw Atomic Data (Pro)'!C143 -> Motivation | L143: ='Raw Atomic Data (Pro)'!D143 -> motivation-emotional-connection | M143: ='Raw Atomic Data (Pro)'!E143 -> fact | N143: =IF(OR(M143="friction",M143="need",M143="workaround"),1,0) -> 0 | O143: =IF(COUNTIFS($K$2:K143,K143,$L$2:L143,L143,$M$2:M143,M143,$J$2:J143,J143)=1,1,0) -> 0 | P143: =IF(AND(N143=1,S143=1,COUNTIFS($L$2:L143,L143,$J$2:J143,J143,$N$2:N143,1,$S$2:S143,1)=1),1,0) -> 0 | Q143: =IF(AND(N143=1,S143=1,COUNTIFS($L$2:L143,L143,$K$2:K143,K143,$N$2:N143,1,$S$2:S143,1)=1),1,0) -> 0 | R143: =IF(AND(N143=1,COUNTIFS($K$2:K143,K143,$L$2:L143,L143,$J$2:J143,J143,$N$2:N143,1)=1),1,0) -> 0 | S143: =IF(AND(K143<>"Context and provider model",K143<>"Motivation"),1,0) -> 0
J144: ='Raw Atomic Data (Pro)'!A144 -> Bruna | K144: ='Raw Atomic Data (Pro)'!C144 -> Motivation | L144: ='Raw Atomic Data (Pro)'!D144 -> motivation-emotional-connection | M144: ='Raw Atomic Data (Pro)'!E144 -> value-statement | N144: =IF(OR(M144="friction",M144="need",M144="workaround"),1,0) -> 0 | O144: =IF(COUNTIFS($K$2:K144,K144,$L$2:L144,L144,$M$2:M144,M144,$J$2:J144,J144)=1,1,0) -> 0 | P144: =IF(AND(N144=1,S144=1,COUNTIFS($L$2:L144,L144,$J$2:J144,J144,$N$2:N144,1,$S$2:S144,1)=1),1,0) -> 0 | Q144: =IF(AND(N144=1,S144=1,COUNTIFS($L$2:L144,L144,$K$2:K144,K144,$N$2:N144,1,$S$2:S144,1)=1),1,0) -> 0 | R144: =IF(AND(N144=1,COUNTIFS($K$2:K144,K144,$L$2:L144,L144,$J$2:J144,J144,$N$2:N144,1)=1),1,0) -> 0 | S144: =IF(AND(K144<>"Context and provider model",K144<>"Motivation"),1,0) -> 0
J145: ='Raw Atomic Data (Pro)'!A145 -> Colin | K145: ='Raw Atomic Data (Pro)'!C145 -> Motivation | L145: ='Raw Atomic Data (Pro)'!D145 -> motivation-emotional-connection | M145: ='Raw Atomic Data (Pro)'!E145 -> value-statement | N145: =IF(OR(M145="friction",M145="need",M145="workaround"),1,0) -> 0 | O145: =IF(COUNTIFS($K$2:K145,K145,$L$2:L145,L145,$M$2:M145,M145,$J$2:J145,J145)=1,1,0) -> 1 | P145: =IF(AND(N145=1,S145=1,COUNTIFS($L$2:L145,L145,$J$2:J145,J145,$N$2:N145,1,$S$2:S145,1)=1),1,0) -> 0 | Q145: =IF(AND(N145=1,S145=1,COUNTIFS($L$2:L145,L145,$K$2:K145,K145,$N$2:N145,1,$S$2:S145,1)=1),1,0) -> 0 | R145: =IF(AND(N145=1,COUNTIFS($K$2:K145,K145,$L$2:L145,L145,$J$2:J145,J145,$N$2:N145,1)=1),1,0) -> 0 | S145: =IF(AND(K145<>"Context and provider model",K145<>"Motivation"),1,0) -> 0
J146: ='Raw Atomic Data (Pro)'!A146 -> Colin | K146: ='Raw Atomic Data (Pro)'!C146 -> Motivation | L146: ='Raw Atomic Data (Pro)'!D146 -> motivation-emotional-connection | M146: ='Raw Atomic Data (Pro)'!E146 -> value-statement | N146: =IF(OR(M146="friction",M146="need",M146="workaround"),1,0) -> 0 | O146: =IF(COUNTIFS($K$2:K146,K146,$L$2:L146,L146,$M$2:M146,M146,$J$2:J146,J146)=1,1,0) -> 0 | P146: =IF(AND(N146=1,S146=1,COUNTIFS($L$2:L146,L146,$J$2:J146,J146,$N$2:N146,1,$S$2:S146,1)=1),1,0) -> 0 | Q146: =IF(AND(N146=1,S146=1,COUNTIFS($L$2:L146,L146,$K$2:K146,K146,$N$2:N146,1,$S$2:S146,1)=1),1,0) -> 0 | R146: =IF(AND(N146=1,COUNTIFS($K$2:K146,K146,$L$2:L146,L146,$J$2:J146,J146,$N$2:N146,1)=1),1,0) -> 0 | S146: =IF(AND(K146<>"Context and provider model",K146<>"Motivation"),1,0) -> 0
... J978: ='Raw Atomic Data (Pro)'!A978 -> Ashley P. | K978: ='Raw Atomic Data (Pro)'!C978 -> Growth and future plans | L978: ='Raw Atomic Data (Pro)'!D978 -> messaging-platform-mechanics | M978: ='Raw Atomic Data (Pro)'!E978 -> friction | N978: =IF(OR(M978="friction",M978="need",M978="workaround"),1,0) -> 1 | O978: =IF(COUNTIFS($K$2:K978,K978,$L$2:L978,L978,$M$2:M978,M978,$J$2:J978,J978)=1,1,0) -> 1 | P978: =IF(AND(N978=1,S978=1,COUNTIFS($L$2:L978,L978,$J$2:J978,J978,$N$2:N978,1,$S$2:S978,1)=1),1,0) -> 0 | Q978: =IF(AND(N978=1,S978=1,COUNTIFS($L$2:L978,L978,$K$2:K978,K978,$N$2:N978,1,$S$2:S978,1)=1),1,0) -> 0 | R978: =IF(AND(N978=1,COUNTIFS($K$2:K978,K978,$L$2:L978,L978,$J$2:J978,J978,$N$2:N978,1)=1),1,0) -> 0 | S978: =IF(AND(K978<>"Context and provider model",K978<>"Motivation"),1,0) -> 1
