Workbook

Sheet ⚙️ Settings
A1: Study Start Date (fill in once confirmed): | B1: 46213
A3: Week # in the Entries and Weekly Digest tabs is calculated from this date. Leave it blank and those columns will show blank; fill it in once your kickoff date is confirmed and everything recalculates automatically.

Sheet 📋 Entries
A1: ROVER DIARY STUDY — SYNTHESIS ANALYSIS TOOL
A2: Date | B2: User Name | C2: Segment | D2: Question | E2: Task Type | F2: Experience Moment | G2: Workflow Area | H2: Tool Used | I2: Platform Role | J2: Behavior | K2: Need | L2: Friction | M2: Value | N2: Signal | O2: Emotion | P2: Opportunity | Q2: Description | R2: Has Attachment? | S2: Attachment | T2: Link | U2: Observations | V2: Week #
A3: 46217 | B3: Richard | C3: M | D3: Topic 2. That's me | Q3: I’m Richard and I live in Austin, Texas. I’m 65 years old and I am a retired medical doctor. I have been dog sitting for my neighbors since the pandemic started. Then one of my neighbors mentioned Rover and I started doing even more pet sitting in the Northwest Austin area. I enjoy reading and researching, weightlifting and walking, and fresh air and sunshine. | R3: No | V3: =IF($A3="","",IF('⚙️ Settings'!$B$1="","",INT(($A3-'⚙️ Settings'!$B$1)/7)+1))
A4: 46217 | B4: Shania | C4: T | D4: Topic 1. Welcome | Q4: Sounds good! | R4: No | V4: =IF($A4="","",IF('⚙️ Settings'!$B$1="","",INT(($A4-'⚙️ Settings'!$B$1)/7)+1))
A5: 46217 | B5: Shania | C5: T | D5: Topic 2. That's me | Q5: I’m Shania. | R5: No | V5: =IF($A5="","",IF('⚙️ Settings'!$B$1="","",INT(($A5-'⚙️ Settings'!$B$1)/7)+1))
A6: 46212 | B6: Kristin | C6: T | D6: Topic 1. Welcome | Q6: Got it! | R6: No | V6: =IF($A6="","",IF('⚙️ Settings'!$B$1="","",INT(($A6-'⚙️ Settings'!$B$1)/7)+1))
A7: 46212 | B7: Kristin | C7: T | D7: Topic 2. That's me | Q7: My name is Kristen. I live in New Mexico, USA. 41. I own my own home. Program Manager. I enjoy reading, traveling and going to concerts. | R7: No | V7: =IF($A7="","",IF('⚙️ Settings'!$B$1="","",INT(($A7-'⚙️ Settings'!$B$1)/7)+1))
A8: 46212 | B8: Tifany | C8: T | D8: Topic 2. That's me | Q8: Hello! I’m Tifany! I’m from Washington state in the good ole US-of-A. I’m 42 years old, I’m single and live alone, and I’m a Bible Instructor as my main source of income. I also do Rover, and have an independent, small business caring for pets called Havenly Paws. Things I enjoy doing would include scrolling Facebook reels about stupid mukbangs (why? I have absolutely no idea because I don’t even eat that stuff lol!), spending time with my 5 month old grandbaby, church functions, ministry, learning more about God’s love for us, socializing, new adventures, sewing and quilting, helping others, learning and playing piano, singing, and most forms of creativity. I also enjoy debating, which I know that most people hate, but it’s because I really love deep thinking and the opportunity to see perspectives I haven’t yet considered. I’m more than willing to be wrong and it’s not that I need to “win”, I just want to learn more — I love learning! But being right can be really fun too (haha). Philosophizing is totes exciting! | R8: Yes | S8: Photo | V8: =IF($A8="","",IF('⚙️ Settings'!$B$1="","",INT(($A8-'⚙️ Settings'!$B$1)/7)+1))
A9: 46212 | B9: Tifany | C9: T | D9: Topic 1. Welcome | Q9: Thank you! | R9: No | V9: =IF($A9="","",IF('⚙️ Settings'!$B$1="","",INT(($A9-'⚙️ Settings'!$B$1)/7)+1))
A10: 46212 | B10: Kristin | C10: T | D10: Topic 3. Me on Rover | Q10: I have been using Rover since 2018. I started using Rover for supplemental income when I was promoted at my full-time job and was no longer receiving overtime. I provide dog- walking, dropin visits and housesitting. Total bookings 1705 Petsitting experience includes pups and kitties to seniors. Medication administering, I love my regulars and meeting new clients. | R10: No | V10: =IF($A10="","",IF('⚙️ Settings'!$B$1="","",INT(($A10-'⚙️ Settings'!$B$1)/7)+1))
A11: 46212 | B11: Kristin | C11: T | D11: Topic 3. Me on Rover | R11: Yes | S11: Photo | V11: =IF($A11="","",IF('⚙️ Settings'!$B$1="","",INT(($A11-'⚙️ Settings'!$B$1)/7)+1))
A12: 46212 | B12: Deborah | C12: N | D12: Topic 2. That's me | Q12: Deborah, but I prefer Debbie. I live in the US in Ohio. I am 74. I am retired and live alone. I enjoy nature, art, and music. I hike often and frequent indoor and outdoor concerts. I am an artist, working in acrylics with abstract and hand-painted details. | R12: No | V12: =IF($A12="","",IF('⚙️ Settings'!$B$1="","",INT(($A12-'⚙️ Settings'!$B$1)/7)+1))
A13: 46212 | B13: Deborah | C13: N | D13: Topic 3. Me on Rover | Q13: I recently started using Rover. I started because I sit with my families dogs and love doing it. I do not have a dog of my own any longer. I offer in home sitting for long weekends or extended vacations. I got my first booking within two days of posting my Rover availablity. I’ve found getting started on Rover easy. The tips on use of the site that were emailed to me later have been timely and helpful | R13: No | V13: =IF($A13="","",IF('⚙️ Settings'!$B$1="","",INT(($A13-'⚙️ Settings'!$B$1)/7)+1))
A14: 46212 | B14: Deborah | C14: N | D14: Topic 4. My motivation to become a pet sitter | Q14: I had a companion, some called her a dog, but she was my best friend. I could never replace her, but found I could get and give love from my families (my grand puppies) dogs. My daughter suggested I check out Rover as a way to combine my love of dogs, make best use of my available time, and earn some extra money. I stay in the clients home, follow their instructions and dogs habits to the letter. i.e. no people food. I would like to pick up long weekends or extended stay vacations once a month or so for extra income. | R14: No | V14: =IF($A14="","",IF('⚙️ Settings'!$B$1="","",INT(($A14-'⚙️ Settings'!$B$1)/7)+1))
A15: 46212 | B15: Deborah | C15: N | D15: Topic 2. That's me | R15: Yes | S15: Photo | V15: =IF($A15="","",IF('⚙️ Settings'!$B$1="","",INT(($A15-'⚙️ Settings'!$B$1)/7)+1))
A16: 46212 | B16: Deborah | C16: N | D16: Topic 1. Welcome | Q16: I found Rover easy to use. I have two meet and greets set for next week | R16: No | V16: =IF($A16="","",IF('⚙️ Settings'!$B$1="","",INT(($A16-'⚙️ Settings'!$B$1)/7)+1))
A17: 46212 | B17: Deborah | C17: N | D17: Topic 1. Welcome | Q17: I love dogs and animals in general. This is me bottle feeding a 9 month old baby bear. The coat is course and rough. This is Bean. He insisted on being pet as he drank. If I stopped petting he whined. | R17: Yes | S17: Photo | V17: =IF($A17="","",IF('⚙️ Settings'!$B$1="","",INT(($A17-'⚙️ Settings'!$B$1)/7)+1))
A18: 46213 | B18: Joey | C18: M | D18: Topic 1. Welcome | Q18: Thank you Myriel and Lisa for the introduction. Looking forward to meeting you soon! | R18: No | V18: =IF($A18="","",IF('⚙️ Settings'!$B$1="","",INT(($A18-'⚙️ Settings'!$B$1)/7)+1))
A19: 46213 | B19: Becky | C19: T | D19: Topic 1. Welcome | Q19: Acknowledged | R19: No | V19: =IF($A19="","",IF('⚙️ Settings'!$B$1="","",INT(($A19-'⚙️ Settings'!$B$1)/7)+1))
A20: 46217 | B20: Shania | C20: T | D20: Topic 1. Welcome | Q20: Sounds good! | R20: No | S20: None | V20: =IF($A20="","",IF('⚙️ Settings'!$B$1="","",INT(($A20-'⚙️ Settings'!$B$1)/7)+1))
A21: 46219 | B21: Alexandra | C21: N | D21: Topic 1. Welcome | Q21: Thank you! Happy to belong to this project investigation! | R21: No | S21: None | V21: =IF($A21="","",IF('⚙️ Settings'!$B$1="","",INT(($A21-'⚙️ Settings'!$B$1)/7)+1))
A22: 46214 | B22: Annabelle | C22: N | D22: Topic 2. That's me | Q22: My name is Bella and I live in Denver, CO in the United States. I am 23 years old and am living with a roommate in an apartment. I am in grad school getting my masters in social work and also working as a therapist for adolescents. I enjoy skiing, hiking, listening to music, being outside, and meeting new people! | R22: No | S22: None | V22: =IF($A22="","",IF('⚙️ Settings'!$B$1="","",INT(($A22-'⚙️ Settings'!$B$1)/7)+1))
A23: 46216 | B23: Naomi | C23: M | D23: Topic 2. That's me | Q23: Naomi USA 37 I own a large single family home in the bronx with a big back yard. I rent out airbnb and 2 long term bedrooms. I used to work in Tech, now I earn rental income and work as a personal trainer, group class instructor and dog sitter. I enjoy outside activities, yoga and MMA. | R23: No | S23: None | V23: =IF($A23="","",IF('⚙️ Settings'!$B$1="","",INT(($A23-'⚙️ Settings'!$B$1)/7)+1))
A24: 46216 | B24: Amy | C24: T | D24: Topic 2. That's me | Q24: My name is Amy. I live near Pittsburgh, Pennsylvania in the USA. I am 60 years old and live in a suburban home with my husband, 2 dogs and cat. We have 3 adult children, 2 of which live nearby. I enjoy walking, swimming, reading, true crime, crocheting, baking and spending time with my kids. I retired from teaching elementary music in June of 24 after 32 years in the profession. I miss the kids, but love the freedom of retirement. | R24: No | S24: None | V24: =IF($A24="","",IF('⚙️ Settings'!$B$1="","",INT(($A24-'⚙️ Settings'!$B$1)/7)+1))
A25: 46217 | B25: Colin | C25: T | D25: Topic 2. That's me | Q25: My name is Colin, I'm originally from Colorado in the USA but now live in Toronto, Canada with my wife and our dog, Pepsi. I have been a teacher for 15 years but I am sick of it and ready for a change. I was fortunate enough to be able to teach abroad in Asia for several years and spend a lot of time solo traveling to new places. I used to love rock and roll, going to the movies, and camping in the mountains. I still like all those but now that I'm older, I just want to spend quiet times with my wife and dog! | R25: No | S25: None | V25: =IF($A25="","",IF('⚙️ Settings'!$B$1="","",INT(($A25-'⚙️ Settings'!$B$1)/7)+1))
A26: 46217 | B26: Caroline | C26: M | D26: Topic 2. That's me | Q26: My name is Caroline and I am from the US born in Ohio and now living in the rural mountains of North Carolina. I am 43 and bought a home where I have a crystal store I sell online as well as taking over the family business of a travel agency! Before this I did Human Resources for 14 years and was a consultant too so hopefully that will help me find great discoveries to help you all in this research! I love to read, see live music and be in nature kayaking! | R26: No | S26: None | V26: =IF($A26="","",IF('⚙️ Settings'!$B$1="","",INT(($A26-'⚙️ Settings'!$B$1)/7)+1))
A27: 46218 | B27: Rachel | C27: N | D27: Topic 2. That's me | Q27: Hi! My name is Rachel, and I like in California. I'm 27 years old and live alone! I'm a city planner working for a government agency. I love hanging out with friends, going to the park, reading, dancing, playing tennis, and thrifting! I also LOVE dogs! | R27: No | S27: None | V27: =IF($A27="","",IF('⚙️ Settings'!$B$1="","",INT(($A27-'⚙️ Settings'!$B$1)/7)+1))
A28: 46218 | B28: Bruna | C28: T | D28: Topic 2. That's me | Q28: Hi! My name is Bruna, I'm 28 years old and I live in New Westminster, British Columbia, Canada, with my boyfriend. I'm from Brazil and have been living in Canada for about six years. I'm a professional dog trainer and pet care provider, and I run my own dog training business. I have a background in neuroscience and biomedicine, and I currently offer dog boarding through Rover. Dogs are a very big part of my daily life, both professionally and personally. Outside of work, I enjoy studying dog behaviour and continuing my education, singing, playing guitar, skiing, spending time with friends and travelling. I also really enjoy learning in general and I'm usually taking a course or becoming interested in a new subject. | R28: No | S28: None | V28: =IF($A28="","",IF('⚙️ Settings'!$B$1="","",INT(($A28-'⚙️ Settings'!$B$1)/7)+1))
A29: 46218 | B29: Ashley | C29: N | D29: Topic 2. That's me | Q29: My name is Ashley. I live in the United States. Jacksonville, Florida in the Springfield Area. I'm 24. I live in a two bedroom apartment with my fiancé and our son. I enjoy working at my job as a server assistant, spending quality time with family and friends, being a tarot reader and creating my botanical products, and spending time outside and with my friends who has pets themselves. | R29: No | S29: None | V29: =IF($A29="","",IF('⚙️ Settings'!$B$1="","",INT(($A29-'⚙️ Settings'!$B$1)/7)+1))
A30: 46218 | B30: Emma | C30: M | D30: Topic 2. That's me | Q30: -Emma -USA, Ohio -27 -Rent an apartment, living alone with my 2 cats! -I work as a course scheduler for the business school at a university -I enjoy running, reading, listening to music (mostly kpop), watching soccer/football, and yoga -I'm left-handed -I've traveled to France, Spain, and Canada. My travel bucket list includes Japan, Iceland, Australia, Italy, Korea, Germany, Ireland, Norway, Turkey, Thailand, Morocco, and Switzerland -I studied international relations and Spanish in university | R30: No | S30: None | V30: =IF($A30="","",IF('⚙️ Settings'!$B$1="","",INT(($A30-'⚙️ Settings'!$B$1)/7)+1))
A31: 46219 | B31: Alexandra | C31: N | D31: Topic 2. That's me | Q31: Hey! My name is Alexandra, currently living in Alberta,Canada! I have 25 years old and I live with my sister. My current profession is Administrative Assistant and pet sitter. I enjoy share my time with pets, dancing, listen to music and eat desserts 😊❤️ | R31: No | S31: None | V31: =IF($A31="","",IF('⚙️ Settings'!$B$1="","",INT(($A31-'⚙️ Settings'!$B$1)/7)+1))
... A36: 46217 | B36: Colin | C36: T | D36: Topic 3. Me on Rover | Q36: I started using Rover in February 2025. Our dog at the time, Poncho, was diagnosed with meningitis in the fall of 2024 and sadly passed away a few months later after fighting so hard. We were very obviously devastated to lose Poncho, so we used Rover as a form of therapy for ourselves, a supplemental income, and as a way to spend more time with cute dogs. Our Rover business started slowly with mostly local walks and the occasional boarding. But soon after school ended and families were traveling during summer so we got a lot of boarding and house sitting requests. Altogether we've had ~20 different dogs board with us in our home, most for 3-10 day stays. we have had a few dogs stay with us for up to three weeks at a time though. I have also done house sitting about 10 times total but all for repeat clients. because we have our own dog now and live in a smaller apartment, we are only taking boarding requests from previous clients. currently we walk several dogs in the neighborhood and board a dog once every couple months. We also have one family who travel a lot and ask me to house/dog sit while they are away, usually for ~7 days at a time | R36: No | S36: None | V36: =IF($A36="","",IF('⚙️ Settings'!$B$1="","",INT(($A36-'⚙️ Settings'!$B$1)/7)+1))
A37: 46212 | B37: Deborah | C37: N | D37: Topic 1. Welcome | Q37: I found Rover easy to use. I have two meet and greets set for next week | R37: No | V37: =IF($A37="","",IF('⚙️ Settings'!$B$1="","",INT(($A37-'⚙️ Settings'!$B$1)/7)+1))
A38: 46220 | B38: Anita | C38: T | D38: Topic 1. Welcome | Q38: I am Anita | R38: No | V38: =IF($A38="","",IF('⚙️ Settings'!$B$1="","",INT(($A38-'⚙️ Settings'!$B$1)/7)+1))
A39: 46222 | B39: Emma | C39: M | D39: Topic 1. Welcome | Q39: Thank you!! | R39: No | V39: =IF($A39="","",IF('⚙️ Settings'!$B$1="","",INT(($A39-'⚙️ Settings'!$B$1)/7)+1))
A40: 46224 | B40: Alexia | C40: M | D40: Topic 1. Welcome | Q40: Sounds great thank you! | R40: No | V40: =IF($A40="","",IF('⚙️ Settings'!$B$1="","",INT(($A40-'⚙️ Settings'!$B$1)/7)+1))
A41: 46225 | B41: Dawn | C41: T | D41: Topic 1. Welcome | Q41: Took care of sweet golden doodle named Emi at my house. This was a booking through Rover. | R41: Yes | S41: Photo | V41: =IF($A41="","",IF('⚙️ Settings'!$B$1="","",INT(($A41-'⚙️ Settings'!$B$1)/7)+1))
A42: 46226 | B42: Emily | C42: N | D42: Topic 1. Welcome | Q42: Excited to join the study! | R42: No | V42: =IF($A42="","",IF('⚙️ Settings'!$B$1="","",INT(($A42-'⚙️ Settings'!$B$1)/7)+1))
A43: 46212 | B43: Kristin | C43: T | D43: Topic 2. That's me | Q43: My name is Kristen. I live in New Mexico, USA. 41. I own my own home. Program Manager. I enjoy reading, traveling and going to concerts. | R43: No | V43: =IF($A43="","",IF('⚙️ Settings'!$B$1="","",INT(($A43-'⚙️ Settings'!$B$1)/7)+1))
A44: 46212 | B44: Tifany | C44: T | D44: Topic 2. That's me | Q44: Hello! I’m Tifany! I’m from Washington state in the good ole US-of-A. I’m 42 years old, I’m single and live alone, and I’m a Bible Instructor as my main source of income. I also do Rover, and have an independent, small business caring for pets called Havenly Paws. Things I enjoy doing would include scrolling Facebook reels about stupid mukbangs (why? I have absolutely no idea because I don’t even eat that stuff lol!), spending time with my 5 month old grandbaby, church functions, ministry, learning more about God’s love for us, socializing, new adventures, sewing and quilting, helping others, learning and playing piano, singing, and most forms of creativity. I also enjoy debating, which I know that most people hate, but it’s because I really love deep thinking and the opportunity to see perspectives I haven’t yet considered. I’m more than willing to be wrong and it’s not that I need to “win”, I just want to learn more — I love learning! But being right can be really fun too (haha). Philosophizing is totes exciting! | R44: Yes | S44: Photo | V44: =IF($A44="","",IF('⚙️ Settings'!$B$1="","",INT(($A44-'⚙️ Settings'!$B$1)/7)+1))
A45: 46213 | B45: Andrew | C45: T | D45: Topic 2. That's me | Q45: My name is Drew. I live in the US— Tennessee, specifically. I’m 41 years old and I live alone. I’ve been a video editor by trade and I spend my free time watching movies and building prop replicas. | R45: No | V45: =IF($A45="","",IF('⚙️ Settings'!$B$1="","",INT(($A45-'⚙️ Settings'!$B$1)/7)+1))
A46: 46213 | B46: Joey | C46: M | D46: Topic 2. That's me | Q46: Hi! My name is Joey and I’m currently living in Ontario, Canada. I’m 28 years old and I currently rent a place and living with my partner. I am a registered social worker and my job is about volunteer management and youth group development. Outside of work, other than spending time with cats, I enjoy playing board games and camping. | R46: No | V46: =IF($A46="","",IF('⚙️ Settings'!$B$1="","",INT(($A46-'⚙️ Settings'!$B$1)/7)+1))
A47: 46213 | B47: Becky | C47: T | D47: Topic 2. That's me | Q47: My name is Becky. I live in San Jose, CA, USA. I am 36 and live alone in a 2 bedroom condo that I bought about 10 years ago. I recently started a new job as. Sr Manager of Project Managers on the Professional Services team at a cybersecurity company. My previous job was at a competitor doing similar work, and I was there for 8 years. When I am not working or dog sitting, I also volunteer at the Humane Society where I socialize with dogs. Otherwise I don’t have any particularly unique hobbies - I enjoy spending time with my friends and family, watching TV, going on adventures, I also exercise regularly. | R47: No | V47: =IF($A47="","",IF('⚙️ Settings'!$B$1="","",INT(($A47-'⚙️ Settings'!$B$1)/7)+1))
A48: 46213 | B48: Julia | C48: N | D48: Topic 2. That's me | Q48: Hi, my name is Julia. I’ve lived in Minnesota my whole life. I am 34 years old, married, with two children and one energetic Siberian husky. I live in a house and worked in a corporate job for the last 11 years, until recently getting laid off. Now I am taking some time off to care for my kids before they start school. My hobbies include: reading (mainly fantasy, thrillers or romance), walking/hiking with our family, and traveling to / camping at national parks throughout the country. My favorite parks I’ve been to so far include: Zion and Glacier national parks. | R48: No | V48: =IF($A48="","",IF('⚙️ Settings'!$B$1="","",INT(($A48-'⚙️ Settings'!$B$1)/7)+1))
A49: 46216 | B49: TR | C49: T | D49: Topic 2. That's me | Q49: My name is Tianrui and people would call me “TR” occasionally. I’m based in US, California. I’m 25, currently preparing for graduate school so I can apply this fall. I enjoy traveling, shopping and watching my cats :) | R49: No | V49: =IF($A49="","",IF('⚙️ Settings'!$B$1="","",INT(($A49-'⚙️ Settings'!$B$1)/7)+1))
A50: 46217 | B50: Shania | C50: T | D50: Topic 2. That's me | Q50: I'm Shania. | R50: No | V50: =IF($A50="","",IF('⚙️ Settings'!$B$1="","",INT(($A50-'⚙️ Settings'!$B$1)/7)+1))
A51: 46217 | B51: Colin | C51: T | D51: Topic 2. That's me | Q51: My name is Colin, I’m originally from Colorado in the USA but now live in Toronto, Canada with my wife and our dog, Pepsi. I have been a teacher for 15 years but I am sick of it and ready for a change. I was fortunate enough to be able to teach abroad in Asia for several years and spend a lot of time solo traveling to new places. I used to love rock and roll, going to the movies, and camping in the mountains. I still like all those but now that I’m older, I just want to spend quiet times with my wife and dog! | R51: No | V51: =IF($A51="","",IF('⚙️ Settings'!$B$1="","",INT(($A51-'⚙️ Settings'!$B$1)/7)+1))
A52: 46217 | B52: Colin | C52: T | D52: Topic 2. That's me | Q52: Pepsi! | R52: Yes | S52: Photo | V52: =IF($A52="","",IF('⚙️ Settings'!$B$1="","",INT(($A52-'⚙️ Settings'!$B$1)/7)+1))
A53: 46218 | B53: Rachel | C53: N | D53: Topic 2. That's me | Q53: Hi! My name is Rachel, and I like in California. I’m 27 years old and live alone! I’m a city planner working for a government agency. I love hanging out with friends, going to the park, reading, dancing, playing tennis, and thrifting! I also LOVE dogs! | R53: No | V53: =IF($A53="","",IF('⚙️ Settings'!$B$1="","",INT(($A53-'⚙️ Settings'!$B$1)/7)+1))
A54: 46218 | B54: Bruna | C54: T | D54: Topic 2. That's me | Q54: Hi! My name is Bruna, I’m 28 years old and I live in New Westminster, British Columbia, Canada, with my boyfriend. I’m from Brazil and have been living in Canada for about six years. I’m a professional dog trainer and pet care provider, and I run my own dog training business. I have a background in neuroscience and biomedicine, and I currently offer dog boarding through Rover. Dogs are a very big part of my daily life, both professionally and personally. Outside of work, I enjoy studying dog behaviour and continuing my education, singing, playing guitar, skiing, spending time with friends and travelling. I also really enjoy learning in general and I’m usually taking a course or becoming interested in a new subject. | R54: No | V54: =IF($A54="","",IF('⚙️ Settings'!$B$1="","",INT(($A54-'⚙️ Settings'!$B$1)/7)+1))
A55: 46218 | B55: Ashley | C55: N | D55: Topic 2. That's me | Q55: My name is Ashley. I live in the United States. Jacksonville, Florida in the Springfield Area. I’m 24. I live in a two bedroom apartment with my fiancé and our son. I enjoy working at my job as a server assistant, spending quality time with family and friends, being a tarot reader and creating my botanical products, and spending time outside and with my friends who has pets themselves. | R55: No | V55: =IF($A55="","",IF('⚙️ Settings'!$B$1="","",INT(($A55-'⚙️ Settings'!$B$1)/7)+1))
A56: 46218 | B56: Emma | C56: M | D56: Topic 2. That's me | Q56: -Emma -USA, Ohio -27 -Rent an apartment, living alone with my 2 cats! -I work as a course scheduler for the business school at a university -I enjoy running, reading, listening to music (mostly kpop), watching soccer/football, and yoga -I’m left-handed -I’ve traveled to France, Spain, and Canada. My travel bucket list includes Japan, Iceland, Australia, Italy, Korea, Germany, Ireland, Norway, Turkey, Thailand, Morocco, and Switzerland -I studied international relations and Spanish in university | R56: No | V56: =IF($A56="","",IF('⚙️ Settings'!$B$1="","",INT(($A56-'⚙️ Settings'!$B$1)/7)+1))
A57: 46218 | B57: Colin | C57: T | D57: Topic 2. That's me | R57: Yes | S57: Photo | V57: =IF($A57="","",IF('⚙️ Settings'!$B$1="","",INT(($A57-'⚙️ Settings'!$B$1)/7)+1))
A58: 46218 | B58: Cate | C58: M | D58: Topic 2. That's me | Q58: Cate MN, USA 39 In a single family home with my husband and 4 children Leadership Development Manager Staying active, cooking, photography, crafting, reading, family time | R58: No | V58: =IF($A58="","",IF('⚙️ Settings'!$B$1="","",INT(($A58-'⚙️ Settings'!$B$1)/7)+1))
A59: 46218 | B59: Megan | C59: M | D59: Topic 2. That's me | Q59: My name is Megan I’m 42 years old and I live in the Waterloo Region of Ontario with my 3 cats and 1 dog. I currently share my home with my ex-partner, who helps take care of my pets when I’m away doing house sits. It works well because he still gets to spend time with them and I know they’re happy and cared for while I’m gone. My main job is pet sitting and house sitting. I absolutely love animals and have always had a strong connection with them. I enjoy getting to know their little personalities, making them feel comfortable, and giving them lots of love and attention while their people are away. Outside of pet sitting I also do energy healing, mediumship, and intuitive channeling readings. I’m really interested in personal growth, spirituality, and learning more about ourselves and our own journeys. When I’m not working, I love being outside in nature, spending time near the water, and enjoying a slower pace of life. I’m a creative person and love things like colouring, making junk journals, and doing different crafts. I also enjoy journaling, meditation, and anything that helps me learn, grow, and connect with myself. Animals bring me so much joy, and I feel lucky that I get to spend so much of my time caring for them and building connections with both pets and their owners. | R59: No | V59: =IF($A59="","",IF('⚙️ Settings'!$B$1="","",INT(($A59-'⚙️ Settings'!$B$1)/7)+1))
A60: 46219 | B60: Alexandra | C60: N | D60: Topic 2. That's me | Q60: Hey! My name is Alexandra, currently living in Alberta,Canada! I have 25 years old and I live with my sister. My current profession is Administrative Assistant and pet sitter. I enjoy share my time with pets, dancing, listen to music and eat desserts ☺️❤️ | R60: No | V60: =IF($A60="","",IF('⚙️ Settings'!$B$1="","",INT(($A60-'⚙️ Settings'!$B$1)/7)+1))
A61: 46219 | B61: Jilian | C61: N | D61: Topic 2. That's me | Q61: My names Jillian, I’m in the US, I’m 31 years old. I live in my house with my dog and work a full time job and enjoy yoga and hiking. | R61: No | V61: =IF($A61="","",IF('⚙️ Settings'!$B$1="","",INT(($A61-'⚙️ Settings'!$B$1)/7)+1))
A62: 46220 | B62: Erika | C62: T | D62: Topic 2. That's me | Q62: I’m Erika and I live in British Columbia in Canada, I’m 30 years old and live with my husband and daughter. I’m an industrial engineer with MBA. I love spend time with my family visiting new places where we can know about Canadian culture and try new kinds of food. I like taking walks with my daughter specially in sunny days and sometimes we decide stay home and enjoy a movie or trivia games, which results very fun as well. | R62: No | V62: =IF($A62="","",IF('⚙️ Settings'!$B$1="","",INT(($A62-'⚙️ Settings'!$B$1)/7)+1))
A63: 46220 | B63: Shania | C63: T | D63: Topic 2. That's me | Q63: I'm Shania. I live in Quebec, Canada. I'm 23 years old. I live in the suburbs with my mother. I'm currently a part time worker. Current interests I have are building Lego and the Eurovision Song Contest. | R63: No | V63: =IF($A63="","",IF('⚙️ Settings'!$B$1="","",INT(($A63-'⚙️ Settings'!$B$1)/7)+1))
A64: 46220 | B64: Anita | C64: T | D64: Topic 2. That's me | Q64: I am Anita. I live in Sacramento California. | R64: No | V64: =IF($A64="","",IF('⚙️ Settings'!$B$1="","",INT(($A64-'⚙️ Settings'!$B$1)/7)+1))
A65: 46220 | B65: Anita | C65: T | D65: Topic 2. That's me | Q65: I am am experienced dog sitter. | R65: No | V65: =IF($A65="","",IF('⚙️ Settings'!$B$1="","",INT(($A65-'⚙️ Settings'!$B$1)/7)+1))
A66: 46220 | B66: Anita | C66: T | D66: Topic 2. That's me | Q66: I am retired and living alone | R66: No | V66: =IF($A66="","",IF('⚙️ Settings'!$B$1="","",INT(($A66-'⚙️ Settings'!$B$1)/7)+1))
A67: 46220 | B67: Anita | C67: T | D67: Topic 2. That's me | Q67: I love walking all of my wonderful puppies. | R67: No | V67: =IF($A67="","",IF('⚙️ Settings'!$B$1="","",INT(($A67-'⚙️ Settings'!$B$1)/7)+1))
A68: 46221 | B68: Emily | C68: N | D68: Topic 2. That's me | Q68: Hi! I’m Emily, 34, and recently moved back to Seattle, WA. It’s just me and my Cavalier King Charles Spaniel, Matilda, living in an apartment downtown. I work in marketing, and when I’m not working you’ll usually find us exploring the city, going on walks and hikes, grabbing coffee, or checking out new dog-friendly spots around the Pacific Northwest. | R68: No | V68: =IF($A68="","",IF('⚙️ Settings'!$B$1="","",INT(($A68-'⚙️ Settings'!$B$1)/7)+1))
A69: 46221 | B69: Desiree | C69: N | D69: Topic 2. That's me | Q69: Desiree Asheville, NC, USA 42 Currently living nomadically after returning this June from 2 years of international travel/living abroad. Primarily house/dog-sitting, and also staying with friends and family, and camping in nature. Entrepreneur - building women's group getaways. Also Independent Contractor - project management. I enjoy being active outdoors in nature (trail running, hiking, biking), all things movement (yoga, strength training, roller skating, etc.), healthy cooking at home, travel internationally & domestic - particularly to nature focused locations, hosting friends & family for visits and adventures, seeing live music, spending time with my partner & all dogs! | R69: No | V69: =IF($A69="","",IF('⚙️ Settings'!$B$1="","",INT(($A69-'⚙️ Settings'!$B$1)/7)+1))
A70: 46221 | B70: David | C70: N | D70: Topic 2. That's me | Q70: - David -United States of America -21 -live with family -AV integrator -theatre, gaming, playing with dogs | R70: No | V70: =IF($A70="","",IF('⚙️ Settings'!$B$1="","",INT(($A70-'⚙️ Settings'!$B$1)/7)+1))
A71: 46221 | B71: Melissa | C71: M | D71: Topic 2. That's me | Q71: Hi! I'm Melissa, I'm 45, live in Columbus, Ohio and I am a single mom to two boys 12 and 9. My oldest son has high needs and so flexibility in my work is very important. I'm currently unemployed but looking for full time work in communications. | R71: Yes | S71: Photo | V71: =IF($A71="","",IF('⚙️ Settings'!$B$1="","",INT(($A71-'⚙️ Settings'!$B$1)/7)+1))
A72: 46224 | B72: Alyssa | C72: N | D72: Topic 2. That's me | Q72: Hi I’m Alyssa! I am 19 years old from North Carolina, USA. Im living with my parents currently while being a college student studying Animal Care Management and Technology and I hope to be a Registered Veterinary Technician in the future. I’ve also worked as a pet sitter (mostly dog sitter) since I was younger for family friends. I have loved all animals my whole life. In my free time I love reading, spending time with friends and family, and taking care of my families sheep. | R72: No | V72: =IF($A72="","",IF('⚙️ Settings'!$B$1="","",INT(($A72-'⚙️ Settings'!$B$1)/7)+1))
A73: 46224 | B73: Alexia | C73: M | D73: Topic 2. That's me | Q73: Hello my name is Alexia Back, I live in Glennville GA USA. I'm 27 years old, I will be 28 in October. I'm currently living with my folks as I work and save up money to move out. My main a source is Rover. I love creating art, i am a graphic novelist and I hope some day soon that will become my main job. I also love to travel and enjoy movies. | R73: No | V73: =IF($A73="","",IF('⚙️ Settings'!$B$1="","",INT(($A73-'⚙️ Settings'!$B$1)/7)+1))
A74: 46224 | B74: Erica | C74: M | D74: Topic 2. That's me | Q74: Hi. I'm Erica from Cincinnati, Ohio, United States. I'm in my upper 40s, single in a condo. I currently work as a receptionist at a pet hospital but am looking for a different office position, more 9 to 5. I like reading, working out, pole dancing, karaoke, and reptiles. | R74: No | V74: =IF($A74="","",IF('⚙️ Settings'!$B$1="","",INT(($A74-'⚙️ Settings'!$B$1)/7)+1))
A75: 46225 | B75: Dawn | C75: T | D75: Topic 2. That's me | Q75: My name is Dawn. I am 62 and single and I live in a house in Huntersville NC. I am semi retired except for part time pet sitting. I love all dogs but especially corgis. I lost my soul dog Lucy in October to lymphoma. | R75: Yes | S75: Photo | V75: =IF($A75="","",IF('⚙️ Settings'!$B$1="","",INT(($A75-'⚙️ Settings'!$B$1)/7)+1))
A76: 46212 | B76: Kristin | C76: T | D76: Topic 3. Me on Rover | Q76: I have been using Rover since 2018. I started using Rover for supplemental income when I was promoted at my full-time job and was no longer receiving overtime. I provide dog- walking, dropin visits and housesitting. Total bookings 1705 Petsitting experience includes pups and kitties to seniors. Medication administering, I love my regulars and meeting new clients. | R76: No | V76: =IF($A76="","",IF('⚙️ Settings'!$B$1="","",INT(($A76-'⚙️ Settings'!$B$1)/7)+1))
A77: 46212 | B77: Deborah | C77: N | D77: Topic 3. Me on Rover | Q77: I recently started using Rover. I started because I sit with my families dogs and love doing it. I do not have a dog of my own any longer. I offer in home sitting for long weekends or extended vacations. I got my first booking within two days of posting my Rover availablity. I've found getting started on Rover easy. The tips on use of the site that were emailed to me later have been timely and helpful | R77: No | V77: =IF($A77="","",IF('⚙️ Settings'!$B$1="","",INT(($A77-'⚙️ Settings'!$B$1)/7)+1))
A78: 46212 | B78: Deborah | C78: N | D78: Topic 3. Me on Rover | Q78: This is Hopper. She is my first Rover client | R78: Yes | S78: Photo | V78: =IF($A78="","",IF('⚙️ Settings'!$B$1="","",INT(($A78-'⚙️ Settings'!$B$1)/7)+1))
A79: 46213 | B79: Tifany | C79: T | D79: Topic 3. Me on Rover | Q79: I started using Rover around July or August of 2023, and I began kind of because of happenstance. My mom had been using Rover for maybe around a year, just as a little side thing (her and her husband are retired, so they don’t really need the money, but something to do), but she had told me about it and that she enjoyed it. Well, coincidentally, a pastor friend of mine was going out of town for 23 days to Jerusalem and had asked me to housesit for them during that time — they told me they could pay me, and I figured it would be nice to have some extra money on top of my job in ministry. I loved it! So, when that job ended, that’s when my mom really encouraged me to apply for the Rover app. And here I am, still working for Rover and even my own business outside of Rover now too. And Rover is what began my side business, Havenly Paws. I kept getting so much word-of-mouth business outside of Rover (neighbors of clients from Rover, church friends, and more) that I started using the Rover app and was busy enough with caring for pets that I also began my own business. Now it’s a wonderful side job for me! Services I offer are: housesitting in their home, boarding pets in my home, drop-ins for all kinds of pets (I’ve even done drop-ins for turtles and iguanas), dog walking, and doggie daycare. My total bookings so far: looks like my booking total is 71 as of today (7/9/26). I have 37 clients on Rover alone, and 12 repeat clients. But I don’t finish the housesitting job I have going for another 2 days, and then I guess I’ll have one more client after that processes:) My petsitting experience has been great so far, over all! I definitely have had some dogs that I would never sit for again, but for the most part, it’s been a really pleasant experience! And I do get a lot of new clients from time to time, but I also have my regulars who I love and they love me. One of my absolute favorite dogs is Boo — I call her “little Boo thang”, and she’s a repeat client’s dog. I always feel bad when I have to say no because I have another booking already. I will say for fun — I love getting new kinds of animals. Farm animals to care for, the turtles and iguanas I mentioned before. And one time I had a client who had a tarantula in a fish tank that I technically didn’t have to care for because there was nothing that needed to be done, but I really enjoy adding it to my list of animals I’ve looked after! | R79: Yes | S79: Photo | V79: =IF($A79="","",IF('⚙️ Settings'!$B$1="","",INT(($A79-'⚙️ Settings'!$B$1)/7)+1))
A80: 46213 | B80: Becky | C80: T | D80: Topic 3. Me on Rover | Q80: I joined Rover in May 2023. After the pandemic, I was stil working from home and was trying to find an easy way to make a little extra money when I was bored. I think I saw an ad for Rover or it was featured in a show or something. So I decided to try it. I offered every available service, and assumed that most people needed help walking their dogs during the day. But it turned out that a lot of folks actually want someone to watch their animials while they are out of town. I rarely get dog walking requests. I average between $10-11k a year. At this point, most of my bookings are repeat doggos but I still get requests from new people fairly regularly. It can just be hard for them to find an opening because I tend to be booked out months in advance. | R80: No | V80: =IF($A80="","",IF('⚙️ Settings'!$B$1="","",INT(($A80-'⚙️ Settings'!$B$1)/7)+1))
A81: 46213 | B81: Becky | C81: T | D81: Topic 3. Me on Rover | Q81: This is me cuddling with one of my regulars on the 4th of July | R81: Yes | S81: Photo | V81: =IF($A81="","",IF('⚙️ Settings'!$B$1="","",INT(($A81-'⚙️ Settings'!$B$1)/7)+1))
A82: 46214 | B82: Joey | C82: M | D82: Topic 3. Me on Rover | Q82: I started using Rover since July 2025 and got my first booking in December 2025. I had guinea pigs for 8 years and they passed away in June 2025. After they passed away, I have more free time that I would love to dedicate to animals. I am huge cat lover as well so I figured out I wanted do some cat sitting. I am also considering owning a cat in the future and I think it is a good way to have a taste of how it’s like to take care of a cat’s routine. On the side I also started to volunteer at a local cat rescue in August 2025 which helps me gaining cat care experience and finally got my first booking in December 2025. I offer drop-in visits for cats and dogs, and also dog walking. I have a total of 19 bookings wi the 8 clients in total so far, and 3 of them are repeat clients. One of the bookings is for dog drop-in visits and the remaining are all drop-in visits for cats. I have received one last-minute request dog walking and have not accepted any dog walking requests. I have two regulars cat clients for drop-ins: one usually booking me for the weekend 1-2 times a month, and another booked me once a month for 3-4 days on average. For dog, I only take smaller dogs, and the only one I did drop-in visits is a senior chihuahua which does not require walking. So far my pet sitting experience is positive, no complaints and everything went well! | R82: No | V82: =IF($A82="","",IF('⚙️ Settings'!$B$1="","",INT(($A82-'⚙️ Settings'!$B$1)/7)+1))
A83: 46214 | B83: Joey | C83: M | D83: Topic 3. Me on Rover | Q83: This is not a picture taken when I’m doing Rover but I guess this represents me well as I adore cats!! | R83: Yes | S83: Photo | V83: =IF($A83="","",IF('⚙️ Settings'!$B$1="","",INT(($A83-'⚙️ Settings'!$B$1)/7)+1))
A84: 46216 | B84: Naomi | C84: M | D84: Topic 3. Me on Rover | Q84: About a year. I used to dogsit for a friend who had 4 dogs and traveled heavily for work. I used to offer day care but now I only offer boarding and sometimes walks. I have been a heavy Booker. Last year I made ~$18k off rover. I had regulars for daycare but I found that they were too much work compared to typical boarding dogs. I am open to new dogs. | R84: No | V84: =IF($A84="","",IF('⚙️ Settings'!$B$1="","",INT(($A84-'⚙️ Settings'!$B$1)/7)+1))
A85: 46216 | B85: Amy | C85: T | D85: Topic 3. Me on Rover | Q85: I created my Rover profile in August of 2025. I love animals and wanted to use what I have learned as a life long dog owner and trained animal shelter volunteer. Being retired gave me more time to interact with animals and having extra income to supplement my pension was attractive. As a kid I always wanted to have lots of dogs- this is my way of having that! I offer drop in visits/dog walking and house sitting. I did get day care/boarding requests early on which I didn't want to commit to since one of my dogs is sometimes "opinionated" with other dogs. I have about 100 bookings since 8/25. I have built up a lot of "regulars". One of them moved, but kindly thanked me before leaving. I have about 14 regular customers. I am currently not accepting new customers. That will change in mid August. I've become very fond of the dogs and cats- sadly 2 of the dogs have passed away since I started 😥 | R85: No | V85: =IF($A85="","",IF('⚙️ Settings'!$B$1="","",INT(($A85-'⚙️ Settings'!$B$1)/7)+1))
A86: 46216 | B86: Amy | C86: T | D86: Topic 3. Me on Rover | Q86: My dogs Sake and Titp | R86: Yes | S86: Photo | V86: =IF($A86="","",IF('⚙️ Settings'!$B$1="","",INT(($A86-'⚙️ Settings'!$B$1)/7)+1))
A87: 46216 | B87: Amy | C87: T | D87: Topic 3. Me on Rover | Q87: Tito | R87: No | V87: =IF($A87="","",IF('⚙️ Settings'!$B$1="","",INT(($A87-'⚙️ Settings'!$B$1)/7)+1))
A88: 46216 | B88: Amy | C88: T | D88: Topic 3. Me on Rover | Q88: My cat Shay | R88: Yes | S88: Photo | V88: =IF($A88="","",IF('⚙️ Settings'!$B$1="","",INT(($A88-'⚙️ Settings'!$B$1)/7)+1))
A89: 46216 | B89: Amy | C89: T | D89: Topic 3. Me on Rover | R89: Yes | S89: Photo | V89: =IF($A89="","",IF('⚙️ Settings'!$B$1="","",INT(($A89-'⚙️ Settings'!$B$1)/7)+1))
A90: 46216 | B90: TR | C90: T | D90: Topic 3. Me on Rover | Q90: I’ve been using Rover since 2023. I started because I always enjoyed taking care of animals, so I figured it was a great idea to make some money from it. I offer drop-ins, boarding and doggy day care. I had 58 total bookings so far. I have my drop-in and boarding regulars, while I still take new clients at the same time. I take cats mostly but I also take dogs too. | R90: No | V90: =IF($A90="","",IF('⚙️ Settings'!$B$1="","",INT(($A90-'⚙️ Settings'!$B$1)/7)+1))
A91: 46216 | B91: TR | C91: T | D91: Topic 3. Me on Rover | R91: Yes | S91: Photo | V91: =IF($A91="","",IF('⚙️ Settings'!$B$1="","",INT(($A91-'⚙️ Settings'!$B$1)/7)+1))
A92: 46216 | B92: Annabelle | C92: N | D92: Topic 3. Me on Rover | Q92: I began using rover in late May, early June. I started because I am a student and needed to supplement my income over the summer while I am not enrolled in classes. I offer dog walking and daily check-ins. I have zero bookings so far. I have previously done overnight dog sitting for a few local people, but not through rover. | R92: No | V92: =IF($A92="","",IF('⚙️ Settings'!$B$1="","",INT(($A92-'⚙️ Settings'!$B$1)/7)+1))
A93: 46216 | B93: Annabelle | C93: N | D93: Topic 3. Me on Rover | R93: Yes | S93: Photo | V93: =IF($A93="","",IF('⚙️ Settings'!$B$1="","",INT(($A93-'⚙️ Settings'!$B$1)/7)+1))
A94: 46216 | B94: Julia | C94: N | D94: Topic 3. Me on Rover | Q94: While I am not new to pet sitting, I am new to using Rover. I have been a sitter on Rover for only about 3 weeks now. I signed up for Rover because our family needed some extra cash and since I have prior experience and a love for animals, I thought this would be a great fit! I offer boarding, doggy day care and drop in visits currently. I have completed one booking so far, with one that is upcoming. My prior pet sitting experience is from watching neighbors/friends/family members pets growing up and in college. All dogs and cats. I had some regular animals I watched over the years when their owners went out of town. Sometimes I stayed at their house, other times their pets stayed at my home. | R94: No | V94: =IF($A94="","",IF('⚙️ Settings'!$B$1="","",INT(($A94-'⚙️ Settings'!$B$1)/7)+1))
A95: 46216 | B95: Julia | C95: N | D95: Topic 3. Me on Rover | R95: Yes | S95: Photo | V95: =IF($A95="","",IF('⚙️ Settings'!$B$1="","",INT(($A95-'⚙️ Settings'!$B$1)/7)+1))
A96: 46217 | B96: Colin | C96: T | D96: Topic 3. Me on Rover | Q96: I started using Rover in February 2025. Our dog at the time, Poncho, was diagnosed with meningitis in the fall of 2024 and sadly passed away a few months later after fighting so hard. We were very obviously devastated to lose Poncho, so we used Rover as a form of therapy for ourselves, a supplemental income, and as a way to spend more time with cute dogs. Our Rover business started slowly with mostly local walks and the occasional boarding. But soon after school ended and families were traveling during summer so we got a lot of boarding and house sitting requests. Altogether we’ve had ~20 different dogs board with us in our home, most for 3-10 day stays. we have had a few dogs stay with us for up to three weeks at a time though. I have also done house sitting about 10 times total but all for repeat clients. because we have our own dog now and live in a smaller apartment, we are only taking boarding requests from previous clients. currently we walk several dogs in the neighborhood and board a dog once every couple months. We also have one family who travel a lot and ask me to house/dog sit while they are away, usually for ~7 days at a time | R96: No | V96: =IF($A96="","",IF('⚙️ Settings'!$B$1="","",INT(($A96-'⚙️ Settings'!$B$1)/7)+1))
A97: 46217 | B97: Colin | C97: T | D97: Topic 3. Me on Rover | Q97: Rover profile pic | R97: Yes | S97: Photo | V97: =IF($A97="","",IF('⚙️ Settings'!$B$1="","",INT(($A97-'⚙️ Settings'!$B$1)/7)+1))
A98: 46217 | B98: Colin | C98: T | D98: Topic 3. Me on Rover | Q98: Two different Rover clients hanging out together | R98: Yes | S98: Photo | V98: =IF($A98="","",IF('⚙️ Settings'!$B$1="","",INT(($A98-'⚙️ Settings'!$B$1)/7)+1))
A99: 46217 | B99: Andrew | C99: T | D99: Topic 3. Me on Rover | Q99: I’ve been using rover since 2024 to make a little cash after getting laid off. I offer boarding and day care services, but it’s almost 100% boarding. I’ve done 50 services with 8 repeat guests, so it’s a pretty even split between regulars and single time users. It’s been pretty chill outside of a couple of incontinent or sick dogs. | R99: No | V99: =IF($A99="","",IF('⚙️ Settings'!$B$1="","",INT(($A99-'⚙️ Settings'!$B$1)/7)+1))
A100: 46217 | B100: Andrew | C100: T | D100: Topic 3. Me on Rover | R100: Yes | S100: Photo | V100: =IF($A100="","",IF('⚙️ Settings'!$B$1="","",INT(($A100-'⚙️ Settings'!$B$1)/7)+1))
A101: 46217 | B101: Caroline | C101: M | D101: Topic 3. Me on Rover | Q101: I started rover July 2025 as I am in a career transition and was taking care of my senior dog. I just offered drop ins and dog walking due to Rocky but now I offer house sitting. I am open to both dogs and cats! I have had 3 completed bookings and numerous requests that I have turned down some due to distance. I have taken care of two dogs and a cat most recently and the a single dog and then two dogs. No regulars yet. I also go to FL in the winter so I change my location for that time and that market is a lot busier than North Carolina. | R101: Yes | S101: Photo | V101: =IF($A101="","",IF('⚙️ Settings'!$B$1="","",INT(($A101-'⚙️ Settings'!$B$1)/7)+1))
A102: 46218 | B102: Rachel | C102: N | D102: Topic 3. Me on Rover | Q102: I haven't used Rover yet but I was approved few weeks ago on the app. I haven't had any bookings because it's been really hard to get visibility. On the Rover app, I offer drop-in visits for cats and small dogs, along with dog walking. I got 1 or 2 recommendations as the app suggests but otherwise I've had no traction. I wanted to use Rover because a lot of my friends recommend it! I thought pet sitting would be a fun/easy way to make some extra money and to get my dog fix, since I don't get to see my childhood dog very often. I have pet sitting experience outside of Rover throughout the years, but I haven't done any petsitting so far through Rover. I was hoping to have some regulars! | R102: No | V102: =IF($A102="","",IF('⚙️ Settings'!$B$1="","",INT(($A102-'⚙️ Settings'!$B$1)/7)+1))
A103: 46218 | B103: Rachel | C103: N | D103: Topic 3. Me on Rover | R103: Yes | S103: Photo | V103: =IF($A103="","",IF('⚙️ Settings'!$B$1="","",INT(($A103-'⚙️ Settings'!$B$1)/7)+1))
A104: 46218 | B104: Bruna | C104: T | D104: Topic 3. Me on Rover | Q104: I have been using Rover since 2021. I initially joined because I was looking for a flexible way to work with dogs and earn additional income. Over time, my interest in dog behaviour became much more serious and eventually developed into my professional career working with dogs. I currently offer dog boarding through Rover. In the past, I have also offered other services, including doggy daycare. So far, I have completed 72 bookings with 48 different clients through the platform. My experience on Rover has been very varied. I have cared for dogs of different breeds, sizes, ages and personalities, and I have both new and repeat clients. Fifteen of my Rover clients have booked with me more than once, so I have also had the opportunity to build longer-term relationships with some of the dogs I care for and become very familiar with their individual routines and personalities. As my knowledge and professional experience in dog behaviour and training have grown, I have also become more comfortable caring for dogs with more complex needs, including fearful, reactive and high-arousal dogs. This has influenced the type of care I provide and how I approach boarding today. | R104: No | V104: =IF($A104="","",IF('⚙️ Settings'!$B$1="","",INT(($A104-'⚙️ Settings'!$B$1)/7)+1))
...

Sheet 🏷️ Tag Taxonomy
A1: TAG TAXONOMY — ROVER DIARY STUDY
A2: Tag Name | B2: Category | C2: Layer | D2: Description
A3: DESCRIPTIVE TAGS
A4: Workflow Area
A5: Relationship management | B5: Workflow Area | C5: Descriptive | D5: Ongoing client retention and nurturing
A6: Scheduling | B6: Workflow Area | C6: Descriptive | D6: Booking and calendar coordination
A7: Communication | B7: Workflow Area | C7: Descriptive | D7: Client-provider messaging
A8: Payments | B8: Workflow Area | C8: Descriptive | D8: Invoicing, rates, payout
A9: Business administration | B9: Workflow Area | C9: Descriptive | D9: Profile, records, reporting
A10: Trust & safety | B10: Workflow Area | C10: Descriptive | D10: Background checks, insurance, incident handling
A11: Client acquisition | B11: Workflow Area | C11: Descriptive | D11: Finding new clients, marketplace browsing
A12: Tool Used
A13: Rover | B13: Tool Used | C13: Descriptive | D13: Native platform action
A14: Google Calendar | B14: Tool Used | C14: Descriptive | D14: External scheduling
A15: Apple Calendar | B15: Tool Used | C15: Descriptive | D15: External scheduling
A16: Spreadsheet | B16: Tool Used | C16: Descriptive | D16: Custom tracking
A17: Text messages | B17: Tool Used | C17: Descriptive | D17: Off-platform comms
A18: WhatsApp | B18: Tool Used | C18: Descriptive | D18: Off-platform comms
A19: Notes app | B19: Tool Used | C19: Descriptive | D19: Personal records
A20: Facebook group | B20: Tool Used | C20: Descriptive | D20: Community/referral
A21: Email | B21: Tool Used | C21: Descriptive | D21: Off-platform comms
A22: Phone call | B22: Tool Used | C22: Descriptive | D22: Off-platform comms
A23: Behavior
A24: Moved communication off-platform | B24: Behavior | C24: Descriptive | D24: Shifted messages to text/WhatsApp/etc.
A25: Used Google Calendar | B25: Behavior | C25: Descriptive | D25: Managed bookings externally
A26: Accepted booking | B26: Behavior | C26: Descriptive | D26: Confirmed a service request
A27: Declined booking | B27: Behavior | C27: Descriptive | D27: Turned down a service request
A28: Created workaround | B28: Behavior | C28: Descriptive | D28: Built a custom solution outside Rover
A29: Contacted client directly | B29: Behavior | C29: Descriptive | D29: Bypassed Rover messaging
A30: Managed schedule externally | B30: Behavior | C30: Descriptive | D30: Primary scheduling not on Rover
A31: Tracked info externally | B31: Behavior | C31: Descriptive | D31: Client notes kept outside platform
A32: Emotion
A33: Confident | B33: Emotion | C33: Descriptive | D33: Provider feels in control and capable
A34: Frustrated | B34: Emotion | C34: Descriptive | D34: Friction causing negative affect
A35: Proud | B35: Emotion | C35: Descriptive | D35: Positive achievement
A36: Overwhelmed | B36: Emotion | C36: Descriptive | D36: Volume or complexity is too much
A37: Uncertain | B37: Emotion | C37: Descriptive | D37: Unclear what to do or expect
A38: Relieved | B38: Emotion | C38: Descriptive | D38: Stress resolved
A39: Excited | B39: Emotion | C39: Descriptive | D39: Positive anticipation
A40: Satisfied | B40: Emotion | C40: Descriptive | D40: Needs met in the moment
A41: DIAGNOSTIC TAGS
A42: Need
A43: Better visibility | B43: Need | C43: Diagnostic | D43: Wants to see more info on platform
A44: Organization | B44: Need | C44: Diagnostic | D44: Wants to manage information better
A45: Guidance | B45: Need | C45: Diagnostic | D45: Needs help navigating a situation
A46: Automation | B46: Need | C46: Diagnostic | D46: Wants repetitive tasks handled automatically
A47: Communication support | B47: Need | C47: Diagnostic | D47: Needs better messaging tools
A48: Client history | B48: Need | C48: Diagnostic | D48: Wants access to past interaction records
A49: Scheduling flexibility | B49: Need | C49: Diagnostic | D49: Needs more control over calendar management
A50: Payment clarity | B50: Need | C50: Diagnostic | D50: Wants transparency on rates/payouts
A51: Friction
A52: Manual work | B52: Friction | C52: Diagnostic | D52: Something that should be automated requires effort
A53: Missing information | B53: Friction | C53: Diagnostic | D53: Needed data is not available in platform
A54: Switching tools | B54: Friction | C54: Diagnostic | D54: Must leave Rover to complete a task
A55: Duplicate work | B55: Friction | C55: Diagnostic | D55: Same task performed in multiple places
A56: Scheduling complexity | B56: Friction | C56: Diagnostic | D56: Calendar coordination is cumbersome
A57: Communication gap | B57: Friction | C57: Diagnostic | D57: Rover messaging is inadequate
A58: Payment delay | B58: Friction | C58: Diagnostic | D58: Payout timing causes issues
A59: Lack of context | B59: Friction | C59: Diagnostic | D59: No client history or background available
A60: Value
A61: Trust | B61: Value | C61: Diagnostic | D61: Platform provides safety or credibility signals
A62: Convenience | B62: Value | C62: Diagnostic | D62: Rover makes a task easier
A63: Demand generation | B63: Value | C63: Diagnostic | D63: Rover brings new clients
A64: Payments | B64: Value | C64: Diagnostic | D64: Rover handles transaction infrastructure
A65: Scheduling | B65: Value | C65: Diagnostic | D65: Rover manages booking logistics
A66: Communication | B66: Value | C66: Diagnostic | D66: Rover facilitates client messaging
A67: Repeat client management | B67: Value | C67: Diagnostic | D67: Rover supports ongoing relationships
A68: Insurance | B68: Value | C68: Diagnostic | D68: Rover provides coverage or protection
A69: Reviews | B69: Value | C69: Diagnostic | D69: Social proof and rating system
A70: STRATEGIC TAGS
A71: Platform Role
A72: Essential | B72: Platform Role | C72: Strategic | D72: Rover is central and irreplaceable in this moment
A73: Helpful | B73: Platform Role | C73: Strategic | D73: Rover adds value but is not the only option
A74: Optional | B74: Platform Role | C74: Strategic | D74: Provider could do this without Rover
A75: Irrelevant | B75: Platform Role | C75: Strategic | D75: Rover is not part of this workflow
A76: Barrier | B76: Platform Role | C76: Strategic | D76: Rover is actively making this harder
A77: Signal
A78: Growing loyalty | B78: Signal | C78: Strategic | D78: Provider increasingly relies on platform
A79: Diversion risk | B79: Signal | C79: Strategic | D79: Provider moving activity off-platform
A80: Professionalization | B80: Signal | C80: Strategic | D80: Provider developing structured business practices
A81: Platform dependence | B81: Signal | C81: Strategic | D81: Provider's business requires Rover
A82: Platform independence | B82: Signal | C82: Strategic | D82: Provider's business could run without Rover
A83: Off-platform migration | B83: Signal | C83: Strategic | D83: Specific workflow fully moved outside
A84: Churn risk | B84: Signal | C84: Strategic | D84: Provider showing signs of leaving
A85: Expansion intent | B85: Signal | C85: Strategic | D85: Provider wants to grow capacity via Rover
A86: Opportunity
A87: Scheduling opportunity | B87: Opportunity | C87: Strategic | D87: Rover could own more of the scheduling flow
A88: Communication opportunity | B88: Opportunity | C88: Strategic | D88: Rover messaging could be more capable
A89: Trust opportunity | B89: Opportunity | C89: Strategic | D89: Rover could provide stronger safety signals
A90: Professionalization opportunity | B90: Opportunity | C90: Strategic | D90: Rover could support business growth
A91: Retention opportunity | B91: Opportunity | C91: Strategic | D91: Rover could do more to deepen loyalty
A92: Automation opportunity | B92: Opportunity | C92: Strategic | D92: Rover could remove manual steps
A93: Visibility opportunity | B93: Opportunity | C93: Strategic | D93: Rover could show providers more useful info
A94: Relationship management opportunity | B94: Opportunity | C94: Strategic | D94: Rover could support repeat client workflows
A95: LIFECYCLE TAGS
A96: Experience Moment
A97: Onboarding & Account creation | B97: Experience Moment | C97: Lifecycle | D97: First-time setup: profile creation, verification, and initial orientation to the platform
A98: Manage account | B98: Experience Moment | C98: Lifecycle | D98: Ongoing upkeep of profile, settings, availability, and listing details
A99: Receive booking | B99: Experience Moment | C99: Lifecycle | D99: Inbound booking requests, offers, and the accept/decline decision
A100: Manage bookings & schedule | B100: Experience Moment | C100: Lifecycle | D100: Coordinating confirmed bookings and calendar logistics across clients
...

Sheet 📊 Summary
A1: SUMMARY DASHBOARD — Use pivot tables to analyse the Entries sheet
A2: HOW TO BUILD PIVOT ANALYSES
A3: 1. Click any cell in the 📋 Entries sheet
A4: 2. Insert → PivotTable → New Worksheet (or Existing Sheet)
A5: 3. Drag fields to Rows, Columns, Values, or Filters
A6: KEY QUESTIONS TO ANSWER
A7: Platform Role by Segment → Rows: Segment | Cols: Platform Role | Values: Count
A8: Workflow Area by Friction → Where are providers struggling most?
A9: Tool Used by Segment → Which tools are providers using outside Rover?
A10: Signal by Week → How does diversion risk evolve over 9 weeks? (See 📅 Weekly Digest tab for a ready-made breakdown)
A11: Emotion by Workflow Area → Where does Rover create/reduce stress?
A12: Opportunity by Platform Role → Where is Rover most irrelevant?
A13: QUICK COUNTS (update these formulas)
A15: Metric | B15: Count
A16: Total entries | B16: =COUNTA('📋 Entries'!A3:A302)
A17: Unique providers | B17: =IFERROR(SUMPRODUCT(1/COUNTIF('📋 Entries'!B3:B302,'📋 Entries'!B3:B302)),0)
A18: Entries flagged as Diversion Risk | B18: =COUNTIF('📋 Entries'!N3:N302,"Diversion risk")
A19: Entries where Platform Role = Barrier | B19: =COUNTIF('📋 Entries'!I3:I302,"Barrier")
A20: Entries where Platform Role = Essential | B20: =COUNTIF('📋 Entries'!I3:I302,"Essential")
A21: Entries with Friction tagged | B21: =COUNTA('📋 Entries'!L3:L302)
A22: Entries with Opportunity tagged | B22: =COUNTA('📋 Entries'!P3:P302)

Sheet 📅 Weekly Digest
A1: WEEKLY DIGEST — auto-updates as entries are logged (requires Study Start Date set in ⚙️ Settings)
A3: Week # | B3: Total Entries | C3: Unique Providers | D3: Platform Role = Essential | E3: Platform Role = Barrier | F3: Signal = Diversion Risk | G3: Signal = Growing Loyalty | H3: Friction Tagged | I3: Opportunity Tagged
A4: 1 | B4: =COUNTIF('📋 Entries'!$V$3:$V$302,$A4) | C4: =IFERROR(SUMPRODUCT((('📋 Entries'!$V$3:$V$302=$A4))/COUNTIFS('📋 Entries'!$B$3:$B$302,'📋 Entries'!$B$3:$B$302&"",'📋 Entries'!$V$3:$V$302,'📋 Entries'!$V$3:$V$302&"")),0) | D4: =COUNTIFS('📋 Entries'!$V$3:$V$302,$A4,'📋 Entries'!$I$3:$I$302,"Essential") | E4: =COUNTIFS('📋 Entries'!$V$3:$V$302,$A4,'📋 Entries'!$I$3:$I$302,"Barrier") | F4: =COUNTIFS('📋 Entries'!$V$3:$V$302,$A4,'📋 Entries'!$N$3:$N$302,"Diversion risk") | G4: =COUNTIFS('📋 Entries'!$V$3:$V$302,$A4,'📋 Entries'!$N$3:$N$302,"Growing loyalty") | H4: =COUNTIFS('📋 Entries'!$V$3:$V$302,$A4,'📋 Entries'!$L$3:$L$302,"<>") | I4: =COUNTIFS('📋 Entries'!$V$3:$V$302,$A4,'📋 Entries'!$P$3:$P$302,"<>")
A5: 2 | B5: =COUNTIF('📋 Entries'!$V$3:$V$302,$A5) | C5: =IFERROR(SUMPRODUCT((('📋 Entries'!$V$3:$V$302=$A5))/COUNTIFS('📋 Entries'!$B$3:$B$302,'📋 Entries'!$B$3:$B$302&"",'📋 Entries'!$V$3:$V$302,'📋 Entries'!$V$3:$V$302&"")),0) | D5: =COUNTIFS('📋 Entries'!$V$3:$V$302,$A5,'📋 Entries'!$I$3:$I$302,"Essential") | E5: =COUNTIFS('📋 Entries'!$V$3:$V$302,$A5,'📋 Entries'!$I$3:$I$302,"Barrier") | F5: =COUNTIFS('📋 Entries'!$V$3:$V$302,$A5,'📋 Entries'!$N$3:$N$302,"Diversion risk") | G5: =COUNTIFS('📋 Entries'!$V$3:$V$302,$A5,'📋 Entries'!$N$3:$N$302,"Growing loyalty") | H5: =COUNTIFS('📋 Entries'!$V$3:$V$302,$A5,'📋 Entries'!$L$3:$L$302,"<>") | I5: =COUNTIFS('📋 Entries'!$V$3:$V$302,$A5,'📋 Entries'!$P$3:$P$302,"<>")
A6: 3 | B6: =COUNTIF('📋 Entries'!$V$3:$V$302,$A6) | C6: =IFERROR(SUMPRODUCT((('📋 Entries'!$V$3:$V$302=$A6))/COUNTIFS('📋 Entries'!$B$3:$B$302,'📋 Entries'!$B$3:$B$302&"",'📋 Entries'!$V$3:$V$302,'📋 Entries'!$V$3:$V$302&"")),0) | D6: =COUNTIFS('📋 Entries'!$V$3:$V$302,$A6,'📋 Entries'!$I$3:$I$302,"Essential") | E6: =COUNTIFS('📋 Entries'!$V$3:$V$302,$A6,'📋 Entries'!$I$3:$I$302,"Barrier") | F6: =COUNTIFS('📋 Entries'!$V$3:$V$302,$A6,'📋 Entries'!$N$3:$N$302,"Diversion risk") | G6: =COUNTIFS('📋 Entries'!$V$3:$V$302,$A6,'📋 Entries'!$N$3:$N$302,"Growing loyalty") | H6: =COUNTIFS('📋 Entries'!$V$3:$V$302,$A6,'📋 Entries'!$L$3:$L$302,"<>") | I6: =COUNTIFS('📋 Entries'!$V$3:$V$302,$A6,'📋 Entries'!$P$3:$P$302,"<>")
A7: 4 | B7: =COUNTIF('📋 Entries'!$V$3:$V$302,$A7) | C7: =IFERROR(SUMPRODUCT((('📋 Entries'!$V$3:$V$302=$A7))/COUNTIFS('📋 Entries'!$B$3:$B$302,'📋 Entries'!$B$3:$B$302&"",'📋 Entries'!$V$3:$V$302,'📋 Entries'!$V$3:$V$302&"")),0) | D7: =COUNTIFS('📋 Entries'!$V$3:$V$302,$A7,'📋 Entries'!$I$3:$I$302,"Essential") | E7: =COUNTIFS('📋 Entries'!$V$3:$V$302,$A7,'📋 Entries'!$I$3:$I$302,"Barrier") | F7: =COUNTIFS('📋 Entries'!$V$3:$V$302,$A7,'📋 Entries'!$N$3:$N$302,"Diversion risk") | G7: =COUNTIFS('📋 Entries'!$V$3:$V$302,$A7,'📋 Entries'!$N$3:$N$302,"Growing loyalty") | H7: =COUNTIFS('📋 Entries'!$V$3:$V$302,$A7,'📋 Entries'!$L$3:$L$302,"<>") | I7: =COUNTIFS('📋 Entries'!$V$3:$V$302,$A7,'📋 Entries'!$P$3:$P$302,"<>")
A8: 5 | B8: =COUNTIF('📋 Entries'!$V$3:$V$302,$A8) | C8: =IFERROR(SUMPRODUCT((('📋 Entries'!$V$3:$V$302=$A8))/COUNTIFS('📋 Entries'!$B$3:$B$302,'📋 Entries'!$B$3:$B$302&"",'📋 Entries'!$V$3:$V$302,'📋 Entries'!$V$3:$V$302&"")),0) | D8: =COUNTIFS('📋 Entries'!$V$3:$V$302,$A8,'📋 Entries'!$I$3:$I$302,"Essential") | E8: =COUNTIFS('📋 Entries'!$V$3:$V$302,$A8,'📋 Entries'!$I$3:$I$302,"Barrier") | F8: =COUNTIFS('📋 Entries'!$V$3:$V$302,$A8,'📋 Entries'!$N$3:$N$302,"Diversion risk") | G8: =COUNTIFS('📋 Entries'!$V$3:$V$302,$A8,'📋 Entries'!$N$3:$N$302,"Growing loyalty") | H8: =COUNTIFS('📋 Entries'!$V$3:$V$302,$A8,'📋 Entries'!$L$3:$L$302,"<>") | I8: =COUNTIFS('📋 Entries'!$V$3:$V$302,$A8,'📋 Entries'!$P$3:$P$302,"<>")
A9: 6 | B9: =COUNTIF('📋 Entries'!$V$3:$V$302,$A9) | C9: =IFERROR(SUMPRODUCT((('📋 Entries'!$V$3:$V$302=$A9))/COUNTIFS('📋 Entries'!$B$3:$B$302,'📋 Entries'!$B$3:$B$302&"",'📋 Entries'!$V$3:$V$302,'📋 Entries'!$V$3:$V$302&"")),0) | D9: =COUNTIFS('📋 Entries'!$V$3:$V$302,$A9,'📋 Entries'!$I$3:$I$302,"Essential") | E9: =COUNTIFS('📋 Entries'!$V$3:$V$302,$A9,'📋 Entries'!$I$3:$I$302,"Barrier") | F9: =COUNTIFS('📋 Entries'!$V$3:$V$302,$A9,'📋 Entries'!$N$3:$N$302,"Diversion risk") | G9: =COUNTIFS('📋 Entries'!$V$3:$V$302,$A9,'📋 Entries'!$N$3:$N$302,"Growing loyalty") | H9: =COUNTIFS('📋 Entries'!$V$3:$V$302,$A9,'📋 Entries'!$L$3:$L$302,"<>") | I9: =COUNTIFS('📋 Entries'!$V$3:$V$302,$A9,'📋 Entries'!$P$3:$P$302,"<>")
A10: 7 | B10: =COUNTIF('📋 Entries'!$V$3:$V$302,$A10) | C10: =IFERROR(SUMPRODUCT((('📋 Entries'!$V$3:$V$302=$A10))/COUNTIFS('📋 Entries'!$B$3:$B$302,'📋 Entries'!$B$3:$B$302&"",'📋 Entries'!$V$3:$V$302,'📋 Entries'!$V$3:$V$302&"")),0) | D10: =COUNTIFS('📋 Entries'!$V$3:$V$302,$A10,'📋 Entries'!$I$3:$I$302,"Essential") | E10: =COUNTIFS('📋 Entries'!$V$3:$V$302,$A10,'📋 Entries'!$I$3:$I$302,"Barrier") | F10: =COUNTIFS('📋 Entries'!$V$3:$V$302,$A10,'📋 Entries'!$N$3:$N$302,"Diversion risk") | G10: =COUNTIFS('📋 Entries'!$V$3:$V$302,$A10,'📋 Entries'!$N$3:$N$302,"Growing loyalty") | H10: =COUNTIFS('📋 Entries'!$V$3:$V$302,$A10,'📋 Entries'!$L$3:$L$302,"<>") | I10: =COUNTIFS('📋 Entries'!$V$3:$V$302,$A10,'📋 Entries'!$P$3:$P$302,"<>")
A11: 8 | B11: =COUNTIF('📋 Entries'!$V$3:$V$302,$A11) | C11: =IFERROR(SUMPRODUCT((('📋 Entries'!$V$3:$V$302=$A11))/COUNTIFS('📋 Entries'!$B$3:$B$302,'📋 Entries'!$B$3:$B$302&"",'📋 Entries'!$V$3:$V$302,'📋 Entries'!$V$3:$V$302&"")),0) | D11: =COUNTIFS('📋 Entries'!$V$3:$V$302,$A11,'📋 Entries'!$I$3:$I$302,"Essential") | E11: =COUNTIFS('📋 Entries'!$V$3:$V$302,$A11,'📋 Entries'!$I$3:$I$302,"Barrier") | F11: =COUNTIFS('📋 Entries'!$V$3:$V$302,$A11,'📋 Entries'!$N$3:$N$302,"Diversion risk") | G11: =COUNTIFS('📋 Entries'!$V$3:$V$302,$A11,'📋 Entries'!$N$3:$N$302,"Growing loyalty") | H11: =COUNTIFS('📋 Entries'!$V$3:$V$302,$A11,'📋 Entries'!$L$3:$L$302,"<>") | I11: =COUNTIFS('📋 Entries'!$V$3:$V$302,$A11,'📋 Entries'!$P$3:$P$302,"<>")
A12: 9 | B12: =COUNTIF('📋 Entries'!$V$3:$V$302,$A12) | C12: =IFERROR(SUMPRODUCT((('📋 Entries'!$V$3:$V$302=$A12))/COUNTIFS('📋 Entries'!$B$3:$B$302,'📋 Entries'!$B$3:$B$302&"",'📋 Entries'!$V$3:$V$302,'📋 Entries'!$V$3:$V$302&"")),0) | D12: =COUNTIFS('📋 Entries'!$V$3:$V$302,$A12,'📋 Entries'!$I$3:$I$302,"Essential") | E12: =COUNTIFS('📋 Entries'!$V$3:$V$302,$A12,'📋 Entries'!$I$3:$I$302,"Barrier") | F12: =COUNTIFS('📋 Entries'!$V$3:$V$302,$A12,'📋 Entries'!$N$3:$N$302,"Diversion risk") | G12: =COUNTIFS('📋 Entries'!$V$3:$V$302,$A12,'📋 Entries'!$N$3:$N$302,"Growing loyalty") | H12: =COUNTIFS('📋 Entries'!$V$3:$V$302,$A12,'📋 Entries'!$L$3:$L$302,"<>") | I12: =COUNTIFS('📋 Entries'!$V$3:$V$302,$A12,'📋 Entries'!$P$3:$P$302,"<>")
A13: Total | B13: =SUM(B4:B12) | C13: see Summary tab | D13: =SUM(D4:D12) | E13: =SUM(E4:E12) | F13: =SUM(F4:F12) | G13: =SUM(G4:G12) | H13: =SUM(H4:H12) | I13: =SUM(I4:I12)

Sheet 👤 Participants
A1: PARTICIPANT TRACKER
A2: User Name | B2: Segment | C2: Start Date | D2: End Date | E2: Notes
A3: Richard | B3: M | C3: 46217
A4: Shania | B4: T | C4: 46217
A5: Kristin | B5: T | C5: 46212
A6: Tifany | B6: T | C6: 46212
A7: Deborah | B7: N | C7: 46212
A8: Joey | B8: M | C8: 46213
A9: Becky | B9: T | C9: 46213
A10: Annabelle | B10: N | C10: 46214
A11: Naomi | B11: M | C11: 46214
A12: Amy | B12: T | C12: 46216
A13: Colin | B13: T | C13: 46217
A14: Caroline | B14: M | C14: 46217
... A35: Dawn | B35: T | C35: 46225
